Workbook
Name Colo: #REF!
Name Data: #REF!
Name Features: #REF!
Name Functional: #REF!
Name General: #REF!
Name intEstimateVolume: 'Demand Requests'!$N$4
Name intEstimateVolume: 'Demand Requests'!$N$4
Name Non_Functional: #REF!
Name Non_Technical: #REF!
Name percPreTargetAdjustment: 'Monthly Recurring Charges'!$AP$3
Name percPreTargetAdjustment: 'Monthly Recurring Charges'!$AP$3
Name Relative: #REF!
Name Technical: #REF!

Sheet introduction
B1: Schedule 5.A (Pricing Sheet) – introduction
B4: This document lists Pricing for the items set out.
B6: Worksheet | C6: Description | D6: Charges
B7: Summary | C7: Overview of the Charges prognosed | D7: Total
B8: Monthly Recurring Charges | C8: Prices that are repetitive, often based on measured volumes | D8: MRC
B9: RU info | C9: Resource Unit measurement and baseline bands | D9: MRC
B10: RU mapping | C10: Show which sections of which service description are covered under which resource units – note that documents other than the referenced service descriptions also contain obligations. | D10: MRC
B11: Devices | C11: Local pricing for laptops, desktops, and printers | D11: MRC
B12: One-time Charges | C12: Prices that are paid once for every execution of an item | D12: OTC
B13: Service Requests | C13: One-time Charges for selected standard changes | D13: OTC
B14: Demand Requests | C14: Hourly Rates for Projects and other work | D14: OTC
B19: Attachment to the: | C19: Schedule 5 (Service Pricing)
B20: of the: | C20: Technology Services
B21: between: | C21: Koninklijke Douwe Egberts B.V.
B22: and: | C22: HCL Technologies B V
B23: Classification: | C23: Confidential Information

Sheet Summary
A1: Schedule 5.A (Pricing Sheet) – Summary
B4: Area | D4: Year 01 | E4: Year 02 | F4: Year 03 | G4: Year 04 | H4: Year 05 | I4: Total | J4: Remarks
B6: Monthly Recurring Charges
C7: Service Integration and Management (SIAM) | D7: ='Monthly Recurring Charges'!AX8 -> 482083.4 | E7: ='Monthly Recurring Charges'!AY8 -> 818164.4 | F7: ='Monthly Recurring Charges'!AZ8 -> 793619.47 | G7: ='Monthly Recurring Charges'!BA8 -> 769810.88 | H7: ='Monthly Recurring Charges'!BB8 -> 746716.56 | I7: =SUM(D7:H7) -> 3610394.7
C8: Service Desk Services (SDS) | D8: ='Monthly Recurring Charges'!AX11 -> 375947.96 | E8: ='Monthly Recurring Charges'!AY11 -> 618702.92 | F8: ='Monthly Recurring Charges'!AZ11 -> 587767.78 | G8: ='Monthly Recurring Charges'!BA11 -> 558379.39 | H8: ='Monthly Recurring Charges'!BB11 -> 530460.42 | I8: =SUM(D8:H8) -> 2671258.5
C9: Workplace Services (WPS) | D9: ='Monthly Recurring Charges'!AX18 -> 1959711.2 | E9: ='Monthly Recurring Charges'!AY18 -> 3225124.7 | F9: ='Monthly Recurring Charges'!AZ18 -> 3027947.7 | G9: ='Monthly Recurring Charges'!BA18 -> 2876550.3 | H9: ='Monthly Recurring Charges'!BB18 -> 2732722.8 | I9: =SUM(D9:H9) -> 13822057
C10: Devices | D10: =Devices!G86 -> 1209499.7 | E10: =Devices!H86 -> 2008751.5 | F10: =Devices!I86 -> 2391385.6 | G10: =Devices!J86 -> 3025907.2 | H10: =Devices!K86 -> 3108123.5 | I10: =SUM(D10:H10) -> 11743668
C11: Cloud and Infrastructure Services (CIS) | D11: ='Monthly Recurring Charges'!AX29 -> 210944.85 | E11: ='Monthly Recurring Charges'!AY29 -> 347154.95 | F11: ='Monthly Recurring Charges'!AZ29 -> 297411.49 | G11: ='Monthly Recurring Charges'!BA29 -> 282540.91 | H11: ='Monthly Recurring Charges'!BB29 -> 268413.87 | I11: =SUM(D11:H11) -> 1406466.1
C12: Operational Technology Services (OTS) | D12: ='Monthly Recurring Charges'!AX39 -> 659134.54 | E12: ='Monthly Recurring Charges'!AY39 -> 1088781.9 | F12: ='Monthly Recurring Charges'!AZ39 -> 1034342.8 | G12: ='Monthly Recurring Charges'!BA39 -> 982625.63 | H12: ='Monthly Recurring Charges'!BB39 -> 933494.34 | I12: =SUM(D12:H12) -> 4698379.1
C13: Security Services (SEC) | D13: ='Monthly Recurring Charges'!AX58 -> 412009.47 | E13: ='Monthly Recurring Charges'!AY58 -> 678049.88 | F13: ='Monthly Recurring Charges'!AZ58 -> 644147.38 | G13: ='Monthly Recurring Charges'!BA58 -> 611940.01 | H13: ='Monthly Recurring Charges'!BB58 -> 581343.01 | I13: =SUM(D13:H13) -> 2927489.8
C14: Options | D14: ='Monthly Recurring Charges'!AX7 -> 125601.37 | E14: ='Monthly Recurring Charges'!AY7 -> 206703.97 | F14: ='Monthly Recurring Charges'!AZ7 -> 244328.92 | G14: ='Monthly Recurring Charges'!BA7 -> 233447.17 | H14: ='Monthly Recurring Charges'!BB7 -> 223109.52 | I14: =SUM(D14:H14) -> 1033190.9
C15: Subtotal | D15: =SUM(D7:D14) -> 5434932.5 | E15: =SUM(E7:E14) -> 8991434.2 | F15: =SUM(F7:F14) -> 9020951.1 | G15: =SUM(G7:G14) -> 9341201.5 | H15: =SUM(H7:H14) -> 9124384 | I15: =SUM(I7:I14) -> 41912903
B17: One-time Charges | I17: =I15+I26 -> 42504341
C18: ='One-time Charges'!B8 -> Transition and Transformation
C19: ='One-time Charges'!C10 -> Transition | D19: ='One-time Charges'!H10 -> 0 | E19: ='One-time Charges'!I10 -> 0 | F19: ='One-time Charges'!J10 -> 0 | G19: ='One-time Charges'!K10 -> 0 | H19: ='One-time Charges'!L10 -> 0 | I19: =SUM(D19:H19) -> 0
C20: ='One-time Charges'!C24 -> Transformation | D20: ='One-time Charges'!H24 -> 0 | E20: ='One-time Charges'!I24 -> 365488.94 | F20: ='One-time Charges'!J24 -> 365488.94 | G20: ='One-time Charges'!K24 -> 365488.94 | H20: ='One-time Charges'!L24 -> 365488.94 | I20: =SUM(D20:H20) -> 1461955.7
C21: ='One-time Charges'!C45 -> Other – In-flight Projects or future Projects | D21: ='One-time Charges'!H45 -> 0 | E21: ='One-time Charges'!I45 -> 131220.05 | F21: ='One-time Charges'!J45 -> 131220.05 | G21: ='One-time Charges'!K45 -> 131220.05 | H21: ='One-time Charges'!L45 -> 454449.46 | I21: =SUM(D21:H21) -> 848109.61
C22: ='One-time Charges'!C51 -> Transfer of Assets | D22: ='One-time Charges'!H51 -> 0 | E22: ='One-time Charges'!I51 -> 0 | F22: ='One-time Charges'!J51 -> 0 | G22: ='One-time Charges'!K51 -> 0 | H22: ='One-time Charges'!L51 -> 0 | I22: =SUM(D22:H22) -> 0
C23: Options | D23: ='One-time Charges'!H9 -> 0 | E23: ='One-time Charges'!I9 -> 0 | F23: ='One-time Charges'!J9 -> 233172.15 | G23: ='One-time Charges'!K9 -> 0 | H23: ='One-time Charges'!L9 -> 0 | I23: =SUM(D23:H23) -> 233172.15
C24: Subtotal | D24: =SUM(D19:D23) -> 0 | E24: =SUM(E19:E23) -> 496708.99 | F24: =SUM(F19:F23) -> 729881.14 | G24: =SUM(G19:G23) -> 496708.99 | H24: =SUM(H19:H23) -> 819938.4 | I24: =SUM(D24:H24) -> 2543237.5
C26: Service Requests | D26: ='Service Requests'!I34 -> 118287.47 | E26: ='Service Requests'!J34 -> 118287.47 | F26: ='Service Requests'!K34 -> 118287.47 | G26: ='Service Requests'!L34 -> 118287.47 | H26: ='Service Requests'!M34 -> 118287.47 | I26: =SUM(D26:H26) -> 591437.33 | J26: at estimated volume
C28: Demand Requests | D28: ='Demand Requests'!N109 -> 299497.9 | E28: =D28 -> 299497.9 | F28: =E28 -> 299497.9 | G28: =F28 -> 299497.9 | H28: =G28 -> 299497.9 | I28: =SUM(D28:H28) -> 1497489.5 | J28: at estimated volume
C30: Exit
C31: ='One-time Charges'!B67 -> Termination for Convenience Fee | D31: ='One-time Charges'!H67 -> 6634171.3 | E31: ='One-time Charges'!I67 -> 10362539 | F31: ='One-time Charges'!J67 -> 8904112.2 | G31: ='One-time Charges'!K67 -> 7049765.8 | H31: ='One-time Charges'!L67 -> 4020820.4 | I31: =SUM(D31:H31) -> 36971409 | J31: Excluded from total
C32: ='One-time Charges'!B78 -> Remaining value Sole-use Assets | D32: =SUM('One-time Charges'!H78:H78) -> 0 | E32: =SUM('One-time Charges'!I78:I79) -> 0 | F32: =SUM('One-time Charges'!J78:J79) -> 0 | G32: =SUM('One-time Charges'!K78:K79) -> 0 | H32: =SUM('One-time Charges'!L78:L79) -> 0 | I32: =SUM(D32:H32) -> 0 | J32: Last year of Term included in total
C33: ='One-time Charges'!B93 -> Exit Assistance | D33: ='One-time Charges'!H93 -> 629264.84 | E33: ='One-time Charges'!I93 -> 629264.84 | F33: ='One-time Charges'!J93 -> 629264.84 | G33: ='One-time Charges'!K93 -> 629264.84 | H33: ='One-time Charges'!L93 -> 629264.84 | I33: =SUM(D33:H33) -> 3146324.2 | J33: Last year of Term included in total
C34: Options | D34: ='One-time Charges'!H104 -> 0 | E34: ='One-time Charges'!I22 -> 0 | F34: ='One-time Charges'!J22 -> 0 | G34: ='One-time Charges'!K22 -> 0 | H34: ='One-time Charges'!L22 -> 0 | I34: =SUM(D34:H34) -> 0 | J34: Last year of Term included in total
C35: Subtotal | D35: =SUM(D31:D34) -> 7263436.1 | E35: =SUM(E31:E34) -> 10991804 | F35: =SUM(F31:F34) -> 9533377.1 | G35: =SUM(G31:G34) -> 7679030.6 | H35: =SUM(H31:H34) -> 4650085.3 | I35: =SUM(D35:H35) -> 40117733
B38: Total Agreement Value | D38: Year 01 | E38: Year 02 | F38: Year 03 | G38: Year 04 | H38: Year 05 | I38: Total
C39: Total | D39: =D15+D24+D26+D28 -> 5852717.8 | E39: =E15+E24+E26+E28 -> 9905928.5 | F39: =F15+F24+F26+F28 -> 10168618 | G39: =G15+G24+G26+G28 -> 10255696 | H39: =H15+H24+H26+H28+H32+H33+H34 -> 10991373 | I39: =SUM(D39:H39) -> 47174332 | J39: At forecasted Baseline Quantities
C40: Without Options | D40: =D39-D14-D23 -> 5727116.5 | E40: =E39-E14-E23 -> 9699224.6 | F40: =F39-F14-F23 -> 9691116.5 | G40: =G39-G14-G23 -> 10022249 | H40: =H39-H14-H23-H35 -> 6118177.9 | I40: =SUM(I7:I13,I19:I22,I26,I28,I32:I33)-'One-time Charges'!M79 -> 48425029
J41: Total = Recurring Charges + these One-time Charges: • Transition and Transformation • Service Requests • Demand Requests • Remaining value Sole-use Assets • Exit Assistance

Sheet Monthly Recurring Charges
A1: Schedule 5.A (Pricing Sheet) – Monthly Recurring Charges (MRC)
BD2: =BD3/BD5 -> 2.0354609
AO3: Interim Services Unit Price Adjustment | BD3: =SUBTOTAL(9,BD6:BD63) -> 59305281
B4: Operational Services Domain | H4: € | I4: Monthly Unit Price | N4: # | O4: Baseline Quantity forecast | AP4: Service Start Date (month # after Agreement Start Date) | AQ4: Σ# | AW4: Σ€ | AX4: Forecasted Charges | BE4: i
C5: Service Component | P5: Year 01 month | AC5: Year 02 month | AR5: Y1+Y2 are averages, may show ramp-up | AX5: =AX8+AX11+AX18+AX29+AX39+AX58 -> 4099831.4 | AY5: =AY8+AY11+AY18+AY29+AY39+AY58 -> 6775978.7 | AZ5: =AZ8+AZ11+AZ18+AZ29+AZ39+AZ58 -> 6385236.6 | BA5: =BA8+BA11+BA18+BA29+BA39+BA58 -> 6081847.1 | BB5: =BB8+BB11+BB18+BB29+BB39+BB58 -> 5793151 | BD5: =BD8+BD11+BD18+BD29+BD39+BD58 -> 29136045
D6: Resource Unit | E6: Invoicing | F6: Baseline band | G6: Option | I6: Year 01 | J6: Year 02 | K6: Year 03 | L6: Year 04 | M6: Year 05 | O6: Current | P6: 1 | Q6: 2 | R6: 3 | S6: 4 | T6: 5 | U6: 6 | V6: 7 | W6: 8 | X6: 9 | Y6: 10 | Z6: 11 | AA6: 12 | AC6: 1 | AD6: 2 | AE6: 3 | AF6: 4 | AG6: 5 | AH6: 6 | AI6: 7 | AJ6: 8 | AK6: 9 | AL6: 10 | AM6: 11 | AN6: 12 | AR6: Year 01 | AS6: Year 02 | AT6: Year 03 | AU6: Year 04 | AV6: Year 05 | AX6: Year 01 | AY6: Year 02 | AZ6: Year 03 | BA6: Year 04 | BB6: Year 05 | BD6: Total | BF6: Remarks | BG6: Data source (indicative only, to be validated during Transition)'
P7: 1 | Q7: =P7+1 -> 2 | R7: =Q7+1 -> 3 | S7: =R7+1 -> 4 | T7: =S7+1 -> 5 | U7: =T7+1 -> 6 | V7: =U7+1 -> 7 | W7: =V7+1 -> 8 | X7: =W7+1 -> 9 | ... AA7: =Z7+1 -> 12 | AC7: =AA7+1 -> 13 | AD7: =AC7+1 -> 14 | AE7: =AD7+1 -> 15 | AF7: =AE7+1 -> 16 | AG7: =AF7+1 -> 17 | AH7: =AG7+1 -> 18 | AI7: =AH7+1 -> 19 | AJ7: =AI7+1 -> 20 | AK7: =AJ7+1 -> 21 | ... AN7: =AM7+1 -> 24 | AT7: 12 | AU7: 12 | AV7: 12 | AX7: =SUMIFS(AX8:AX63,$G8:$G63,"Option") -> 125601.37 | AY7: =SUMIFS(AY8:AY63,$G8:$G63,"Option") -> 206703.97 | AZ7: =SUMIFS(AZ8:AZ63,$G8:$G63,"Option") -> 244328.92 | BA7: =SUMIFS(BA8:BA63,$G8:$G63,"Option") -> 233447.17 | BB7: =SUMIFS(BB8:BB63,$G8:$G63,"Option") -> 223109.52 | BF7: Total of Options
B8: Service Integration and Management (SIAM) | P8: =IF(P$7<$AP$8,percPreTargetAdjustment,0%) -> 0 | Q8: =IF(Q$7<$AP$8,percPreTargetAdjustment,0%) -> 0 | R8: =IF(R$7<$AP$8,percPreTargetAdjustment,0%) -> 0 | S8: =IF(S$7<$AP$8,percPreTargetAdjustment,0%) -> 0 | T8: =IF(T$7<$AP$8,percPreTargetAdjustment,0%) -> 0 | U8: =IF(U$7<$AP$8,percPreTargetAdjustment,0%) -> 0 | V8: =IF(V$7<$AP$8,percPreTargetAdjustment,0%) -> 0 | W8: =IF(W$7<$AP$8,percPreTargetAdjustment,0%) -> 0 | ... AA8: =IF(AA$7<$AP$8,percPreTargetAdjustment,0%) -> 0 | AC8: =IF(AC$7<$AP$8,percPreTargetAdjustment,0%) -> 0 | AD8: =IF(AD$7<$AP$8,percPreTargetAdjustment,0%) -> 0 | AE8: =IF(AE$7<$AP$8,percPreTargetAdjustment,0%) -> 0 | AF8: =IF(AF$7<$AP$8,percPreTargetAdjustment,0%) -> 0 | AG8: =IF(AG$7<$AP$8,percPreTargetAdjustment,0%) -> 0 | AH8: =IF(AH$7<$AP$8,percPreTargetAdjustment,0%) -> 0 | AI8: =IF(AI$7<$AP$8,percPreTargetAdjustment,0%) -> 0 | AJ8: =IF(AJ$7<$AP$8,percPreTargetAdjustment,0%) -> 0 | ... AN8: =IF(AN$7<$AP$8,percPreTargetAdjustment,0%) -> 0 | AP8: 8 | AX8: =SUMIFS(AX9:AX10,$G9:$G10,"<>Option") -> 482083.4 | AY8: =SUMIFS(AY9:AY10,$G9:$G10,"<>Option") -> 818164.4 | AZ8: =SUMIFS(AZ9:AZ10,$G9:$G10,"<>Option") -> 793619.47 | BA8: =SUMIFS(BA9:BA10,$G9:$G10,"<>Option") -> 769810.88 | BB8: =SUMIFS(BB9:BB10,$G9:$G10,"<>Option") -> 746716.56 | BD8: =SUM(AX8:BB8) -> 3610394.7 | BF8: Domain totals exclude Options
C9: Service Integration and Management | D9: Fixed monthly | E9: central | F9: n/a | I9: 68869.057 | J9: 68180.367 | K9: 66134.956 | L9: 64150.907 | M9: 62226.38 | O9: 1 | U9: =$O$9 -> 1 | V9: =$O$9 -> 1 | W9: =$O$9 -> 1 | X9: =$O$9 -> 1 | Y9: =$O$9 -> 1 | Z9: =$O$9 -> 1 | AA9: =$O$9 -> 1 | AC9: =$O$9 -> 1 | AD9: =$O$9 -> 1 | AE9: =$O$9 -> 1 | AF9: =$O$9 -> 1 | AG9: =$O$9 -> 1 | AH9: =$O$9 -> 1 | AI9: =$O$9 -> 1 | AJ9: =$O$9 -> 1 | ... AN9: =$O$9 -> 1 | AR9: =IFERROR(AVERAGE(P9:AA9),0) -> 1 | AS9: =IFERROR(AVERAGE(AC9:AN9),0) -> 1 | AT9: =O9 -> 1 | AU9: =AT9 -> 1 | AV9: =AU9 -> 1 | AX9: =P9*(I9*(100%+P$8))+Q9*(I9*(100%+Q$8))+R9*(I9*(100%+R$8))+S9*(I9*(100%+S$8))+T9*(I9*(100%+T$8))+U9*(I9*(100%+U$8))+V9*(I9*(100%+V$8))+W9*(I9*(100%+W$8))+X9*(I9*(100%+X$8))+Y9*(I9*(100%+Y$8))+Z9*(I9*(100%+Z$8))+AA9*(I9*(100%+AA$8)) -> 482083.4 | AY9: =AC9*(J9*(100%+AC$8))+AD9*(J9*(100%+AD$8))+AE9*(J9*(100%+AE$8))+AF9*(J9*(100%+AF$8))+AG9*(J9*(100%+AG$8))+AH9*(J9*(100%+AH$8))+AI9*(J9*(100%+AI$8))+AJ9*(J9*(100%+AJ$8))+AK9*(J9*(100%+AK$8))+AL9*(J9*(100%+AL$8))+AM9*(J9*(100%+AM$8))+AN9*(J9*(100%+AN$8)) -> 818164.4 | AZ9: =K9*AT9*AT$7 -> 793619.47 | BA9: =L9*AU9*AU$7 -> 769810.88 | BB9: =M9*AV9*AV$7 -> 746716.56 | BD9: =SUM(AX9:BB9) -> 3610394.7 | BF9: Baseline band: +/- 2 Service Providers in Attachment 3.B3.L (Integrated Service Providers)
B11: Service Desk Services (SDS) | P11: =IF(P$7<$AP$11,percPreTargetAdjustment,0%) -> 0 | Q11: =IF(Q$7<$AP$11,percPreTargetAdjustment,0%) -> 0 | R11: =IF(R$7<$AP$11,percPreTargetAdjustment,0%) -> 0 | S11: =IF(S$7<$AP$11,percPreTargetAdjustment,0%) -> 0 | T11: =IF(T$7<$AP$11,percPreTargetAdjustment,0%) -> 0 | U11: =IF(U$7<$AP$11,percPreTargetAdjustment,0%) -> 0 | V11: =IF(V$7<$AP$11,percPreTargetAdjustment,0%) -> 0 | W11: =IF(W$7<$AP$11,percPreTargetAdjustment,0%) -> 0 | ... AA11: =IF(AA$7<$AP$11,percPreTargetAdjustment,0%) -> 0 | AC11: =IF(AC$7<$AP$11,percPreTargetAdjustment,0%) -> 0 | AD11: =IF(AD$7<$AP$11,percPreTargetAdjustment,0%) -> 0 | AE11: =IF(AE$7<$AP$11,percPreTargetAdjustment,0%) -> 0 | AF11: =IF(AF$7<$AP$11,percPreTargetAdjustment,0%) -> 0 | AG11: =IF(AG$7<$AP$11,percPreTargetAdjustment,0%) -> 0 | AH11: =IF(AH$7<$AP$11,percPreTargetAdjustment,0%) -> 0 | AI11: =IF(AI$7<$AP$11,percPreTargetAdjustment,0%) -> 0 | AJ11: =IF(AJ$7<$AP$11,percPreTargetAdjustment,0%) -> 0 | ... AN11: =IF(AN$7<$AP$11,percPreTargetAdjustment,0%) -> 0 | AX11: =SUMIFS(AX12:AX17,$G12:$G17,"<>Option") -> 375947.96 | AY11: =SUMIFS(AY12:AY17,$G12:$G17,"<>Option") -> 618702.92 | AZ11: =SUMIFS(AZ12:AZ17,$G12:$G17,"<>Option") -> 587767.78 | BA11: =SUMIFS(BA12:BA17,$G12:$G17,"<>Option") -> 558379.39 | BB11: =SUMIFS(BB12:BB17,$G12:$G17,"<>Option") -> 530460.42 | BD11: =SUM(AX11:BB11) -> 2671258.5
C12: Standard | D12: User | E12: central | F12: normal | I12: 3.3566782 | J12: 3.222411 | K12: 3.0612905 | L12: 2.908226 | M12: 2.7628147 | O12: 16000 | U12: =$O$12 -> 16000 | V12: =$O$12 -> 16000 | W12: =$O$12 -> 16000 | X12: =$O$12 -> 16000 | Y12: =$O$12 -> 16000 | Z12: =$O$12 -> 16000 | AA12: =$O$12 -> 16000 | AC12: =$O$12 -> 16000 | AD12: =$O$12 -> 16000 | AE12: =$O$12 -> 16000 | AF12: =$O$12 -> 16000 | AG12: =$O$12 -> 16000 | AH12: =$O$12 -> 16000 | AI12: =$O$12 -> 16000 | AJ12: =$O$12 -> 16000 | ... AN12: =$O$12 -> 16000 | AR12: =IFERROR(AVERAGE(P12:AA12),0) -> 16000 | AS12: =IFERROR(AVERAGE(AC12:AN12),0) -> 16000 | AT12: =O12 -> 16000 | AU12: =AT12 -> 16000 | AV12: =AU12 -> 16000 | AX12: =P12*(I12*(100%+P$11))+Q12*(I12*(100%+Q$11))+R12*(I12*(100%+R$11))+S12*(I12*(100%+S$11))+T12*(I12*(100%+T$11))+U12*(I12*(100%+U$11))+V12*(I12*(100%+V$11))+W12*(I12*(100%+W$11))+X12*(I12*(100%+X$11))+Y12*(I12*(100%+Y$11))+Z12*(I12*(100%+Z$11))+AA12*(I12*(100%+AA$11)) -> 375947.96 | AY12: =AC12*(J12*(100%+AC$11))+AD12*(J12*(100%+AD$11))+AE12*(J12*(100%+AE$11))+AF12*(J12*(100%+AF$11))+AG12*(J12*(100%+AG$11))+AH12*(J12*(100%+AH$11))+AI12*(J12*(100%+AI$11))+AJ12*(J12*(100%+AJ$11))+AK12*(J12*(100%+AK$11))+AL12*(J12*(100%+AL$11))+AM12*(J12*(100%+AM$11))+AN12*(J12*(100%+AN$11)) -> 618702.92 | AZ12: =K12*AT12*AT$7 -> 587767.78 | BA12: =L12*AU12*AU$7 -> 558379.39 | BB12: =M12*AV12*AV$7 -> 530460.42 | BD12: =SUM(AX12:BB12) -> 2671258.5 | BF12: Users in a country that may have a local-language add-on are counted too | BG12: Users File: Account Type "User" + "Generic"
C13: Brazilian Portuguese | D13: Fixed monthly | E13: local | F13: normal | G13: Option | I13: 4366.9152 | J13: 4192.2386 | K13: 3982.6267 | L13: 3783.4953 | M13: 3594.3206 | O13: 1 | U13: =$O$13 -> 1 | V13: =$O$13 -> 1 | W13: =$O$13 -> 1 | X13: =$O$13 -> 1 | Y13: =$O$13 -> 1 | Z13: =$O$13 -> 1 | AA13: =$O$13 -> 1 | AC13: =$O$13 -> 1 | AD13: =$O$13 -> 1 | AE13: =$O$13 -> 1 | AF13: =$O$13 -> 1 | AG13: =$O$13 -> 1 | AH13: =$O$13 -> 1 | AI13: =$O$13 -> 1 | AJ13: =$O$13 -> 1 | ... AN13: =$O$13 -> 1 | AR13: =IFERROR(AVERAGE(P13:AA13),0) -> 1 | AS13: =IFERROR(AVERAGE(AC13:AN13),0) -> 1 | AT13: =O13 -> 1 | AU13: =AT13 -> 1 | AV13: =AU13 -> 1 | AX13: =P13*(I13*(100%+P$11))+Q13*(I13*(100%+Q$11))+R13*(I13*(100%+R$11))+S13*(I13*(100%+S$11))+T13*(I13*(100%+T$11))+U13*(I13*(100%+U$11))+V13*(I13*(100%+V$11))+W13*(I13*(100%+W$11))+X13*(I13*(100%+X$11))+Y13*(I13*(100%+Y$11))+Z13*(I13*(100%+Z$11))+AA13*(I13*(100%+AA$11)) -> 30568.406 | AY13: =AC13*(J13*(100%+AC$11))+AD13*(J13*(100%+AD$11))+AE13*(J13*(100%+AE$11))+AF13*(J13*(100%+AF$11))+AG13*(J13*(100%+AG$11))+AH13*(J13*(100%+AH$11))+AI13*(J13*(100%+AI$11))+AJ13*(J13*(100%+AJ$11))+AK13*(J13*(100%+AK$11))+AL13*(J13*(100%+AL$11))+AM13*(J13*(100%+AM$11))+AN13*(J13*(100%+AN$11)) -> 50306.863 | AZ13: =K13*AT13*AT$7 -> 47791.52 | BA13: =L13*AU13*AU$7 -> 45401.944 | BB13: =M13*AV13*AV$7 -> 43131.847 | BD13: =SUM(AX13:BB13) -> 217200.58 | BF13: Baseline band measured on number of Users in Brazil: 2050 | BG13: Users File: Country "Brazil", Account Type "User"
C14: German | D14: Fixed monthly | E14: local | F14: normal | G14: Option | I14: 5651.4585 | J14: 5425.4002 | K14: 5154.1302 | L14: 4896.4237 | M14: 4651.6025 | O14: 1 | U14: =$O$14 -> 1 | V14: =$O$14 -> 1 | W14: =$O$14 -> 1 | X14: =$O$14 -> 1 | Y14: =$O$14 -> 1 | Z14: =$O$14 -> 1 | AA14: =$O$14 -> 1 | AC14: =$O$14 -> 1 | AD14: =$O$14 -> 1 | AE14: =$O$14 -> 1 | AF14: =$O$14 -> 1 | AG14: =$O$14 -> 1 | AH14: =$O$14 -> 1 | AI14: =$O$14 -> 1 | AJ14: =$O$14 -> 1 | ... AN14: =$O$14 -> 1 | AR14: =IFERROR(AVERAGE(P14:AA14),0) -> 1 | AS14: =IFERROR(AVERAGE(AC14:AN14),0) -> 1 | AT14: =O14 -> 1 | AU14: =AT14 -> 1 | AV14: =AU14 -> 1 | AX14: =P14*(I14*(100%+P$11))+Q14*(I14*(100%+Q$11))+R14*(I14*(100%+R$11))+S14*(I14*(100%+S$11))+T14*(I14*(100%+T$11))+U14*(I14*(100%+U$11))+V14*(I14*(100%+V$11))+W14*(I14*(100%+W$11))+X14*(I14*(100%+X$11))+Y14*(I14*(100%+Y$11))+Z14*(I14*(100%+Z$11))+AA14*(I14*(100%+AA$11)) -> 39560.21 | AY14: =AC14*(J14*(100%+AC$11))+AD14*(J14*(100%+AD$11))+AE14*(J14*(100%+AE$11))+AF14*(J14*(100%+AF$11))+AG14*(J14*(100%+AG$11))+AH14*(J14*(100%+AH$11))+AI14*(J14*(100%+AI$11))+AJ14*(J14*(100%+AJ$11))+AK14*(J14*(100%+AK$11))+AL14*(J14*(100%+AL$11))+AM14*(J14*(100%+AM$11))+AN14*(J14*(100%+AN$11)) -> 65104.802 | AZ14: =K14*AT14*AT$7 -> 61849.562 | BA14: =L14*AU14*AU$7 -> 58757.084 | BB14: =M14*AV14*AV$7 -> 55819.23 | BD14: =SUM(AX14:BB14) -> 281090.89 | BF14: Baseline band measured on number of Users in Germany: 1515 | BG14: Users File: Country "Germany", Account Type "User"
C15: French | D15: Fixed monthly | E15: local | F15: normal | G15: Option | I15: 5039.3869 | J15: 4837.8114 | K15: 4595.9208 | L15: 4366.1248 | M15: 4147.8185 | O15: 1 | U15: =$O$15 -> 1 | V15: =$O$15 -> 1 | W15: =$O$15 -> 1 | X15: =$O$15 -> 1 | Y15: =$O$15 -> 1 | Z15: =$O$15 -> 1 | AA15: =$O$15 -> 1 | AC15: =$O$15 -> 1 | AD15: =$O$15 -> 1 | AE15: =$O$15 -> 1 | AF15: =$O$15 -> 1 | AG15: =$O$15 -> 1 | AH15: =$O$15 -> 1 | AI15: =$O$15 -> 1 | AJ15: =$O$15 -> 1 | ... AN15: =$O$15 -> 1 | AR15: =IFERROR(AVERAGE(P15:AA15),0) -> 1 | AS15: =IFERROR(AVERAGE(AC15:AN15),0) -> 1 | AT15: =O15 -> 1 | AU15: =AT15 -> 1 | AV15: =AU15 -> 1 | AX15: =P15*(I15*(100%+P$11))+Q15*(I15*(100%+Q$11))+R15*(I15*(100%+R$11))+S15*(I15*(100%+S$11))+T15*(I15*(100%+T$11))+U15*(I15*(100%+U$11))+V15*(I15*(100%+V$11))+W15*(I15*(100%+W$11))+X15*(I15*(100%+X$11))+Y15*(I15*(100%+Y$11))+Z15*(I15*(100%+Z$11))+AA15*(I15*(100%+AA$11)) -> 35275.708 | AY15: =AC15*(J15*(100%+AC$11))+AD15*(J15*(100%+AD$11))+AE15*(J15*(100%+AE$11))+AF15*(J15*(100%+AF$11))+AG15*(J15*(100%+AG$11))+AH15*(J15*(100%+AH$11))+AI15*(J15*(100%+AI$11))+AJ15*(J15*(100%+AJ$11))+AK15*(J15*(100%+AK$11))+AL15*(J15*(100%+AL$11))+AM15*(J15*(100%+AM$11))+AN15*(J15*(100%+AN$11)) -> 58053.737 | AZ15: =K15*AT15*AT$7 -> 55151.05 | BA15: =L15*AU15*AU$7 -> 52393.497 | BB15: =M15*AV15*AV$7 -> 49773.822 | BD15: =SUM(AX15:BB15) -> 250647.81 | BF15: Baseline band measured on number of Users in France: 872 | BG15: Users File: Country "France", Account Type "User"
C16: Mandarin | D16: Fixed monthly | E16: local | F16: normal | G16: Option | I16: 2885.2922 | J16: 2769.8805 | K16: 2631.3865 | L16: 2499.8172 | M16: 2374.8263 | O16: 1 | U16: =$O$16 -> 1 | V16: =$O$16 -> 1 | W16: =$O$16 -> 1 | X16: =$O$16 -> 1 | Y16: =$O$16 -> 1 | Z16: =$O$16 -> 1 | AA16: =$O$16 -> 1 | AC16: =$O$16 -> 1 | AD16: =$O$16 -> 1 | AE16: =$O$16 -> 1 | AF16: =$O$16 -> 1 | AG16: =$O$16 -> 1 | AH16: =$O$16 -> 1 | AI16: =$O$16 -> 1 | AJ16: =$O$16 -> 1 | ... AN16: =$O$16 -> 1 | AR16: =IFERROR(AVERAGE(P16:AA16),0) -> 1 | AS16: =IFERROR(AVERAGE(AC16:AN16),0) -> 1 | AT16: =O16 -> 1 | AU16: =AT16 -> 1 | AV16: =AU16 -> 1 | AX16: =P16*(I16*(100%+P$11))+Q16*(I16*(100%+Q$11))+R16*(I16*(100%+R$11))+S16*(I16*(100%+S$11))+T16*(I16*(100%+T$11))+U16*(I16*(100%+U$11))+V16*(I16*(100%+V$11))+W16*(I16*(100%+W$11))+X16*(I16*(100%+X$11))+Y16*(I16*(100%+Y$11))+Z16*(I16*(100%+Z$11))+AA16*(I16*(100%+AA$11)) -> 20197.046 | AY16: =AC16*(J16*(100%+AC$11))+AD16*(J16*(100%+AD$11))+AE16*(J16*(100%+AE$11))+AF16*(J16*(100%+AF$11))+AG16*(J16*(100%+AG$11))+AH16*(J16*(100%+AH$11))+AI16*(J16*(100%+AI$11))+AJ16*(J16*(100%+AJ$11))+AK16*(J16*(100%+AK$11))+AL16*(J16*(100%+AL$11))+AM16*(J16*(100%+AM$11))+AN16*(J16*(100%+AN$11)) -> 33238.566 | AZ16: =K16*AT16*AT$7 -> 31576.638 | BA16: =L16*AU16*AU$7 -> 29997.806 | BB16: =M16*AV16*AV$7 -> 28497.916 | BD16: =SUM(AX16:BB16) -> 143507.97 | BF16: Baseline band measured on number of Users in China: 213 | BG16: Users File: Country "China", Account Type "User"
B18: Workplace Services (WPS) | P18: =IF(P$7<$AP$18,percPreTargetAdjustment,0%) -> 0 | Q18: =IF(Q$7<$AP$18,percPreTargetAdjustment,0%) -> 0 | R18: =IF(R$7<$AP$18,percPreTargetAdjustment,0%) -> 0 | S18: =IF(S$7<$AP$18,percPreTargetAdjustment,0%) -> 0 | T18: =IF(T$7<$AP$18,percPreTargetAdjustment,0%) -> 0 | U18: =IF(U$7<$AP$18,percPreTargetAdjustment,0%) -> 0 | V18: =IF(V$7<$AP$18,percPreTargetAdjustment,0%) -> 0 | W18: =IF(W$7<$AP$18,percPreTargetAdjustment,0%) -> 0 | ... AA18: =IF(AA$7<$AP$18,percPreTargetAdjustment,0%) -> 0 | AC18: =IF(AC$7<$AP$18,percPreTargetAdjustment,0%) -> 0 | AD18: =IF(AD$7<$AP$18,percPreTargetAdjustment,0%) -> 0 | AE18: =IF(AE$7<$AP$18,percPreTargetAdjustment,0%) -> 0 | AF18: =IF(AF$7<$AP$18,percPreTargetAdjustment,0%) -> 0 | AG18: =IF(AG$7<$AP$18,percPreTargetAdjustment,0%) -> 0 | AH18: =IF(AH$7<$AP$18,percPreTargetAdjustment,0%) -> 0 | AI18: =IF(AI$7<$AP$18,percPreTargetAdjustment,0%) -> 0 | AJ18: =IF(AJ$7<$AP$18,percPreTargetAdjustment,0%) -> 0 | ... AN18: =IF(AN$7<$AP$18,percPreTargetAdjustment,0%) -> 0 | AX18: =SUMIFS(AX19:AX28,$G19:$G28,"<>Option") -> 1959711.2 | AY18: =SUMIFS(AY19:AY28,$G19:$G28,"<>Option") -> 3225124.7 | AZ18: =SUMIFS(AZ19:AZ28,$G19:$G28,"<>Option") -> 3027947.7 | BA18: =SUMIFS(BA19:BA28,$G19:$G28,"<>Option") -> 2876550.3 | BB18: =SUMIFS(BB19:BB28,$G19:$G28,"<>Option") -> 2732722.8 | BD18: =SUM(AX18:BB18) -> 13822057
C19: Managed PC | D19: PC device | E19: local | F19: normal | I19: 19.431735 | J19: 18.654465 | K19: 17.721742 | L19: 16.835655 | M19: 15.993872 | O19: 10156 | U19: =$O$19 -> 10156 | V19: =$O$19 -> 10156 | W19: =$O$19 -> 10156 | X19: =$O$19 -> 10156 | Y19: =$O$19 -> 10156 | Z19: =$O$19 -> 10156 | AA19: =$O$19 -> 10156 | AC19: =$O$19 -> 10156 | AD19: =$O$19 -> 10156 | AE19: =$O$19 -> 10156 | AF19: =$O$19 -> 10156 | AG19: =$O$19 -> 10156 | AH19: =$O$19 -> 10156 | AI19: =$O$19 -> 10156 | AJ19: =$O$19 -> 10156 | ... AN19: =$O$19 -> 10156 | AR19: =IFERROR(AVERAGE(P19:AA19),0) -> 10156 | AS19: =IFERROR(AVERAGE(AC19:AN19),0) -> 10156 | AT19: =O19 -> 10156 | AU19: =AT19 -> 10156 | AV19: =AU19 -> 10156 | AX19: =P19*(I19*(100%+P$18))+Q19*(I19*(100%+Q$18))+R19*(I19*(100%+R$18))+S19*(I19*(100%+S$18))+T19*(I19*(100%+T$18))+U19*(I19*(100%+U$18))+V19*(I19*(100%+V$18))+W19*(I19*(100%+W$18))+X19*(I19*(100%+X$18))+Y19*(I19*(100%+Y$18))+Z19*(I19*(100%+Z$18))+AA19*(I19*(100%+AA$18)) -> 1381440.9 | AY19: =AC19*(J19*(100%+AC$18))+AD19*(J19*(100%+AD$18))+AE19*(J19*(100%+AE$18))+AF19*(J19*(100%+AF$18))+AG19*(J19*(100%+AG$18))+AH19*(J19*(100%+AH$18))+AI19*(J19*(100%+AI$18))+AJ19*(J19*(100%+AJ$18))+AK19*(J19*(100%+AK$18))+AL19*(J19*(100%+AL$18))+AM19*(J19*(100%+AM$18))+AN19*(J19*(100%+AN$18)) -> 2273457 | AZ19: =K19*AT19*AT$7 -> 2159784.2 | BA19: =L19*AU19*AU$7 -> 2051795 | BB19: =M19*AV19*AV$7 -> 1949205.2 | BD19: =SUM(AX19:BB19) -> 9815682.2 | BF19: For OpEx ( DaaS) + CapEx (Non-DaaS) PCs | BG19: Device CMDB File: Total device count
C20: Uplift on 'Managed PC' for ReadyTech kiosk | D20: PC device | E20: local | F20: wide | G20: Option | I20: =I19+Devices!$V$9 -> 41.676782 | J20: =J19+Devices!$V$9 -> 40.899512 | K20: =K19+Devices!$V$9 -> 39.966789 | L20: =L19+Devices!$V$9 -> 39.080702 | M20: =M19+Devices!$V$9 -> 38.238919 | O20: 0 | U20: =$O$20 -> 0 | V20: =$O$20 -> 0 | W20: =$O$20 -> 0 | X20: =$O$20 -> 0 | Y20: =$O$20 -> 0 | Z20: =$O$20 -> 0 | AA20: =$O$20 -> 0 | AC20: =$O$20 -> 0 | AD20: =$O$20 -> 0 | AE20: =$O$20 -> 0 | AF20: =$O$20 -> 0 | AG20: =$O$20 -> 0 | AH20: =$O$20 -> 0 | AI20: =$O$20 -> 0 | AJ20: =$O$20 -> 0 | ... AN20: =$O$20 -> 0 | AR20: =IFERROR(AVERAGE(P20:AA20),0) -> 0 | AS20: =IFERROR(AVERAGE(AC20:AN20),0) -> 0 | AT20: 100 | AU20: =AT20 -> 100 | AV20: =AU20 -> 100 | AX20: =P20*(I20*(100%+P$18))+Q20*(I20*(100%+Q$18))+R20*(I20*(100%+R$18))+S20*(I20*(100%+S$18))+T20*(I20*(100%+T$18))+U20*(I20*(100%+U$18))+V20*(I20*(100%+V$18))+W20*(I20*(100%+W$18))+X20*(I20*(100%+X$18))+Y20*(I20*(100%+Y$18))+Z20*(I20*(100%+Z$18))+AA20*(I20*(100%+AA$18)) -> 0 | AY20: =AC20*(J20*(100%+AC$18))+AD20*(J20*(100%+AD$18))+AE20*(J20*(100%+AE$18))+AF20*(J20*(100%+AF$18))+AG20*(J20*(100%+AG$18))+AH20*(J20*(100%+AH$18))+AI20*(J20*(100%+AI$18))+AJ20*(J20*(100%+AJ$18))+AK20*(J20*(100%+AK$18))+AL20*(J20*(100%+AL$18))+AM20*(J20*(100%+AM$18))+AN20*(J20*(100%+AN$18)) -> 0 | AZ20: =K20*AT20*AT$7 -> 47960.147 | BA20: =L20*AU20*AU$7 -> 46896.842 | BB20: =M20*AV20*AV$7 -> 45886.703 | BD20: =SUM(AX20:BB20) -> 140743.69
C21: Company Smartphone and Company Tablet | D21: Mobile Device | E21: local | F21: wide | I21: 13.474287 | J21: 12.935315 | K21: 12.28855 | L21: 11.674122 | M21: 11.090416 | O21: 459 | U21: =$O$21 -> 459 | V21: =$O$21 -> 459 | W21: =$O$21 -> 459 | X21: =$O$21 -> 459 | Y21: =$O$21 -> 459 | Z21: =$O$21 -> 459 | AA21: =$O$21 -> 459 | AC21: =$O$21 -> 459 | AD21: =$O$21 -> 459 | AE21: =$O$21 -> 459 | AF21: =$O$21 -> 459 | AG21: =$O$21 -> 459 | AH21: =$O$21 -> 459 | AI21: =$O$21 -> 459 | AJ21: =$O$21 -> 459 | ... AN21: =$O$21 -> 459 | AR21: =IFERROR(AVERAGE(P21:AA21),0) -> 459 | AS21: =IFERROR(AVERAGE(AC21:AN21),0) -> 459 | AT21: =O21 -> 459 | AU21: =AT21 -> 459 | AV21: =AU21 -> 459 | AX21: =P21*(I21*(100%+P$18))+Q21*(I21*(100%+Q$18))+R21*(I21*(100%+R$18))+S21*(I21*(100%+S$18))+T21*(I21*(100%+T$18))+U21*(I21*(100%+U$18))+V21*(I21*(100%+V$18))+W21*(I21*(100%+W$18))+X21*(I21*(100%+X$18))+Y21*(I21*(100%+Y$18))+Z21*(I21*(100%+Z$18))+AA21*(I21*(100%+AA$18)) -> 43292.884 | AY21: =AC21*(J21*(100%+AC$18))+AD21*(J21*(100%+AD$18))+AE21*(J21*(100%+AE$18))+AF21*(J21*(100%+AF$18))+AG21*(J21*(100%+AG$18))+AH21*(J21*(100%+AH$18))+AI21*(J21*(100%+AI$18))+AJ21*(J21*(100%+AJ$18))+AK21*(J21*(100%+AK$18))+AL21*(J21*(100%+AL$18))+AM21*(J21*(100%+AM$18))+AN21*(J21*(100%+AN$18)) -> 71247.717 | AZ21: =K21*AT21*AT$7 -> 67685.331 | BA21: =L21*AU21*AU$7 -> 64301.065 | BB21: =M21*AV21*AV$7 -> 61086.011 | BD21: =SUM(AX21:BB21) -> 307613.01 | BF21: Baseline band is for Company Smartphone + Company Tablet + Managed Mobile | BG21: October Factory Tables Invoice from Accenture
C22: Managed Mobile | D22: Mobile Device | E22: local | F22: wide | I22: 1.7597105 | J22: 1.6893221 | K22: 1.604856 | L22: 1.5246132 | M22: 1.4483826 | O22: 9688 | U22: =$O$22 -> 9688 | V22: =$O$22 -> 9688 | W22: =$O$22 -> 9688 | X22: =$O$22 -> 9688 | Y22: =$O$22 -> 9688 | Z22: =$O$22 -> 9688 | AA22: =$O$22 -> 9688 | AC22: =$O$22 -> 9688 | AD22: =$O$22 -> 9688 | AE22: =$O$22 -> 9688 | AF22: =$O$22 -> 9688 | AG22: =$O$22 -> 9688 | AH22: =$O$22 -> 9688 | AI22: =$O$22 -> 9688 | AJ22: =$O$22 -> 9688 | ... AN22: =$O$22 -> 9688 | AR22: =IFERROR(AVERAGE(P22:AA22),0) -> 9688 | AS22: =IFERROR(AVERAGE(AC22:AN22),0) -> 9688 | AT22: =O22 -> 9688 | AU22: =AT22 -> 9688 | AV22: =AU22 -> 9688 | AX22: =P22*(I22*(100%+P$18))+Q22*(I22*(100%+Q$18))+R22*(I22*(100%+R$18))+S22*(I22*(100%+S$18))+T22*(I22*(100%+T$18))+U22*(I22*(100%+U$18))+V22*(I22*(100%+V$18))+W22*(I22*(100%+W$18))+X22*(I22*(100%+X$18))+Y22*(I22*(100%+Y$18))+Z22*(I22*(100%+Z$18))+AA22*(I22*(100%+AA$18)) -> 119336.53 | AY22: =AC22*(J22*(100%+AC$18))+AD22*(J22*(100%+AD$18))+AE22*(J22*(100%+AE$18))+AF22*(J22*(100%+AF$18))+AG22*(J22*(100%+AG$18))+AH22*(J22*(100%+AH$18))+AI22*(J22*(100%+AI$18))+AJ22*(J22*(100%+AJ$18))+AK22*(J22*(100%+AK$18))+AL22*(J22*(100%+AL$18))+AM22*(J22*(100%+AM$18))+AN22*(J22*(100%+AN$18)) -> 196393.83 | AZ22: =K22*AT22*AT$7 -> 186574.14 | BA22: =L22*AU22*AU$7 -> 177245.43 | BB22: =M22*AV22*AV$7 -> 168383.16 | BD22: =SUM(AX22:BB22) -> 847933.1 | BF22: Baseline band is for Company Smartphone + Company Tablet + Managed Mobile | BG22: InTune File: minus factory tablet volume from Accenture invoicing.
C23: Microsoft 365 full usage | D23: User | E23: local | F23: normal | I23: 3.0329179 | J23: 2.9116012 | K23: 2.7660212 | L23: 2.6277201 | M23: 2.4963341 | O23: 12250 | U23: =$O$23 -> 12250 | V23: =$O$23 -> 12250 | W23: =$O$23 -> 12250 | X23: =$O$23 -> 12250 | Y23: =$O$23 -> 12250 | Z23: =$O$23 -> 12250 | AA23: =$O$23 -> 12250 | AC23: =$O$23 -> 12250 | AD23: =$O$23 -> 12250 | AE23: =$O$23 -> 12250 | AF23: =$O$23 -> 12250 | AG23: =$O$23 -> 12250 | AH23: =$O$23 -> 12250 | AI23: =$O$23 -> 12250 | AJ23: =$O$23 -> 12250 | ... AN23: =$O$23 -> 12250 | AR23: =IFERROR(AVERAGE(P23:AA23),0) -> 12250 | AS23: =IFERROR(AVERAGE(AC23:AN23),0) -> 12250 | AT23: =O23 -> 12250 | AU23: =AT23 -> 12250 | AV23: =AU23 -> 12250 | AX23: =P23*(I23*(100%+P$18))+Q23*(I23*(100%+Q$18))+R23*(I23*(100%+R$18))+S23*(I23*(100%+S$18))+T23*(I23*(100%+T$18))+U23*(I23*(100%+U$18))+V23*(I23*(100%+V$18))+W23*(I23*(100%+W$18))+X23*(I23*(100%+X$18))+Y23*(I23*(100%+Y$18))+Z23*(I23*(100%+Z$18))+AA23*(I23*(100%+AA$18)) -> 260072.71 | AY23: =AC23*(J23*(100%+AC$18))+AD23*(J23*(100%+AD$18))+AE23*(J23*(100%+AE$18))+AF23*(J23*(100%+AF$18))+AG23*(J23*(100%+AG$18))+AH23*(J23*(100%+AH$18))+AI23*(J23*(100%+AI$18))+AJ23*(J23*(100%+AJ$18))+AK23*(J23*(100%+AK$18))+AL23*(J23*(100%+AL$18))+AM23*(J23*(100%+AM$18))+AN23*(J23*(100%+AN$18)) -> 428005.38 | AZ23: =K23*AT23*AT$7 -> 406605.11 | BA23: =L23*AU23*AU$7 -> 386274.85 | BB23: =M23*AV23*AV$7 -> 366961.11 | BD23: =SUM(AX23:BB23) -> 1847919.2 | BG23: Users File: O365 License Type "Enterprise"
C24: Microsoft 365 light usage | D24: User | E24: local | F24: wide | I24: 2.4515913 | J24: 2.3535276 | K24: 2.2358512 | L24: 2.1240587 | M24: 2.0178557 | O24: 2600 | U24: =$O$24 -> 2600 | V24: =$O$24 -> 2600 | W24: =$O$24 -> 2600 | X24: =$O$24 -> 2600 | Y24: =$O$24 -> 2600 | Z24: =$O$24 -> 2600 | AA24: =$O$24 -> 2600 | AC24: =$O$24 -> 2600 | AD24: =$O$24 -> 2600 | AE24: =$O$24 -> 2600 | AF24: =$O$24 -> 2600 | AG24: =$O$24 -> 2600 | AH24: =$O$24 -> 2600 | AI24: =$O$24 -> 2600 | AJ24: =$O$24 -> 2600 | ... AN24: =$O$24 -> 2600 | AR24: =IFERROR(AVERAGE(P24:AA24),0) -> 2600 | AS24: =IFERROR(AVERAGE(AC24:AN24),0) -> 2600 | AT24: =O24 -> 2600 | AU24: =AT24 -> 2600 | AV24: =AU24 -> 2600 | AX24: =P24*(I24*(100%+P$18))+Q24*(I24*(100%+Q$18))+R24*(I24*(100%+R$18))+S24*(I24*(100%+S$18))+T24*(I24*(100%+T$18))+U24*(I24*(100%+U$18))+V24*(I24*(100%+V$18))+W24*(I24*(100%+W$18))+X24*(I24*(100%+X$18))+Y24*(I24*(100%+Y$18))+Z24*(I24*(100%+Z$18))+AA24*(I24*(100%+AA$18)) -> 44618.961 | AY24: =AC24*(J24*(100%+AC$18))+AD24*(J24*(100%+AD$18))+AE24*(J24*(100%+AE$18))+AF24*(J24*(100%+AF$18))+AG24*(J24*(100%+AG$18))+AH24*(J24*(100%+AH$18))+AI24*(J24*(100%+AI$18))+AJ24*(J24*(100%+AJ$18))+AK24*(J24*(100%+AK$18))+AL24*(J24*(100%+AL$18))+AM24*(J24*(100%+AM$18))+AN24*(J24*(100%+AN$18)) -> 73430.062 | AZ24: =K24*AT24*AT$7 -> 69758.559 | BA24: =L24*AU24*AU$7 -> 66270.631 | BB24: =M24*AV24*AV$7 -> 62957.099 | BD24: =SUM(AX24:BB24) -> 317035.31 | BG24: Users File: O365 License Type "Firstline"
C25: Teams meeting room platform management | D25: Fixed monthly | E25: central | F25: n/a | I25: 6836.261 | J25: 6562.8106 | K25: 6234.6701 | L25: 5922.9366 | M25: 5626.7897 | O25: 1 | U25: =$O$25 -> 1 | V25: =$O$25 -> 1 | W25: =$O$25 -> 1 | X25: =$O$25 -> 1 | Y25: =$O$25 -> 1 | Z25: =$O$25 -> 1 | AA25: =$O$25 -> 1 | AC25: =$O$25 -> 1 | AD25: =$O$25 -> 1 | AE25: =$O$25 -> 1 | AF25: =$O$25 -> 1 | AG25: =$O$25 -> 1 | AH25: =$O$25 -> 1 | AI25: =$O$25 -> 1 | AJ25: =$O$25 -> 1 | ... AN25: =$O$25 -> 1 | AR25: =IFERROR(AVERAGE(P25:AA25),0) -> 1 | AS25: =IFERROR(AVERAGE(AC25:AN25),0) -> 1 | AT25: =O25 -> 1 | AU25: =AT25 -> 1 | AV25: =AU25 -> 1 | AX25: =P25*(I25*(100%+P$18))+Q25*(I25*(100%+Q$18))+R25*(I25*(100%+R$18))+S25*(I25*(100%+S$18))+T25*(I25*(100%+T$18))+U25*(I25*(100%+U$18))+V25*(I25*(100%+V$18))+W25*(I25*(100%+W$18))+X25*(I25*(100%+X$18))+Y25*(I25*(100%+Y$18))+Z25*(I25*(100%+Z$18))+AA25*(I25*(100%+AA$18)) -> 47853.827 | AY25: =AC25*(J25*(100%+AC$18))+AD25*(J25*(100%+AD$18))+AE25*(J25*(100%+AE$18))+AF25*(J25*(100%+AF$18))+AG25*(J25*(100%+AG$18))+AH25*(J25*(100%+AH$18))+AI25*(J25*(100%+AI$18))+AJ25*(J25*(100%+AJ$18))+AK25*(J25*(100%+AK$18))+AL25*(J25*(100%+AL$18))+AM25*(J25*(100%+AM$18))+AN25*(J25*(100%+AN$18)) -> 78753.727 | AZ25: =K25*AT25*AT$7 -> 74816.041 | BA25: =L25*AU25*AU$7 -> 71075.239 | BB25: =M25*AV25*AV$7 -> 67521.477 | BD25: =SUM(AX25:BB25) -> 340020.31
C26: Azure Virtual Desktop | D26: Workspace/Host Pool | E26: central | F26: n/a | I26: 892.49796 | J26: 856.79804 | K26: 813.95814 | L26: 773.26023 | M26: 734.59722 | O26: 5 | U26: =$O$26 -> 5 | V26: =$O$26 -> 5 | W26: =$O$26 -> 5 | X26: =$O$26 -> 5 | Y26: =$O$26 -> 5 | Z26: =$O$26 -> 5 | AA26: =$O$26 -> 5 | AC26: =$O$26 -> 5 | AD26: =$O$26 -> 5 | AE26: =$O$26 -> 5 | AF26: =$O$26 -> 5 | AG26: =$O$26 -> 5 | AH26: =$O$26 -> 5 | AI26: =$O$26 -> 5 | AJ26: =$O$26 -> 5 | ... AN26: =$O$26 -> 5 | AR26: =IFERROR(AVERAGE(P26:AA26),0) -> 5 | AS26: =IFERROR(AVERAGE(AC26:AN26),0) -> 5 | AT26: =O26 -> 5 | AU26: =AT26 -> 5 | AV26: =AU26 -> 5 | AX26: =P26*(I26*(100%+P$18))+Q26*(I26*(100%+Q$18))+R26*(I26*(100%+R$18))+S26*(I26*(100%+S$18))+T26*(I26*(100%+T$18))+U26*(I26*(100%+U$18))+V26*(I26*(100%+V$18))+W26*(I26*(100%+W$18))+X26*(I26*(100%+X$18))+Y26*(I26*(100%+Y$18))+Z26*(I26*(100%+Z$18))+AA26*(I26*(100%+AA$18)) -> 31237.429 | AY26: =AC26*(J26*(100%+AC$18))+AD26*(J26*(100%+AD$18))+AE26*(J26*(100%+AE$18))+AF26*(J26*(100%+AF$18))+AG26*(J26*(100%+AG$18))+AH26*(J26*(100%+AH$18))+AI26*(J26*(100%+AI$18))+AJ26*(J26*(100%+AJ$18))+AK26*(J26*(100%+AK$18))+AL26*(J26*(100%+AL$18))+AM26*(J26*(100%+AM$18))+AN26*(J26*(100%+AN$18)) -> 51407.882 | AZ26: =K26*AT26*AT$7 -> 48837.488 | BA26: =L26*AU26*AU$7 -> 46395.614 | BB26: =M26*AV26*AV$7 -> 44075.833 | BD26: =SUM(AX26:BB26) -> 221954.25
C27: CIS Managed OS for On-site and Azure WPS servers | D27: =D34 -> OS instance | E27: =E34 -> local | F27: =$F$33 -> normal | I27: =I34 -> 16.918712 | J27: =J34 -> 16.241964 | K27: =K34 -> 15.429866 | L27: =L34 -> 14.658372 | M27: =M34 -> 13.925454 | O27: 269 | U27: =$O$27 -> 269 | V27: =$O$27 -> 269 | W27: =$O$27 -> 269 | X27: =$O$27 -> 269 | Y27: =$O$27 -> 269 | Z27: =$O$27 -> 269 | AA27: =$O$27 -> 269 | AC27: =$O$27 -> 269 | AD27: =$O$27 -> 269 | AE27: =$O$27 -> 269 | AF27: =$O$27 -> 269 | AG27: =$O$27 -> 269 | AH27: =$O$27 -> 269 | AI27: =$O$27 -> 269 | AJ27: =$O$27 -> 269 | ... AN27: =$O$27 -> 269 | AR27: =IFERROR(AVERAGE(P27:AA27),0) -> 269 | AS27: =IFERROR(AVERAGE(AC27:AN27),0) -> 269 | AT27: 75 | AU27: =AT27 -> 75 | AV27: =AU27 -> 75 | AX27: =P27*(I27*(100%+P$18))+Q27*(I27*(100%+Q$18))+R27*(I27*(100%+R$18))+S27*(I27*(100%+S$18))+T27*(I27*(100%+T$18))+U27*(I27*(100%+U$18))+V27*(I27*(100%+V$18))+W27*(I27*(100%+W$18))+X27*(I27*(100%+X$18))+Y27*(I27*(100%+Y$18))+Z27*(I27*(100%+Z$18))+AA27*(I27*(100%+AA$18)) -> 31857.935 | AY27: =AC27*(J27*(100%+AC$18))+AD27*(J27*(100%+AD$18))+AE27*(J27*(100%+AE$18))+AF27*(J27*(100%+AF$18))+AG27*(J27*(100%+AG$18))+AH27*(J27*(100%+AH$18))+AI27*(J27*(100%+AI$18))+AJ27*(J27*(100%+AJ$18))+AK27*(J27*(100%+AK$18))+AL27*(J27*(100%+AL$18))+AM27*(J27*(100%+AM$18))+AN27*(J27*(100%+AN$18)) -> 52429.059 | AZ27: =K27*AT27*AT$7 -> 13886.879 | BA27: =L27*AU27*AU$7 -> 13192.535 | BB27: =M27*AV27*AV$7 -> 12532.908 | BD27: =SUM(AX27:BB27) -> 123899.32 | BG27: Server CMDB file: Server Function "EUS", Hosting Location "On Prem"
B29: Cloud and Infrastructure Services (CIS) | P29: =IF(P$7<$AP$29,percPreTargetAdjustment,0%) -> 0 | Q29: =IF(Q$7<$AP$29,percPreTargetAdjustment,0%) -> 0 | R29: =IF(R$7<$AP$29,percPreTargetAdjustment,0%) -> 0 | S29: =IF(S$7<$AP$29,percPreTargetAdjustment,0%) -> 0 | T29: =IF(T$7<$AP$29,percPreTargetAdjustment,0%) -> 0 | U29: =IF(U$7<$AP$29,percPreTargetAdjustment,0%) -> 0 | V29: =IF(V$7<$AP$29,percPreTargetAdjustment,0%) -> 0 | W29: =IF(W$7<$AP$29,percPreTargetAdjustment,0%) -> 0 | ... AA29: =IF(AA$7<$AP$29,percPreTargetAdjustment,0%) -> 0 | AC29: =IF(AC$7<$AP$29,percPreTargetAdjustment,0%) -> 0 | AD29: =IF(AD$7<$AP$29,percPreTargetAdjustment,0%) -> 0 | AE29: =IF(AE$7<$AP$29,percPreTargetAdjustment,0%) -> 0 | AF29: =IF(AF$7<$AP$29,percPreTargetAdjustment,0%) -> 0 | AG29: =IF(AG$7<$AP$29,percPreTargetAdjustment,0%) -> 0 | AH29: =IF(AH$7<$AP$29,percPreTargetAdjustment,0%) -> 0 | AI29: =IF(AI$7<$AP$29,percPreTargetAdjustment,0%) -> 0 | AJ29: =IF(AJ$7<$AP$29,percPreTargetAdjustment,0%) -> 0 | ... AN29: =IF(AN$7<$AP$29,percPreTargetAdjustment,0%) -> 0 | AX29: =SUMIFS(AX30:AX38,$G30:$G38,"<>Option") -> 210944.85 | AY29: =SUMIFS(AY30:AY38,$G30:$G38,"<>Option") -> 347154.95 | AZ29: =SUMIFS(AZ30:AZ38,$G30:$G38,"<>Option") -> 297411.49 | BA29: =SUMIFS(BA30:BA38,$G30:$G38,"<>Option") -> 282540.91 | BB29: =SUMIFS(BB30:BB38,$G30:$G38,"<>Option") -> 268413.87 | BD29: =SUM(AX29:BB29) -> 1406466.1
C30: Cloud Center of Excellence – IT part | D30: Fixed monthly | E30: central | F30: n/a | I30: 18880.862 | J30: 18125.627 | K30: 17219.346 | L30: 16358.379 | M30: 15540.46 | O30: 1 | U30: =$O$30 -> 1 | V30: =$O$30 -> 1 | W30: =$O$30 -> 1 | X30: =$O$30 -> 1 | Y30: =$O$30 -> 1 | Z30: =$O$30 -> 1 | AA30: =$O$30 -> 1 | AC30: =$O$30 -> 1 | AD30: =$O$30 -> 1 | AE30: =$O$30 -> 1 | AF30: =$O$30 -> 1 | AG30: =$O$30 -> 1 | AH30: =$O$30 -> 1 | AI30: =$O$30 -> 1 | AJ30: =$O$30 -> 1 | ... AN30: =$O$30 -> 1 | AR30: =IFERROR(AVERAGE(P30:AA30),0) -> 1 | AS30: =IFERROR(AVERAGE(AC30:AN30),0) -> 1 | AT30: =O30 -> 1 | AU30: =AT30 -> 1 | AV30: =AU30 -> 1 | AX30: =P30*(I30*(100%+P$29))+Q30*(I30*(100%+Q$29))+R30*(I30*(100%+R$29))+S30*(I30*(100%+S$29))+T30*(I30*(100%+T$29))+U30*(I30*(100%+U$29))+V30*(I30*(100%+V$29))+W30*(I30*(100%+W$29))+X30*(I30*(100%+X$29))+Y30*(I30*(100%+Y$29))+Z30*(I30*(100%+Z$29))+AA30*(I30*(100%+AA$29)) -> 132166.03 | AY30: =AC30*(J30*(100%+AC$29))+AD30*(J30*(100%+AD$29))+AE30*(J30*(100%+AE$29))+AF30*(J30*(100%+AF$29))+AG30*(J30*(100%+AG$29))+AH30*(J30*(100%+AH$29))+AI30*(J30*(100%+AI$29))+AJ30*(J30*(100%+AJ$29))+AK30*(J30*(100%+AK$29))+AL30*(J30*(100%+AL$29))+AM30*(J30*(100%+AM$29))+AN30*(J30*(100%+AN$29)) -> 217507.53 | AZ30: =K30*AT30*AT$7 -> 206632.15 | BA30: =L30*AU30*AU$7 -> 196300.55 | BB30: =M30*AV30*AV$7 -> 186485.52 | BD30: =SUM(AX30:BB30) -> 939091.78
C31: Workload management
C32: Managed database non-PaaS | D32: Database Instance | E32: local | F32: wide | I32: 18.58313 | J32: 17.839805 | K32: 16.947815 | L32: 16.100424 | M32: 15.295403 | O32: 130 | U32: =$O$32 -> 130 | V32: =$O$32 -> 130 | W32: =$O$32 -> 130 | X32: =$O$32 -> 130 | Y32: =$O$32 -> 130 | Z32: =$O$32 -> 130 | AA32: =$O$32 -> 130 | AC32: =$O$32 -> 130 | AD32: =$O$32 -> 130 | AE32: =$O$32 -> 130 | AF32: =$O$32 -> 130 | AG32: =$O$32 -> 130 | AH32: =$O$32 -> 130 | AI32: =$O$32 -> 130 | AJ32: =$O$32 -> 130 | ... AN32: =$O$32 -> 130 | AR32: =IFERROR(AVERAGE(P32:AA32),0) -> 130 | AS32: =IFERROR(AVERAGE(AC32:AN32),0) -> 130 | AT32: =O32 -> 130 | AU32: =AT32 -> 130 | AV32: =AU32 -> 130 | AX32: =P32*(I32*(100%+P$29))+Q32*(I32*(100%+Q$29))+R32*(I32*(100%+R$29))+S32*(I32*(100%+S$29))+T32*(I32*(100%+T$29))+U32*(I32*(100%+U$29))+V32*(I32*(100%+V$29))+W32*(I32*(100%+W$29))+X32*(I32*(100%+X$29))+Y32*(I32*(100%+Y$29))+Z32*(I32*(100%+Z$29))+AA32*(I32*(100%+AA$29)) -> 16910.649 | AY32: =AC32*(J32*(100%+AC$29))+AD32*(J32*(100%+AD$29))+AE32*(J32*(100%+AE$29))+AF32*(J32*(100%+AF$29))+AG32*(J32*(100%+AG$29))+AH32*(J32*(100%+AH$29))+AI32*(J32*(100%+AI$29))+AJ32*(J32*(100%+AJ$29))+AK32*(J32*(100%+AK$29))+AL32*(J32*(100%+AL$29))+AM32*(J32*(100%+AM$29))+AN32*(J32*(100%+AN$29)) -> 27830.096 | AZ32: =K32*AT32*AT$7 -> 26438.591 | BA32: =L32*AU32*AU$7 -> 25116.662 | BB32: =M32*AV32*AV$7 -> 23860.829 | BD32: =SUM(AX32:BB32) -> 120156.83 | BF32: Baseline band is for all database instances combined | BG32: Database CMDB File: Infra Type "blank"
C33: Managed operating system (OS) – in Azure | D33: OS instance | E33: local | F33: normal | I33: 19.174621 | J33: 18.407636 | K33: 17.487255 | L33: 16.612892 | M33: 15.782247 | O33: 102 | U33: =$O$33 -> 102 | V33: =$O$33 -> 102 | W33: =$O$33 -> 102 | X33: =$O$33 -> 102 | Y33: =$O$33 -> 102 | Z33: =$O$33 -> 102 | AA33: =$O$33 -> 102 | AC33: =$O$33 -> 102 | AD33: =$O$33 -> 102 | AE33: =$O$33 -> 102 | AF33: =$O$33 -> 102 | AG33: =$O$33 -> 102 | AH33: =$O$33 -> 102 | AI33: =$O$33 -> 102 | AJ33: =$O$33 -> 102 | ... AN33: =$O$33 -> 102 | AR33: =IFERROR(AVERAGE(P33:AA33),0) -> 102 | AS33: =IFERROR(AVERAGE(AC33:AN33),0) -> 102 | AT33: =O33 -> 102 | AU33: =AT33 -> 102 | AV33: =AU33 -> 102 | AX33: =P33*(I33*(100%+P$29))+Q33*(I33*(100%+Q$29))+R33*(I33*(100%+R$29))+S33*(I33*(100%+S$29))+T33*(I33*(100%+T$29))+U33*(I33*(100%+U$29))+V33*(I33*(100%+V$29))+W33*(I33*(100%+W$29))+X33*(I33*(100%+X$29))+Y33*(I33*(100%+Y$29))+Z33*(I33*(100%+Z$29))+AA33*(I33*(100%+AA$29)) -> 13690.68 | AY33: =AC33*(J33*(100%+AC$29))+AD33*(J33*(100%+AD$29))+AE33*(J33*(100%+AE$29))+AF33*(J33*(100%+AF$29))+AG33*(J33*(100%+AG$29))+AH33*(J33*(100%+AH$29))+AI33*(J33*(100%+AI$29))+AJ33*(J33*(100%+AJ$29))+AK33*(J33*(100%+AK$29))+AL33*(J33*(100%+AL$29))+AM33*(J33*(100%+AM$29))+AN33*(J33*(100%+AN$29)) -> 22530.947 | AZ33: =K33*AT33*AT$7 -> 21404.4 | BA33: =L33*AU33*AU$7 -> 20334.18 | BB33: =M33*AV33*AV$7 -> 19317.471 | BD33: =SUM(AX33:BB33) -> 97277.676 | BF33: Baseline band is for all OS instances combined RDS Servers are due to be decommissioned but baseline maintained allowing for increased cloud adoption | BG33: 250228 Server CMDB File: Hosting location = "Cloud", ACN Server Function = "LAHS"&"RDS"
C34: Managed operating system (OS) – on premises | D34: OS instance | E34: local | F34: =$F$33 -> normal | I34: 16.918712 | J34: 16.241964 | K34: 15.429866 | L34: 14.658372 | M34: 13.925454 | O34: 22 | U34: =$O$34 -> 22 | V34: =$O$34 -> 22 | W34: =$O$34 -> 22 | X34: =$O$34 -> 22 | Y34: =$O$34 -> 22 | Z34: =$O$34 -> 22 | AA34: =$O$34 -> 22 | AC34: =$O$34 -> 22 | AD34: =$O$34 -> 22 | AE34: =$O$34 -> 22 | AF34: =$O$34 -> 22 | AG34: =$O$34 -> 22 | AH34: =$O$34 -> 22 | AI34: =$O$34 -> 22 | AJ34: =$O$34 -> 22 | ... AN34: =$O$34 -> 22 | AR34: =IFERROR(AVERAGE(P34:AA34),0) -> 22 | AS34: =IFERROR(AVERAGE(AC34:AN34),0) -> 22 | AT34: =O34 -> 22 | AU34: =AT34 -> 22 | AV34: =AU34 -> 22 | AX34: =P34*(I34*(100%+P$29))+Q34*(I34*(100%+Q$29))+R34*(I34*(100%+R$29))+S34*(I34*(100%+S$29))+T34*(I34*(100%+T$29))+U34*(I34*(100%+U$29))+V34*(I34*(100%+V$29))+W34*(I34*(100%+W$29))+X34*(I34*(100%+X$29))+Y34*(I34*(100%+Y$29))+Z34*(I34*(100%+Z$29))+AA34*(I34*(100%+AA$29)) -> 2605.4817 | AY34: =AC34*(J34*(100%+AC$29))+AD34*(J34*(100%+AD$29))+AE34*(J34*(100%+AE$29))+AF34*(J34*(100%+AF$29))+AG34*(J34*(100%+AG$29))+AH34*(J34*(100%+AH$29))+AI34*(J34*(100%+AI$29))+AJ34*(J34*(100%+AJ$29))+AK34*(J34*(100%+AK$29))+AL34*(J34*(100%+AL$29))+AM34*(J34*(100%+AM$29))+AN34*(J34*(100%+AN$29)) -> 4287.8784 | AZ34: =K34*AT34*AT$7 -> 4073.4845 | BA34: =L34*AU34*AU$7 -> 3869.8103 | BB34: =M34*AV34*AV$7 -> 3676.3198 | BD34: =SUM(AX34:BB34) -> 18512.975 | BF34: RDS Servers are due to be decommissioned however difference is minimal so baseline maintained. | BG34: Server CMDB File": Hosting Location = "On-Prem", Is Virtual = "Physical" & "Virtual" ("Yes"&"No"), ACN Server Function = "LAHS"&"RDS"
C35: On-premises server
C36: On-premises server – Service Management | D36: Physical Server | E36: local | F36: wide | I36: 39.269277 | J36: 37.698506 | K36: 35.813581 | L36: 34.022902 | M36: 32.321756 | O36: 55 | U36: =$O$36 -> 55 | V36: =$O$36 -> 55 | W36: =$O$36 -> 55 | X36: =$O$36 -> 55 | Y36: =$O$36 -> 55 | Z36: =$O$36 -> 55 | AA36: =$O$36 -> 55 | AC36: =$O$36 -> 55 | AD36: =$O$36 -> 55 | AE36: =$O$36 -> 55 | AF36: =$O$36 -> 55 | AG36: =$O$36 -> 55 | AH36: =$O$36 -> 55 | AI36: =$O$36 -> 55 | AJ36: =$O$36 -> 55 | ... AN36: =$O$36 -> 55 | AR36: =IFERROR(AVERAGE(P36:AA36),0) -> 55 | AS36: =IFERROR(AVERAGE(AC36:AN36),0) -> 55 | AT36: 30 | AU36: =AT36 -> 30 | AV36: =AU36 -> 30 | AX36: =P36*(I36*(100%+P$29))+Q36*(I36*(100%+Q$29))+R36*(I36*(100%+R$29))+S36*(I36*(100%+S$29))+T36*(I36*(100%+T$29))+U36*(I36*(100%+U$29))+V36*(I36*(100%+V$29))+W36*(I36*(100%+W$29))+X36*(I36*(100%+X$29))+Y36*(I36*(100%+Y$29))+Z36*(I36*(100%+Z$29))+AA36*(I36*(100%+AA$29)) -> 15118.672 | AY36: =AC36*(J36*(100%+AC$29))+AD36*(J36*(100%+AD$29))+AE36*(J36*(100%+AE$29))+AF36*(J36*(100%+AF$29))+AG36*(J36*(100%+AG$29))+AH36*(J36*(100%+AH$29))+AI36*(J36*(100%+AI$29))+AJ36*(J36*(100%+AJ$29))+AK36*(J36*(100%+AK$29))+AL36*(J36*(100%+AL$29))+AM36*(J36*(100%+AM$29))+AN36*(J36*(100%+AN$29)) -> 24881.014 | AZ36: =K36*AT36*AT$7 -> 12892.889 | BA36: =L36*AU36*AU$7 -> 12248.245 | BB36: =M36*AV36*AV$7 -> 11635.832 | BD36: =SUM(AX36:BB36) -> 76776.651 | BF36: Baseline band is for all Physical Servers combined | BG36: 250228 Server CMDB File: Server CMDB File: Hosting Location = "On-Prem", Is Virtual = "Physical" ("No"), ACN Server Function = "LAHS"&"RDS"&"EUS"
C37: On-premises server – Hardware Maintenance | D37: Physical Server | E37: local | F37: wide | I37: 79.099565 | J37: 75.935583 | K37: 72.138804 | L37: 68.531863 | M37: 65.10527 | O37: 55 | U37: =$O$37 -> 55 | V37: =$O$37 -> 55 | W37: =$O$37 -> 55 | X37: =$O$37 -> 55 | Y37: =$O$37 -> 55 | Z37: =$O$37 -> 55 | AA37: =$O$37 -> 55 | AC37: =$O$37 -> 55 | AD37: =$O$37 -> 55 | AE37: =$O$37 -> 55 | AF37: =$O$37 -> 55 | AG37: =$O$37 -> 55 | AH37: =$O$37 -> 55 | AI37: =$O$37 -> 55 | AJ37: =$O$37 -> 55 | ... AN37: =$O$37 -> 55 | AR37: =IFERROR(AVERAGE(P37:AA37),0) -> 55 | AS37: =IFERROR(AVERAGE(AC37:AN37),0) -> 55 | AT37: 30 | AU37: =AT37 -> 30 | AV37: =AU37 -> 30 | AX37: =P37*(I37*(100%+P$29))+Q37*(I37*(100%+Q$29))+R37*(I37*(100%+R$29))+S37*(I37*(100%+S$29))+T37*(I37*(100%+T$29))+U37*(I37*(100%+U$29))+V37*(I37*(100%+V$29))+W37*(I37*(100%+W$29))+X37*(I37*(100%+X$29))+Y37*(I37*(100%+Y$29))+Z37*(I37*(100%+Z$29))+AA37*(I37*(100%+AA$29)) -> 30453.333 | AY37: =AC37*(J37*(100%+AC$29))+AD37*(J37*(100%+AD$29))+AE37*(J37*(100%+AE$29))+AF37*(J37*(100%+AF$29))+AG37*(J37*(100%+AG$29))+AH37*(J37*(100%+AH$29))+AI37*(J37*(100%+AI$29))+AJ37*(J37*(100%+AJ$29))+AK37*(J37*(100%+AK$29))+AL37*(J37*(100%+AL$29))+AM37*(J37*(100%+AM$29))+AN37*(J37*(100%+AN$29)) -> 50117.485 | AZ37: =K37*AT37*AT$7 -> 25969.969 | BA37: =L37*AU37*AU$7 -> 24671.471 | BB37: =M37*AV37*AV$7 -> 23437.897 | BD37: =SUM(AX37:BB37) -> 154650.15 | BF37: Baseline band is for all Physical Servers combined
B39: Operational Technology Services (OTS) | P39: =IF(P$7<$AP$39,percPreTargetAdjustment,0%) -> 0 | Q39: =IF(Q$7<$AP$39,percPreTargetAdjustment,0%) -> 0 | R39: =IF(R$7<$AP$39,percPreTargetAdjustment,0%) -> 0 | S39: =IF(S$7<$AP$39,percPreTargetAdjustment,0%) -> 0 | T39: =IF(T$7<$AP$39,percPreTargetAdjustment,0%) -> 0 | U39: =IF(U$7<$AP$39,percPreTargetAdjustment,0%) -> 0 | V39: =IF(V$7<$AP$39,percPreTargetAdjustment,0%) -> 0 | W39: =IF(W$7<$AP$39,percPreTargetAdjustment,0%) -> 0 | ... AA39: =IF(AA$7<$AP$39,percPreTargetAdjustment,0%) -> 0 | AC39: =IF(AC$7<$AP$39,percPreTargetAdjustment,0%) -> 0 | AD39: =IF(AD$7<$AP$39,percPreTargetAdjustment,0%) -> 0 | AE39: =IF(AE$7<$AP$39,percPreTargetAdjustment,0%) -> 0 | AF39: =IF(AF$7<$AP$39,percPreTargetAdjustment,0%) -> 0 | AG39: =IF(AG$7<$AP$39,percPreTargetAdjustment,0%) -> 0 | AH39: =IF(AH$7<$AP$39,percPreTargetAdjustment,0%) -> 0 | AI39: =IF(AI$7<$AP$39,percPreTargetAdjustment,0%) -> 0 | AJ39: =IF(AJ$7<$AP$39,percPreTargetAdjustment,0%) -> 0 | ... AN39: =IF(AN$7<$AP$39,percPreTargetAdjustment,0%) -> 0 | AX39: =SUMIFS(AX40:AX57,$G40:$G57,"<>Option") -> 659134.54 | AY39: =SUMIFS(AY40:AY57,$G40:$G57,"<>Option") -> 1088781.9 | AZ39: =SUMIFS(AZ40:AZ57,$G40:$G57,"<>Option") -> 1034342.8 | BA39: =SUMIFS(BA40:BA57,$G40:$G57,"<>Option") -> 982625.63 | BB39: =SUMIFS(BB40:BB57,$G40:$G57,"<>Option") -> 933494.34 | BD39: =SUM(AX39:BB39) -> 4698379.1 | BF39: Music3 rollout assumed complete as of 1st of October 2025
C40: Cloud Center of Excellence – OT part | D40: Fixed monthly | E40: central | F40: n/a | I40: 10112.58 | J40: 9708.077 | K40: 9222.6732 | L40: 8761.5395 | M40: 8323.4625 | O40: 1 | U40: =$O$40 -> 1 | V40: =$AT40 -> 1 | W40: =$AT40 -> 1 | X40: =$AT40 -> 1 | Y40: =$AT40 -> 1 | Z40: =$AT40 -> 1 | AA40: =$AT40 -> 1 | AC40: =$AT40 -> 1 | AD40: =$AT40 -> 1 | AE40: =$AT40 -> 1 | AF40: =$AT40 -> 1 | AG40: =$AT40 -> 1 | AH40: =$AT40 -> 1 | AI40: =$AT40 -> 1 | AJ40: =$AT40 -> 1 | ... AN40: =$AT40 -> 1 | AR40: =IFERROR(AVERAGE(P40:AA40),0) -> 1 | AS40: =IFERROR(AVERAGE(AC40:AN40),0) -> 1 | AT40: =O40 -> 1 | AU40: =AT40 -> 1 | AV40: =AU40 -> 1 | AX40: =P40*(I40*(100%+P$39))+Q40*(I40*(100%+Q$39))+R40*(I40*(100%+R$39))+S40*(I40*(100%+S$39))+T40*(I40*(100%+T$39))+U40*(I40*(100%+U$39))+V40*(I40*(100%+V$39))+W40*(I40*(100%+W$39))+X40*(I40*(100%+X$39))+Y40*(I40*(100%+Y$39))+Z40*(I40*(100%+Z$39))+AA40*(I40*(100%+AA$39)) -> 70788.062 | AY40: =AC40*(J40*(100%+AC$39))+AD40*(J40*(100%+AD$39))+AE40*(J40*(100%+AE$39))+AF40*(J40*(100%+AF$39))+AG40*(J40*(100%+AG$39))+AH40*(J40*(100%+AH$39))+AI40*(J40*(100%+AI$39))+AJ40*(J40*(100%+AJ$39))+AK40*(J40*(100%+AK$39))+AL40*(J40*(100%+AL$39))+AM40*(J40*(100%+AM$39))+AN40*(J40*(100%+AN$39)) -> 116496.92 | AZ40: =K40*AT40*AT$7 -> 110672.08 | BA40: =L40*AU40*AU$7 -> 105138.47 | BB40: =M40*AV40*AV$7 -> 99881.55 | BD40: =SUM(AX40:BB40) -> 502977.09
C41: =C31 -> Workload management
C42: =C32 -> Managed database non-PaaS | D42: =D32 -> Database Instance | E42: =E32 -> local | F42: wide | I42: =I32 -> 18.58313 | J42: =J32 -> 17.839805 | K42: =K32 -> 16.947815 | L42: =L32 -> 16.100424 | M42: =M32 -> 15.295403 | O42: 86 | U42: =$O$42 -> 86 | V42: =$AT42 -> 101 | W42: =$AT42 -> 101 | X42: =$AT42 -> 101 | Y42: =$AT42 -> 101 | Z42: =$AT42 -> 101 | AA42: =$AT42 -> 101 | AC42: =$AT42 -> 101 | AD42: =$AT42 -> 101 | AE42: =$AT42 -> 101 | AF42: =$AT42 -> 101 | AG42: =$AT42 -> 101 | AH42: =$AT42 -> 101 | AI42: =$AT42 -> 101 | AJ42: =$AT42 -> 101 | ... AN42: =$AT42 -> 101 | AR42: =IFERROR(AVERAGE(P42:AA42),0) -> 98.857143 | AS42: =IFERROR(AVERAGE(AC42:AN42),0) -> 101 | AT42: =O42+15 -> 101 | AU42: =AT42 -> 101 | AV42: =AU42 -> 101 | AX42: =P42*(I42*(100%+P$29))+Q42*(I42*(100%+Q$29))+R42*(I42*(100%+R$29))+S42*(I42*(100%+S$29))+T42*(I42*(100%+T$29))+U42*(I42*(100%+U$29))+V42*(I42*(100%+V$29))+W42*(I42*(100%+W$29))+X42*(I42*(100%+X$29))+Y42*(I42*(100%+Y$29))+Z42*(I42*(100%+Z$29))+AA42*(I42*(100%+AA$29)) -> 12859.526 | AY42: =AC42*(J42*(100%+AC$29))+AD42*(J42*(100%+AD$29))+AE42*(J42*(100%+AE$29))+AF42*(J42*(100%+AF$29))+AG42*(J42*(100%+AG$29))+AH42*(J42*(100%+AH$29))+AI42*(J42*(100%+AI$29))+AJ42*(J42*(100%+AJ$29))+AK42*(J42*(100%+AK$29))+AL42*(J42*(100%+AL$29))+AM42*(J42*(100%+AM$29))+AN42*(J42*(100%+AN$29)) -> 21621.844 | AZ42: =K42*AT42*AT$7 -> 20540.752 | BA42: =L42*AU42*AU$7 -> 19513.714 | BB42: =M42*AV42*AV$7 -> 18538.028 | BD42: =SUM(AX42:BB42) -> 93073.865 | BF42: common for OTS workloads: Yr3 forecast based on MUSIC3: +15 assumed based on OT app servers listed in Managed operationing System (OS) - on premises. | BG42: Database CMDB File: Infra type "OT" Music3 is an ongoing OT Cyber Security project. The changes in volumes + & - will be introduced in phases between now and the end of September 2025 which is the current planned completion date of the project.
C43: =C33 -> Managed operating system (OS) – in Azure | D43: =D33 -> OS instance | E43: =E33 -> local | F43: =$F$33 -> normal | I43: =I33 -> 19.174621 | J43: =J33 -> 18.407636 | K43: =K33 -> 17.487255 | L43: =L33 -> 16.612892 | M43: =M33 -> 15.782247 | O43: 115 | U43: =$O$43 -> 115 | V43: =$AT43 -> 115 | W43: =$AT43 -> 115 | X43: =$AT43 -> 115 | Y43: =$AT43 -> 115 | Z43: =$AT43 -> 115 | AA43: =$AT43 -> 115 | AC43: =$AT43 -> 115 | AD43: =$AT43 -> 115 | AE43: =$AT43 -> 115 | AF43: =$AT43 -> 115 | AG43: =$AT43 -> 115 | AH43: =$AT43 -> 115 | AI43: =$AT43 -> 115 | AJ43: =$AT43 -> 115 | ... AN43: =$AT43 -> 115 | AR43: =IFERROR(AVERAGE(P43:AA43),0) -> 115 | AS43: =IFERROR(AVERAGE(AC43:AN43),0) -> 115 | AT43: =O43 -> 115 | AU43: =AT43 -> 115 | AV43: =AU43 -> 115 | AX43: =P43*(I43*(100%+P$29))+Q43*(I43*(100%+Q$29))+R43*(I43*(100%+R$29))+S43*(I43*(100%+S$29))+T43*(I43*(100%+T$29))+U43*(I43*(100%+U$29))+V43*(I43*(100%+V$29))+W43*(I43*(100%+W$29))+X43*(I43*(100%+X$29))+Y43*(I43*(100%+Y$29))+Z43*(I43*(100%+Z$29))+AA43*(I43*(100%+AA$29)) -> 15435.57 | AY43: =AC43*(J43*(100%+AC$29))+AD43*(J43*(100%+AD$29))+AE43*(J43*(100%+AE$29))+AF43*(J43*(100%+AF$29))+AG43*(J43*(100%+AG$29))+AH43*(J43*(100%+AH$29))+AI43*(J43*(100%+AI$29))+AJ43*(J43*(100%+AJ$29))+AK43*(J43*(100%+AK$29))+AL43*(J43*(100%+AL$29))+AM43*(J43*(100%+AM$29))+AN43*(J43*(100%+AN$29)) -> 25402.538 | AZ43: =K43*AT43*AT$7 -> 24132.411 | BA43: =L43*AU43*AU$7 -> 22925.791 | BB43: =M43*AV43*AV$7 -> 21779.501 | BD43: =SUM(AX43:BB43) -> 109675.81 | BF43: Baseline band is for all OS instances combined Compared to values from azure reporting there is a discrepancy of 18 servers. Azure values used, discrepancy to be investigated by JDE Assumptions for volume increase vs CMDB driving by Music3 program are in the 250228Server CMDB File | BG43: 250228Server CMDB File: Hosting Location = "Cloud", ACN Server Function = "MU-LAHS" &"MU-RAS"
C44: =C34 -> Managed operating system (OS) – on premises | D44: =D34 -> OS instance | E44: =E34 -> local | F44: =$F$33 -> normal | I44: =I34 -> 16.918712 | J44: =J34 -> 16.241964 | K44: =K34 -> 15.429866 | L44: =L34 -> 14.658372 | M44: =M34 -> 13.925454 | O44: 789 | U44: =$O$44 -> 789 | V44: =$AT44 -> 789 | W44: =$AT44 -> 789 | X44: =$AT44 -> 789 | Y44: =$AT44 -> 789 | Z44: =$AT44 -> 789 | AA44: =$AT44 -> 789 | AC44: =$AT44 -> 789 | AD44: =$AT44 -> 789 | AE44: =$AT44 -> 789 | AF44: =$AT44 -> 789 | AG44: =$AT44 -> 789 | AH44: =$AT44 -> 789 | AI44: =$AT44 -> 789 | AJ44: =$AT44 -> 789 | ... AN44: =$AT44 -> 789 | AR44: =IFERROR(AVERAGE(P44:AA44),0) -> 789 | AS44: =IFERROR(AVERAGE(AC44:AN44),0) -> 789 | AT44: 789 | AU44: =AT44 -> 789 | AV44: =AU44 -> 789 | AX44: =P44*(I44*(100%+P$29))+Q44*(I44*(100%+Q$29))+R44*(I44*(100%+R$29))+S44*(I44*(100%+S$29))+T44*(I44*(100%+T$29))+U44*(I44*(100%+U$29))+V44*(I44*(100%+V$29))+W44*(I44*(100%+W$29))+X44*(I44*(100%+X$29))+Y44*(I44*(100%+Y$29))+Z44*(I44*(100%+Z$29))+AA44*(I44*(100%+AA$29)) -> 93442.048 | AY44: =AC44*(J44*(100%+AC$29))+AD44*(J44*(100%+AD$29))+AE44*(J44*(100%+AE$29))+AF44*(J44*(100%+AF$29))+AG44*(J44*(100%+AG$29))+AH44*(J44*(100%+AH$29))+AI44*(J44*(100%+AI$29))+AJ44*(J44*(100%+AJ$29))+AK44*(J44*(100%+AK$29))+AL44*(J44*(100%+AL$29))+AM44*(J44*(100%+AM$29))+AN44*(J44*(100%+AN$29)) -> 153778.91 | AZ44: =K44*AT44*AT$7 -> 146089.97 | BA44: =L44*AU44*AU$7 -> 138785.47 | BB44: =M44*AV44*AV$7 -> 131846.2 | BD44: =SUM(AX44:BB44) -> 663942.59 | BF44: Assumptions for volume increase vs CMDB driving by Music3 program are in the 250228Server CMDB File | BG44: 250228Server CMDB File: Hosting Location = "On-Prem", Is Virtual = "Virtual"&"Physical" ("Yes"& "No"), ACN Server Function = "MU-LAHS"&"MU-RAS"
C45: =C35 -> On-premises server
C46: =C36 -> On-premises server – Service Management | D46: =D36 -> Physical Server | E46: =E36 -> local | F46: =F36 -> wide | I46: =I36 -> 39.269277 | J46: =J36 -> 37.698506 | K46: =K36 -> 35.813581 | L46: =L36 -> 34.022902 | M46: =M36 -> 32.321756 | O46: 158 | U46: =$O$46 -> 158 | V46: =$AT46 -> 158 | W46: =$AT46 -> 158 | X46: =$AT46 -> 158 | Y46: =$AT46 -> 158 | Z46: =$AT46 -> 158 | AA46: =$AT46 -> 158 | AC46: =$AT46 -> 158 | AD46: =$AT46 -> 158 | AE46: =$AT46 -> 158 | AF46: =$AT46 -> 158 | AG46: =$AT46 -> 158 | AH46: =$AT46 -> 158 | AI46: =$AT46 -> 158 | AJ46: =$AT46 -> 158 | ... AN46: =$AT46 -> 158 | AR46: =IFERROR(AVERAGE(P46:AA46),0) -> 158 | AS46: =IFERROR(AVERAGE(AC46:AN46),0) -> 158 | AT46: 158 | AU46: =AT46 -> 158 | AV46: =AU46 -> 158 | AX46: =P46*(I46*(100%+P$29))+Q46*(I46*(100%+Q$29))+R46*(I46*(100%+R$29))+S46*(I46*(100%+S$29))+T46*(I46*(100%+T$29))+U46*(I46*(100%+U$29))+V46*(I46*(100%+V$29))+W46*(I46*(100%+W$29))+X46*(I46*(100%+X$29))+Y46*(I46*(100%+Y$29))+Z46*(I46*(100%+Z$29))+AA46*(I46*(100%+AA$29)) -> 43431.82 | AY46: =AC46*(J46*(100%+AC$29))+AD46*(J46*(100%+AD$29))+AE46*(J46*(100%+AE$29))+AF46*(J46*(100%+AF$29))+AG46*(J46*(100%+AG$29))+AH46*(J46*(100%+AH$29))+AI46*(J46*(100%+AI$29))+AJ46*(J46*(100%+AJ$29))+AK46*(J46*(100%+AK$29))+AL46*(J46*(100%+AL$29))+AM46*(J46*(100%+AM$29))+AN46*(J46*(100%+AN$29)) -> 71476.367 | AZ46: =K46*AT46*AT$7 -> 67902.549 | BA46: =L46*AU46*AU$7 -> 64507.421 | BB46: =M46*AV46*AV$7 -> 61282.05 | BD46: =SUM(AX46:BB46) -> 308600.21 | BF46: Baseline band is for all Physical Servers combined For Yr1 forecast increased from current based on Music3 Completion: Details in 250228 Server CMDB File | BG46: 250228Server CMDB File: Hosting Location = "On-Prem", Is Virtual = "Physical" ("No"), ACN Server Function = "MU-LAHS"
C47: =C37 -> On-premises server – Hardware Maintenance | D47: =D37 -> Physical Server | E47: =E37 -> local | F47: =F37 -> wide | I47: =I37 -> 79.099565 | J47: =J37 -> 75.935583 | K47: =K37 -> 72.138804 | L47: =L37 -> 68.531863 | M47: =M37 -> 65.10527 | O47: 158 | U47: =$O$47 -> 158 | V47: =$AT47 -> 158 | W47: =$AT47 -> 158 | X47: =$AT47 -> 158 | Y47: =$AT47 -> 158 | Z47: =$AT47 -> 158 | AA47: =$AT47 -> 158 | AC47: =$AT47 -> 158 | AD47: =$AT47 -> 158 | AE47: =$AT47 -> 158 | AF47: =$AT47 -> 158 | AG47: =$AT47 -> 158 | AH47: =$AT47 -> 158 | AI47: =$AT47 -> 158 | AJ47: =$AT47 -> 158 | ... AN47: =$AT47 -> 158 | AR47: =IFERROR(AVERAGE(P47:AA47),0) -> 158 | AS47: =IFERROR(AVERAGE(AC47:AN47),0) -> 158 | AT47: 158 | AU47: =AT47 -> 158 | AV47: =AU47 -> 158 | AX47: =P47*(I47*(100%+P$29))+Q47*(I47*(100%+Q$29))+R47*(I47*(100%+R$29))+S47*(I47*(100%+S$29))+T47*(I47*(100%+T$29))+U47*(I47*(100%+U$29))+V47*(I47*(100%+V$29))+W47*(I47*(100%+W$29))+X47*(I47*(100%+X$29))+Y47*(I47*(100%+Y$29))+Z47*(I47*(100%+Z$29))+AA47*(I47*(100%+AA$29)) -> 87484.119 | AY47: =AC47*(J47*(100%+AC$29))+AD47*(J47*(100%+AD$29))+AE47*(J47*(100%+AE$29))+AF47*(J47*(100%+AF$29))+AG47*(J47*(100%+AG$29))+AH47*(J47*(100%+AH$29))+AI47*(J47*(100%+AI$29))+AJ47*(J47*(100%+AJ$29))+AK47*(J47*(100%+AK$29))+AL47*(J47*(100%+AL$29))+AM47*(J47*(100%+AM$29))+AN47*(J47*(100%+AN$29)) -> 143973.86 | AZ47: =K47*AT47*AT$7 -> 136775.17 | BA47: =L47*AU47*AU$7 -> 129936.41 | BB47: =M47*AV47*AV$7 -> 123439.59 | BD47: =SUM(AX47:BB47) -> 621609.16 | BF47: Baseline band is for all Physical Servers combined
C48: OT-specific Services
C49: Factory OT services | D49: Factory | E49: local | F49: n/a | I49: 974.68793 | J49: 935.70042 | K49: 888.91539 | L49: 844.46963 | M49: 802.24614 | O49: 20 | U49: =$O$49 -> 20 | V49: =$AT49 -> 20 | W49: =$AT49 -> 20 | X49: =$AT49 -> 20 | Y49: =$AT49 -> 20 | Z49: =$AT49 -> 20 | AA49: =$AT49 -> 20 | AC49: =$AT49 -> 20 | AD49: =$AT49 -> 20 | AE49: =$AT49 -> 20 | AF49: =$AT49 -> 20 | AG49: =$AT49 -> 20 | AH49: =$AT49 -> 20 | AI49: =$AT49 -> 20 | AJ49: =$AT49 -> 20 | ... AN49: =$AT49 -> 20 | AR49: =IFERROR(AVERAGE(P49:AA49),0) -> 20 | AS49: =IFERROR(AVERAGE(AC49:AN49),0) -> 20 | AT49: =O49 -> 20 | AU49: =AT49 -> 20 | AV49: =AU49 -> 20 | AX49: =P49*(I49*(100%+P$39))+Q49*(I49*(100%+Q$39))+R49*(I49*(100%+R$39))+S49*(I49*(100%+S$39))+T49*(I49*(100%+T$39))+U49*(I49*(100%+U$39))+V49*(I49*(100%+V$39))+W49*(I49*(100%+W$39))+X49*(I49*(100%+X$39))+Y49*(I49*(100%+Y$39))+Z49*(I49*(100%+Z$39))+AA49*(I49*(100%+AA$39)) -> 136456.31 | AY49: =AC49*(J49*(100%+AC$39))+AD49*(J49*(100%+AD$39))+AE49*(J49*(100%+AE$39))+AF49*(J49*(100%+AF$39))+AG49*(J49*(100%+AG$39))+AH49*(J49*(100%+AH$39))+AI49*(J49*(100%+AI$39))+AJ49*(J49*(100%+AJ$39))+AK49*(J49*(100%+AK$39))+AL49*(J49*(100%+AL$39))+AM49*(J49*(100%+AM$39))+AN49*(J49*(100%+AN$39)) -> 224568.1 | AZ49: =K49*AT49*AT$7 -> 213339.69 | BA49: =L49*AU49*AU$7 -> 202672.71 | BB49: =M49*AV49*AV$7 -> 192539.07 | BD49: =SUM(AX49:BB49) -> 969575.89 | BG49: 1 AD per factory in MUSIC3 scope.
C50: Claroty OT security | D50: Sensor | E50: local | F50: normal | I50: 31.771338 | J50: 30.500484 | K50: 28.97546 | L50: 27.526687 | M50: 26.150353 | O50: 187 | U50: =$O$50 -> 187 | V50: =$AT50 -> 200 | W50: =$AT50 -> 200 | X50: =$AT50 -> 200 | Y50: =$AT50 -> 200 | Z50: =$AT50 -> 200 | AA50: =$AT50 -> 200 | AC50: =$AT50 -> 200 | AD50: =$AT50 -> 200 | AE50: =$AT50 -> 200 | AF50: =$AT50 -> 200 | AG50: =$AT50 -> 200 | AH50: =$AT50 -> 200 | AI50: =$AT50 -> 200 | AJ50: =$AT50 -> 200 | ... AN50: =$AT50 -> 200 | AR50: =IFERROR(AVERAGE(P50:AA50),0) -> 198.14286 | AS50: =IFERROR(AVERAGE(AC50:AN50),0) -> 200 | AT50: 200 | AU50: 200 | AV50: =AU50 -> 200 | AX50: =P50*(I50*(100%+P$39))+Q50*(I50*(100%+Q$39))+R50*(I50*(100%+R$39))+S50*(I50*(100%+S$39))+T50*(I50*(100%+T$39))+U50*(I50*(100%+U$39))+V50*(I50*(100%+V$39))+W50*(I50*(100%+W$39))+X50*(I50*(100%+X$39))+Y50*(I50*(100%+Y$39))+Z50*(I50*(100%+Z$39))+AA50*(I50*(100%+AA$39)) -> 44066.846 | AY50: =AC50*(J50*(100%+AC$39))+AD50*(J50*(100%+AD$39))+AE50*(J50*(100%+AE$39))+AF50*(J50*(100%+AF$39))+AG50*(J50*(100%+AG$39))+AH50*(J50*(100%+AH$39))+AI50*(J50*(100%+AI$39))+AJ50*(J50*(100%+AJ$39))+AK50*(J50*(100%+AK$39))+AL50*(J50*(100%+AL$39))+AM50*(J50*(100%+AM$39))+AN50*(J50*(100%+AN$39)) -> 73201.163 | AZ50: =K50*AT50*AT$7 -> 69541.105 | BA50: =L50*AU50*AU$7 -> 66064.049 | BB50: =M50*AV50*AV$7 -> 62760.847 | BD50: =SUM(AX50:BB50) -> 315634.01 | BG50: Server CMDB File: Server Function "MUOTMON"
C51: Remote Access | D51: Fixed monthly | E51: central | F51: n/a | I51: 3835.6678 | J51: 3682.2411 | K51: 3498.129 | L51: 3323.2226 | M51: 3157.0615 | O51: 1 | U51: =$O$51 -> 1 | V51: =$AT51 -> 1 | W51: =$AT51 -> 1 | X51: =$AT51 -> 1 | Y51: =$AT51 -> 1 | Z51: =$AT51 -> 1 | AA51: =$AT51 -> 1 | AC51: =$AT51 -> 1 | AD51: =$AT51 -> 1 | AE51: =$AT51 -> 1 | AF51: =$AT51 -> 1 | AG51: =$AT51 -> 1 | AH51: =$AT51 -> 1 | AI51: =$AT51 -> 1 | AJ51: =$AT51 -> 1 | ... AN51: =$AT51 -> 1 | AR51: =IFERROR(AVERAGE(P51:AA51),0) -> 1 | AS51: =IFERROR(AVERAGE(AC51:AN51),0) -> 1 | AT51: =O51 -> 1 | AU51: =AT51 -> 1 | AV51: =AU51 -> 1 | AX51: =P51*(I51*(100%+P$39))+Q51*(I51*(100%+Q$39))+R51*(I51*(100%+R$39))+S51*(I51*(100%+S$39))+T51*(I51*(100%+T$39))+U51*(I51*(100%+U$39))+V51*(I51*(100%+V$39))+W51*(I51*(100%+W$39))+X51*(I51*(100%+X$39))+Y51*(I51*(100%+Y$39))+Z51*(I51*(100%+Z$39))+AA51*(I51*(100%+AA$39)) -> 26849.675 | AY51: =AC51*(J51*(100%+AC$39))+AD51*(J51*(100%+AD$39))+AE51*(J51*(100%+AE$39))+AF51*(J51*(100%+AF$39))+AG51*(J51*(100%+AG$39))+AH51*(J51*(100%+AH$39))+AI51*(J51*(100%+AI$39))+AJ51*(J51*(100%+AJ$39))+AK51*(J51*(100%+AK$39))+AL51*(J51*(100%+AL$39))+AM51*(J51*(100%+AM$39))+AN51*(J51*(100%+AN$39)) -> 44186.893 | AZ51: =K51*AT51*AT$7 -> 41977.548 | BA51: =L51*AU51*AU$7 -> 39878.671 | BB51: =M51*AV51*AV$7 -> 37884.737 | BD51: =SUM(AX51:BB51) -> 190777.52
C52: Public Key Infrastructure | D52: Fixed monthly | E52: central | F52: n/a | I52: 4588.3341 | J52: 4404.8008 | K52: 4184.5607 | L52: 3975.3327 | M52: 3776.566 | O52: 1 | U52: =$O$52 -> 1 | V52: =$AT52 -> 1 | W52: =$AT52 -> 1 | X52: =$AT52 -> 1 | Y52: =$AT52 -> 1 | Z52: =$AT52 -> 1 | AA52: =$AT52 -> 1 | AC52: =$AT52 -> 1 | AD52: =$AT52 -> 1 | AE52: =$AT52 -> 1 | AF52: =$AT52 -> 1 | AG52: =$AT52 -> 1 | AH52: =$AT52 -> 1 | AI52: =$AT52 -> 1 | AJ52: =$AT52 -> 1 | ... AN52: =$AT52 -> 1 | AR52: =IFERROR(AVERAGE(P52:AA52),0) -> 1 | AS52: =IFERROR(AVERAGE(AC52:AN52),0) -> 1 | AT52: =O52 -> 1 | AU52: =AT52 -> 1 | AV52: =AU52 -> 1 | AX52: =P52*(I52*(100%+P$39))+Q52*(I52*(100%+Q$39))+R52*(I52*(100%+R$39))+S52*(I52*(100%+S$39))+T52*(I52*(100%+T$39))+U52*(I52*(100%+U$39))+V52*(I52*(100%+V$39))+W52*(I52*(100%+W$39))+X52*(I52*(100%+X$39))+Y52*(I52*(100%+Y$39))+Z52*(I52*(100%+Z$39))+AA52*(I52*(100%+AA$39)) -> 32118.339 | AY52: =AC52*(J52*(100%+AC$39))+AD52*(J52*(100%+AD$39))+AE52*(J52*(100%+AE$39))+AF52*(J52*(100%+AF$39))+AG52*(J52*(100%+AG$39))+AH52*(J52*(100%+AH$39))+AI52*(J52*(100%+AI$39))+AJ52*(J52*(100%+AJ$39))+AK52*(J52*(100%+AK$39))+AL52*(J52*(100%+AL$39))+AM52*(J52*(100%+AM$39))+AN52*(J52*(100%+AN$39)) -> 52857.609 | AZ52: =K52*AT52*AT$7 -> 50214.729 | BA52: =L52*AU52*AU$7 -> 47703.992 | BB52: =M52*AV52*AV$7 -> 45318.793 | BD52: =SUM(AX52:BB52) -> 228213.46
C53: Endpoint Protection Services | D53: Fixed monthly | E53: central | F53: n/a | I53: 1694.4029 | J53: 1626.6268 | K53: 1545.2954 | L53: 1468.0306 | M53: 1394.6291 | O53: 1 | U53: =$O$53 -> 1 | V53: =$AT53 -> 1 | W53: =$AT53 -> 1 | X53: =$AT53 -> 1 | Y53: =$AT53 -> 1 | Z53: =$AT53 -> 1 | AA53: =$AT53 -> 1 | AC53: =$AT53 -> 1 | AD53: =$AT53 -> 1 | AE53: =$AT53 -> 1 | AF53: =$AT53 -> 1 | AG53: =$AT53 -> 1 | AH53: =$AT53 -> 1 | AI53: =$AT53 -> 1 | AJ53: =$AT53 -> 1 | ... AN53: =$AT53 -> 1 | AR53: =IFERROR(AVERAGE(P53:AA53),0) -> 1 | AS53: =IFERROR(AVERAGE(AC53:AN53),0) -> 1 | AT53: =O53 -> 1 | AU53: =AT53 -> 1 | AV53: =AU53 -> 1 | AX53: =P53*(I53*(100%+P$39))+Q53*(I53*(100%+Q$39))+R53*(I53*(100%+R$39))+S53*(I53*(100%+S$39))+T53*(I53*(100%+T$39))+U53*(I53*(100%+U$39))+V53*(I53*(100%+V$39))+W53*(I53*(100%+W$39))+X53*(I53*(100%+X$39))+Y53*(I53*(100%+Y$39))+Z53*(I53*(100%+Z$39))+AA53*(I53*(100%+AA$39)) -> 11860.82 | AY53: =AC53*(J53*(100%+AC$39))+AD53*(J53*(100%+AD$39))+AE53*(J53*(100%+AE$39))+AF53*(J53*(100%+AF$39))+AG53*(J53*(100%+AG$39))+AH53*(J53*(100%+AH$39))+AI53*(J53*(100%+AI$39))+AJ53*(J53*(100%+AJ$39))+AK53*(J53*(100%+AK$39))+AL53*(J53*(100%+AL$39))+AM53*(J53*(100%+AM$39))+AN53*(J53*(100%+AN$39)) -> 19519.521 | AZ53: =K53*AT53*AT$7 -> 18543.545 | BA53: =L53*AU53*AU$7 -> 17616.368 | BB53: =M53*AV53*AV$7 -> 16735.549 | BD53: =SUM(AX53:BB53) -> 84275.803
C54: Security Integration Services – OT part | D54: Fixed monthly | E54: central | F54: n/a | I54: 562.96257 | J54: 540.44407 | K54: 513.42187 | L54: 487.75077 | M54: 463.36323 | O54: 1 | U54: =$O$54 -> 1 | V54: =$AT54 -> 1 | W54: =$AT54 -> 1 | X54: =$AT54 -> 1 | Y54: =$AT54 -> 1 | Z54: =$AT54 -> 1 | AA54: =$AT54 -> 1 | AC54: =$AT54 -> 1 | AD54: =$AT54 -> 1 | AE54: =$AT54 -> 1 | AF54: =$AT54 -> 1 | AG54: =$AT54 -> 1 | AH54: =$AT54 -> 1 | AI54: =$AT54 -> 1 | AJ54: =$AT54 -> 1 | ... AN54: =$AT54 -> 1 | AR54: =IFERROR(AVERAGE(P54:AA54),0) -> 1 | AS54: =IFERROR(AVERAGE(AC54:AN54),0) -> 1 | AT54: =O54 -> 1 | AU54: =AT54 -> 1 | AV54: =AU54 -> 1 | AX54: =P54*(I54*(100%+P$39))+Q54*(I54*(100%+Q$39))+R54*(I54*(100%+R$39))+S54*(I54*(100%+S$39))+T54*(I54*(100%+T$39))+U54*(I54*(100%+U$39))+V54*(I54*(100%+V$39))+W54*(I54*(100%+W$39))+X54*(I54*(100%+X$39))+Y54*(I54*(100%+Y$39))+Z54*(I54*(100%+Z$39))+AA54*(I54*(100%+AA$39)) -> 3940.738 | AY54: =AC54*(J54*(100%+AC$39))+AD54*(J54*(100%+AD$39))+AE54*(J54*(100%+AE$39))+AF54*(J54*(100%+AF$39))+AG54*(J54*(100%+AG$39))+AH54*(J54*(100%+AH$39))+AI54*(J54*(100%+AI$39))+AJ54*(J54*(100%+AJ$39))+AK54*(J54*(100%+AK$39))+AL54*(J54*(100%+AL$39))+AM54*(J54*(100%+AM$39))+AN54*(J54*(100%+AN$39)) -> 6485.3288 | AZ54: =K54*AT54*AT$7 -> 6161.0624 | BA54: =L54*AU54*AU$7 -> 5853.0093 | BB54: =M54*AV54*AV$7 -> 5560.3588 | BD54: =SUM(AX54:BB54) -> 28000.497
C55: Security Operation Center – OT part | D55: Fixed monthly | E55: central | F55: n/a | I55: 9977.3362 | J55: 9578.2427 | K55: 9099.3306 | L55: 8644.3641 | M55: 8212.1458 | O55: 1 | U55: =$O$55 -> 1 | V55: =$AT55 -> 1 | W55: =$AT55 -> 1 | X55: =$AT55 -> 1 | Y55: =$AT55 -> 1 | Z55: =$AT55 -> 1 | AA55: =$AT55 -> 1 | AC55: =$AT55 -> 1 | AD55: =$AT55 -> 1 | AE55: =$AT55 -> 1 | AF55: =$AT55 -> 1 | AG55: =$AT55 -> 1 | AH55: =$AT55 -> 1 | AI55: =$AT55 -> 1 | AJ55: =$AT55 -> 1 | ... AN55: =$AT55 -> 1 | AR55: =IFERROR(AVERAGE(P55:AA55),0) -> 1 | AS55: =IFERROR(AVERAGE(AC55:AN55),0) -> 1 | AT55: =O55 -> 1 | AU55: =AT55 -> 1 | AV55: =AU55 -> 1 | AX55: =P55*(I55*(100%+P$39))+Q55*(I55*(100%+Q$39))+R55*(I55*(100%+R$39))+S55*(I55*(100%+S$39))+T55*(I55*(100%+T$39))+U55*(I55*(100%+U$39))+V55*(I55*(100%+V$39))+W55*(I55*(100%+W$39))+X55*(I55*(100%+X$39))+Y55*(I55*(100%+Y$39))+Z55*(I55*(100%+Z$39))+AA55*(I55*(100%+AA$39)) -> 69841.353 | AY55: =AC55*(J55*(100%+AC$39))+AD55*(J55*(100%+AD$39))+AE55*(J55*(100%+AE$39))+AF55*(J55*(100%+AF$39))+AG55*(J55*(100%+AG$39))+AH55*(J55*(100%+AH$39))+AI55*(J55*(100%+AI$39))+AJ55*(J55*(100%+AJ$39))+AK55*(J55*(100%+AK$39))+AL55*(J55*(100%+AL$39))+AM55*(J55*(100%+AM$39))+AN55*(J55*(100%+AN$39)) -> 114938.91 | AZ55: =K55*AT55*AT$7 -> 109191.97 | BA55: =L55*AU55*AU$7 -> 103732.37 | BB55: =M55*AV55*AV$7 -> 98545.75 | BD55: =SUM(AX55:BB55) -> 496250.35
C56: Backup and Recovery for non-Supplier-managed systems | D56: OS instance | E56: local | F56: n/a | I56: 4.3997131 | J56: 4.2237246 | K56: 4.0125384 | L56: 3.8119114 | M56: 3.6213159 | U56: =$O$56 -> 0 | V56: =$AT56 -> 400 | W56: =$AT56 -> 400 | X56: =$AT56 -> 400 | Y56: =$AT56 -> 400 | Z56: =$AT56 -> 400 | AA56: =$AT56 -> 400 | AC56: =$AT56 -> 400 | AD56: =$AT56 -> 400 | AE56: =$AT56 -> 400 | AF56: =$AT56 -> 400 | AG56: =$AT56 -> 400 | AH56: =$AT56 -> 400 | AI56: =$AT56 -> 400 | AJ56: =$AT56 -> 400 | ... AN56: =$AT56 -> 400 | AR56: =IFERROR(AVERAGE(P56:AA56),0) -> 342.85714 | AS56: =IFERROR(AVERAGE(AC56:AN56),0) -> 400 | AT56: =AT49*20 -> 400 | AU56: =AT56 -> 400 | AV56: =AU56 -> 400 | AX56: =P56*(I56*(100%+P$39))+Q56*(I56*(100%+Q$39))+R56*(I56*(100%+R$39))+S56*(I56*(100%+S$39))+T56*(I56*(100%+T$39))+U56*(I56*(100%+U$39))+V56*(I56*(100%+V$39))+W56*(I56*(100%+W$39))+X56*(I56*(100%+X$39))+Y56*(I56*(100%+Y$39))+Z56*(I56*(100%+Z$39))+AA56*(I56*(100%+AA$39)) -> 10559.311 | AY56: =AC56*(J56*(100%+AC$39))+AD56*(J56*(100%+AD$39))+AE56*(J56*(100%+AE$39))+AF56*(J56*(100%+AF$39))+AG56*(J56*(100%+AG$39))+AH56*(J56*(100%+AH$39))+AI56*(J56*(100%+AI$39))+AJ56*(J56*(100%+AJ$39))+AK56*(J56*(100%+AK$39))+AL56*(J56*(100%+AL$39))+AM56*(J56*(100%+AM$39))+AN56*(J56*(100%+AN$39)) -> 20273.878 | AZ56: =K56*AT56*AT$7 -> 19260.184 | BA56: =L56*AU56*AU$7 -> 18297.175 | BB56: =M56*AV56*AV$7 -> 17382.316 | BD56: =SUM(AX56:BB56) -> 85772.865 | BG56: Approximately 20 engineering stations per factory
B58: Security Services (SEC) | P58: =IF(P$7<$AP$58,percPreTargetAdjustment,0%) -> 0 | Q58: =IF(Q$7<$AP$58,percPreTargetAdjustment,0%) -> 0 | R58: =IF(R$7<$AP$58,percPreTargetAdjustment,0%) -> 0 | S58: =IF(S$7<$AP$58,percPreTargetAdjustment,0%) -> 0 | T58: =IF(T$7<$AP$58,percPreTargetAdjustment,0%) -> 0 | U58: =IF(U$7<$AP$58,percPreTargetAdjustment,0%) -> 0 | V58: =IF(V$7<$AP$58,percPreTargetAdjustment,0%) -> 0 | W58: =IF(W$7<$AP$58,percPreTargetAdjustment,0%) -> 0 | ... AA58: =IF(AA$7<$AP$58,percPreTargetAdjustment,0%) -> 0 | AC58: =IF(AC$7<$AP$58,percPreTargetAdjustment,0%) -> 0 | AD58: =IF(AD$7<$AP$58,percPreTargetAdjustment,0%) -> 0 | AE58: =IF(AE$7<$AP$58,percPreTargetAdjustment,0%) -> 0 | AF58: =IF(AF$7<$AP$58,percPreTargetAdjustment,0%) -> 0 | AG58: =IF(AG$7<$AP$58,percPreTargetAdjustment,0%) -> 0 | AH58: =IF(AH$7<$AP$58,percPreTargetAdjustment,0%) -> 0 | AI58: =IF(AI$7<$AP$58,percPreTargetAdjustment,0%) -> 0 | AJ58: =IF(AJ$7<$AP$58,percPreTargetAdjustment,0%) -> 0 | ... AN58: =IF(AN$7<$AP$58,percPreTargetAdjustment,0%) -> 0 | AX58: =SUMIFS(AX59:AX63,$G59:$G63,"<>Option") -> 412009.47 | AY58: =SUMIFS(AY59:AY63,$G59:$G63,"<>Option") -> 678049.88 | AZ58: =SUMIFS(AZ59:AZ63,$G59:$G63,"<>Option") -> 644147.38 | BA58: =SUMIFS(BA59:BA63,$G59:$G63,"<>Option") -> 611940.01 | BB58: =SUMIFS(BB59:BB63,$G59:$G63,"<>Option") -> 581343.01 | BD58: =SUM(AX58:BB58) -> 2927489.8
C59: Security Integration Services – IT part | D59: Fixed monthly | E59: central | F59: n/a | I59: 10014.883 | J59: 9614.2877 | K59: 9133.5733 | L59: 8676.8947 | M59: 8243.0499 | O59: 1 | U59: =$O$59 -> 1 | V59: =$O$59 -> 1 | W59: =$O$59 -> 1 | X59: =$O$59 -> 1 | Y59: =$O$59 -> 1 | Z59: =$O$59 -> 1 | AA59: =$O$59 -> 1 | AC59: =$O$59 -> 1 | AD59: =$O$59 -> 1 | AE59: =$O$59 -> 1 | AF59: =$O$59 -> 1 | AG59: =$O$59 -> 1 | AH59: =$O$59 -> 1 | AI59: =$O$59 -> 1 | AJ59: =$O$59 -> 1 | ... AN59: =$O$59 -> 1 | AR59: =IFERROR(AVERAGE(P59:AA59),0) -> 1 | AS59: =IFERROR(AVERAGE(AC59:AN59),0) -> 1 | AT59: =O59 -> 1 | AU59: =AT59 -> 1 | AV59: =AU59 -> 1 | AX59: =P59*(I59*(100%+P$58))+Q59*(I59*(100%+Q$58))+R59*(I59*(100%+R$58))+S59*(I59*(100%+S$58))+T59*(I59*(100%+T$58))+U59*(I59*(100%+U$58))+V59*(I59*(100%+V$58))+W59*(I59*(100%+W$58))+X59*(I59*(100%+X$58))+Y59*(I59*(100%+Y$58))+Z59*(I59*(100%+Z$58))+AA59*(I59*(100%+AA$58)) -> 70104.181 | AY59: =AC59*(J59*(100%+AC$58))+AD59*(J59*(100%+AD$58))+AE59*(J59*(100%+AE$58))+AF59*(J59*(100%+AF$58))+AG59*(J59*(100%+AG$58))+AH59*(J59*(100%+AH$58))+AI59*(J59*(100%+AI$58))+AJ59*(J59*(100%+AJ$58))+AK59*(J59*(100%+AK$58))+AL59*(J59*(100%+AL$58))+AM59*(J59*(100%+AM$58))+AN59*(J59*(100%+AN$58)) -> 115371.45 | AZ59: =K59*AT59*AT$7 -> 109602.88 | BA59: =L59*AU59*AU$7 -> 104122.74 | BB59: =M59*AV59*AV$7 -> 98916.599 | BD59: =SUM(AX59:BB59) -> 498117.85
C60: Security Operation Center – IT part | D60: Fixed monthly | E60: central | F60: n/a | I60: 32472.285 | J60: 31173.393 | K60: 29614.724 | L60: 28133.988 | M60: 26727.288 | O60: 1 | U60: =$O$60 -> 1 | V60: =$O$60 -> 1 | W60: =$O$60 -> 1 | X60: =$O$60 -> 1 | Y60: =$O$60 -> 1 | Z60: =$O$60 -> 1 | AA60: =$O$60 -> 1 | AC60: =$O$60 -> 1 | AD60: =$O$60 -> 1 | AE60: =$O$60 -> 1 | AF60: =$O$60 -> 1 | AG60: =$O$60 -> 1 | AH60: =$O$60 -> 1 | AI60: =$O$60 -> 1 | AJ60: =$O$60 -> 1 | ... AN60: =$O$60 -> 1 | AR60: =IFERROR(AVERAGE(P60:AA60),0) -> 1 | AS60: =IFERROR(AVERAGE(AC60:AN60),0) -> 1 | AT60: =O60 -> 1 | AU60: =AT60 -> 1 | AV60: =AU60 -> 1 | AX60: =P60*(I60*(100%+P$58))+Q60*(I60*(100%+Q$58))+R60*(I60*(100%+R$58))+S60*(I60*(100%+S$58))+T60*(I60*(100%+T$58))+U60*(I60*(100%+U$58))+V60*(I60*(100%+V$58))+W60*(I60*(100%+W$58))+X60*(I60*(100%+X$58))+Y60*(I60*(100%+Y$58))+Z60*(I60*(100%+Z$58))+AA60*(I60*(100%+AA$58)) -> 227305.99 | AY60: =AC60*(J60*(100%+AC$58))+AD60*(J60*(100%+AD$58))+AE60*(J60*(100%+AE$58))+AF60*(J60*(100%+AF$58))+AG60*(J60*(100%+AG$58))+AH60*(J60*(100%+AH$58))+AI60*(J60*(100%+AI$58))+AJ60*(J60*(100%+AJ$58))+AK60*(J60*(100%+AK$58))+AL60*(J60*(100%+AL$58))+AM60*(J60*(100%+AM$58))+AN60*(J60*(100%+AN$58)) -> 374080.72 | AZ60: =K60*AT60*AT$7 -> 355376.69 | BA60: =L60*AU60*AU$7 -> 337607.85 | BB60: =M60*AV60*AV$7 -> 320727.46 | BD60: =SUM(AX60:BB60) -> 1615098.7
C61: Endpoint Protection Services | D61: Fixed monthly | E61: central | F61: n/a | I61: 9601.6162 | J61: 9217.5516 | K61: 8756.674 | L61: 8318.8403 | M61: 7902.8983 | O61: 1 | U61: =$O$61 -> 1 | V61: =$O$61 -> 1 | W61: =$O$61 -> 1 | X61: =$O$61 -> 1 | Y61: =$O$61 -> 1 | Z61: =$O$61 -> 1 | AA61: =$O$61 -> 1 | AC61: =$O$61 -> 1 | AD61: =$O$61 -> 1 | AE61: =$O$61 -> 1 | AF61: =$O$61 -> 1 | AG61: =$O$61 -> 1 | AH61: =$O$61 -> 1 | AI61: =$O$61 -> 1 | AJ61: =$O$61 -> 1 | ... AN61: =$O$61 -> 1 | AR61: =IFERROR(AVERAGE(P61:AA61),0) -> 1 | AS61: =IFERROR(AVERAGE(AC61:AN61),0) -> 1 | AT61: =O61 -> 1 | AU61: =AT61 -> 1 | AV61: =AU61 -> 1 | AX61: =P61*(I61*(100%+P$58))+Q61*(I61*(100%+Q$58))+R61*(I61*(100%+R$58))+S61*(I61*(100%+S$58))+T61*(I61*(100%+T$58))+U61*(I61*(100%+U$58))+V61*(I61*(100%+V$58))+W61*(I61*(100%+W$58))+X61*(I61*(100%+X$58))+Y61*(I61*(100%+Y$58))+Z61*(I61*(100%+Z$58))+AA61*(I61*(100%+AA$58)) -> 67211.314 | AY61: =AC61*(J61*(100%+AC$58))+AD61*(J61*(100%+AD$58))+AE61*(J61*(100%+AE$58))+AF61*(J61*(100%+AF$58))+AG61*(J61*(100%+AG$58))+AH61*(J61*(100%+AH$58))+AI61*(J61*(100%+AI$58))+AJ61*(J61*(100%+AJ$58))+AK61*(J61*(100%+AK$58))+AL61*(J61*(100%+AL$58))+AM61*(J61*(100%+AM$58))+AN61*(J61*(100%+AN$58)) -> 110610.62 | AZ61: =K61*AT61*AT$7 -> 105080.09 | BA61: =L61*AU61*AU$7 -> 99826.084 | BB61: =M61*AV61*AV$7 -> 94834.78 | BD61: =SUM(AX61:BB61) -> 477562.88
C62: Vulnerability Management Services | D62: Fixed monthly | E62: central | F62: n/a | I62: 6769.7122 | J62: 6498.9237 | K62: 6173.9775 | L62: 5865.2786 | M62: 5572.0147 | O62: 1 | U62: =$O$62 -> 1 | V62: =$O$62 -> 1 | W62: =$O$62 -> 1 | X62: =$O$62 -> 1 | Y62: =$O$62 -> 1 | Z62: =$O$62 -> 1 | AA62: =$O$62 -> 1 | AC62: =$O$62 -> 1 | AD62: =$O$62 -> 1 | AE62: =$O$62 -> 1 | AF62: =$O$62 -> 1 | AG62: =$O$62 -> 1 | AH62: =$O$62 -> 1 | AI62: =$O$62 -> 1 | AJ62: =$O$62 -> 1 | ... AN62: =$O$62 -> 1 | AR62: =IFERROR(AVERAGE(P62:AA62),0) -> 1 | AS62: =IFERROR(AVERAGE(AC62:AN62),0) -> 1 | AT62: =O62 -> 1 | AU62: =AT62 -> 1 | AV62: =AU62 -> 1 | AX62: =P62*(I62*(100%+P$58))+Q62*(I62*(100%+Q$58))+R62*(I62*(100%+R$58))+S62*(I62*(100%+S$58))+T62*(I62*(100%+T$58))+U62*(I62*(100%+U$58))+V62*(I62*(100%+V$58))+W62*(I62*(100%+W$58))+X62*(I62*(100%+X$58))+Y62*(I62*(100%+Y$58))+Z62*(I62*(100%+Z$58))+AA62*(I62*(100%+AA$58)) -> 47387.985 | AY62: =AC62*(J62*(100%+AC$58))+AD62*(J62*(100%+AD$58))+AE62*(J62*(100%+AE$58))+AF62*(J62*(100%+AF$58))+AG62*(J62*(100%+AG$58))+AH62*(J62*(100%+AH$58))+AI62*(J62*(100%+AI$58))+AJ62*(J62*(100%+AJ$58))+AK62*(J62*(100%+AK$58))+AL62*(J62*(100%+AL$58))+AM62*(J62*(100%+AM$58))+AN62*(J62*(100%+AN$58)) -> 77987.084 | AZ62: =K62*AT62*AT$7 -> 74087.73 | BA62: =L62*AU62*AU$7 -> 70383.343 | BB62: =M62*AV62*AV$7 -> 66864.176 | BD62: =SUM(AX62:BB62) -> 336710.32
I63: aop 26 jan - dec
I64: jan-mar (y1) 1q | J64: apr-dez (y2) 3q | P64: April | Q64: May | R64: June | S64: July | T64: August | U64: September | V64: October | W64: November | X64: December | Y64: January | Z64: February | AA64: March | AX64: =AX50*0.25 -> 11016.711 | AY64: =AY50*0.75 -> 54900.872
G65: Security Integration Services – OT part | I65: =I54*3 -> 1688.8877 | J65: =J54*9 -> 4863.9966 | K65: =J65+I65 -> 6552.8844
G66: Security Operation Center – OT part | I66: =I55*3 -> 29932.008 | J66: =J55*9 -> 86204.184 | K66: =J66+I66 -> 116136.19
G67: Claroty OT security | I67: =I50*3*200 -> 19062.803 | J67: =J50*9*200 -> 54900.872 | K67: =J67+I67 -> 73963.675
G68: Endpoint Protection Services | I68: =I53*3 -> 5083.2086 | J68: =J53*9 -> 14639.641 | K68: =J68+I68 -> 19722.849
G70: Security Integration Services – IT part | I70: =I59*3 -> 30044.649 | J70: =J59*9 -> 86528.589 | K70: =J70+I70 -> 116573.24
G71: Security Operation Center – IT part | I71: =I60*3 -> 97416.855 | J71: =J60*9 -> 280560.54 | K71: =J71+I71 -> 377977.4
G72: Endpoint Protection Services | I72: =I61*3 -> 28804.849 | J72: =J61*9 -> 82957.964 | K72: =J72+I72 -> 111762.81
G73: Vulnerability Management Services | I73: =I62*3 -> 20309.137 | J73: =J62*9 -> 58490.313 | K73: =J73+I73 -> 78799.45

Sheet RU info
A1: Schedule 5.A (Pricing Sheet) – Resource Unit information
B4: Default Unit measurements for Monthly Recurring Charges
C5: The following common definitions apply to describe default (standard) Units and Unit measurements as used in the Unit Price section below. Each Unit is measured as set out in Schedule 5.B (Charges) for that month, based on information in Customer’s ITSM Tooling – which may originate from other systems.
B6: Unit Measurement | C6: Definition of measuring
B7: Fixed monthly | C7: Single Price for a complete or part of a Service Component, including any underpinning Service Components.
B8: User | C8: The number of Users ('named') which: • are Personnel, excluding Personnel of Supplier and Supplier Third Parties • are authorized to use the respective Service (such as SDS or AVD), and • are active in Customer's authoritative source ('lastSignInDateTime' is in the last 60 Days). Authorization is maintained in the user account directory and synchronized with the ITSM Tooling where it is reported from.
B9: PC device | C9: A personal computer class of device that: • runs an agreed workplace operating system, and • is assigned to one or more Users, and • is in the ‘Monitor and Service’ stage set out in Schedule 3.B3 (Asset Lifecycle Services) – meaning for example not being provisioned, in stock, or retired.
B10: Mobile Device | C10: A smartphone or tablet computer class of device that: • runs an agreed operating system for the mobile world, such as Apple iOS, iPadOS, or Google Android (variations), and • is assigned to one or more Users, and • is in the ‘Monitor and Service’ stage set out in Schedule 3.B3 (Asset Lifecycle Services) – meaning for example not being provisioned, in stock, or retired.
B11: Meeting room | C11: A physical room at a Customer Location with the required audiovisual equipment active in Customer's Microsoft Teams environment.
B12: Physical Server | C12: Is an independent, functional, physical compute host: • physically located in a Customer Location (on-premises), and is typically used to run one or more virtual OS instances, and • is in the ‘Monitor and Service’ stage set out in Schedule 3.B2 (Asset Lifecycle Responsibilities). This number is measured and reported using the IT Service Management Tool
B13: Database Instance | C13: The number of databases instances (this includes all databases of the instance). This number is measured and reported using the ITSM Tooling, based on input from for example the public cloud ‘update manager / subscriptions / tagging’ in. One counted database instance can ‘serve’ one or more Applications, and vice versa one Application can ‘use’ one or more databases. For the avoidance of doubt: Platform-as-a-Service (PaaS, using NIST definition) databases are not counted as databases.
B14: OS instance | C14: The number of Operating Systems (OS) • are running ('started') or defined ('allocated'), and • which run (any version of) the operating systems agreed. This information is maintained in the cloud provider's management system and the ITSM Tooling, and synchronized with the ITSM Tooling where it is reported from.
B15: Factory | C15: Means a Customer Location with production facilities where the provisioning of this Service is Accepted
B16: Sensor | C16: Means the number of active Claroty sensors, as measured in the console(s) and reported from the ITSM Tooling.
B17: Endpoint | C17: Protected endpoints in scope of Endpoint Protection or Vulnerability Management, such as laptops, smartphones, servers, or any other connected devices, as measured in the respective tool and reported from the ITSM Tooling.
B18: Workspace | C18: A workspace in Azure Virtual Desktop is a logical grouping of application groups. Each application group must be associated with a workspace for users to see the desktops and applications published to them, as measured in the AVD service and reported from the ITSM Tooling.
B20: Default Baseline bands
B21: Baseline band | C21: Baseline band tolerance are set at …
B22: Normal | C22: 25% above and below the total of all Baselines for this Service component
B23: Wide | C23: 100% above and below the total of all Baselines for this Service component
B24: Not applicable, or N/A | C24: not applicable, meaning the Price is valid at any volume

Sheet RU mapping
A1: Schedule 5.A (Pricing Sheet) – Resource Unit Mapping to Service Descriptions
A2: This worksheet creates a direct link between Resource Units and the Service descriptions of Schedule 3 Operational Services. Other obligations from other Agreement documents are not affected.
A3: It is indicative only, as It only aims to increase understanding of the relation between the documents and pricing, without being complete (i.e. obligations in the documents take precedence).
A5: Service Domain – Document – Chapter – Section | G5: Resource Unit | U5: Remarks
A6: Service Integration and Management (SIAM)
G7: Service Integration and Management
A8: Schedule 3.B1 (Service Description and Responsibilities) | G8: x
A9: Schedule 3.B2 (Asset Lifecycle Responsibilities) | G9: x
B10: 3.3 Network connections | G10: x
B11: 3.4 Underpinning Assets | G11: x
A12: Schedule 3.B3 (Service Integration and Management) | G12: x
B13: 1 Introduction | G13: x
C14: 1.1 Context | G14: x
B15: 2 Service portfolio catalogue components | G15: x
B16: 3 Service Responsibilities | G16: x
C17: 3.1 Service Integration and Management | G17: x
C18: 3.2 Coordinated performance | G18: x
C19: 3.3 Responsibility to escalate | G19: x
C20: 3.4 Operational Level Agreements | G20: x
C21: 3.5 Progress monitoring and management | G21: x
B22: 4 Service Outcomes | G22: x
B23: 5 Reporting | G23: x
A25: Service Desk Services (SDS)
G26: Standard | H26: Brazilian Portuguese | I26: German | J26: French | K26: Mandarin
A27: Schedule 3.B1 (Service Description and Responsibilities) | G27: x | H27: x | I27: x | J27: x | K27: x
A28: Schedule 3.B2 (Asset Lifecycle Responsibilities) | G28: x | H28: x | I28: x | J28: x | K28: x
B29: 3.3 Network connections | G29: x | H29: x | I29: x | J29: x | K29: x
B30: 3.4 Underpinning Assets | G30: x | H30: x | I30: x | J30: x | K30: x
A31: Schedule 3.B5 (Service Desk Services) | G31: x | H31: x | I31: x | J31: x | K31: x
B32: 1 Introduction | G32: x | H32: x | I32: x | J32: x | K32: x
C33: 1.1 Context | G33: x | H33: x | I33: x | J33: x | K33: x
B34: 2 Service portfolio catalogue components | G34: x | H34: x | I34: x | J34: x | K34: x
B35: 3 Service Responsibilities | G35: x | H35: x | I35: x | J35: x | K35: x
C36: 3.1 Responsibility assignment matrixes | G36: x | H36: x | I36: x | J36: x | K36: x
C37: 3.2 Service Desk | G37: x | H37: x | I37: x | J37: x | K37: x
B38: 4 Service Outcomes | G38: x | H38: x | I38: x | J38: x | K38: x
B39: 5 Reporting | G39: x | H39: x | I39: x | J39: x | K39: x
A41: Workplace Services (WPS)
G42: Managed Computer | H42: Company Smartphone and Company Tablet | I42: Managed Mobile | J42: Microsoft 365 full usage | K42: Microsoft 365 light usage | L42: Teams certified equipment | M42: Azure Virtual Desktop | N42: CIS Managed OS for On-site 'Office in a Box’ server
A43: Schedule 3.B1 (Service Description and Responsibilities) | G43: x | H43: x | I43: x | J43: x | K43: x | L43: x | M43: x | N43: x
A44: Schedule 3.B2 (Asset Lifecycle Responsibilities) | G44: x | H44: x | I44: x | J44: x | K44: x | L44: x | M44: x | N44: x
B45: 3.1 Hardware
C46: 3.1.1 Personal Computers (PCs) | G46: x | L46: x | U46: For OpEx + CapEx devices
C47: 3.1.2 Smartphones and tablets – Company Smartphone and Tablet | H47: x
C48: 3.1.2 Smartphones and tablets – Managed mobile | I48: x
C49: 3.1.3 Other Hardware – Meeting room Hardware | L49: x
B50: 3.2 Software – User Software | G50: x | H50: x | I50: x | M50: x
B51: 3.3 Network connections | G51: x | H51: x | I51: x | J51: x | K51: x | L51: x | M51: x | N51: x
B52: 3.4 Underpinning Assets | G52: x | H52: x | I52: x | J52: x | K52: x | L52: x | M52: x | N52: x
A53: Schedule 3.B6 (Workplace Services) | G53: x | H53: x | I53: x | J53: x | K53: x | L53: x | M53: x | N53: x
B54: 1 Introduction | G54: x | H54: x | I54: x | J54: x | K54: x | L54: x | M54: x | N54: x
C55: 1.1 Context | G55: x | H55: x | I55: x | J55: x | K55: x | L55: x | M55: x | N55: x
B56: 2 Service Portfolio Catalogue items | G56: x | H56: x | I56: x | J56: x | K56: x | L56: x | M56: x | N56: x
B57: 3 Service Responsibilities | G57: x | H57: x | I57: x | J57: x | K57: x | L57: x | M57: x | N57: x
C58: 3.1 Responsibility assignment matrixes | G58: x | H58: x | I58: x | J58: x | K58: x | L58: x | M58: x | N58: x
C59: 3.2 Software Distribution and Application Packaging | G59: x | H59: x | I59: x | J59: x | L59: x | M59: x
C60: 3.3 Profile Management | G60: x | H60: x | I60: x | J60: x | K60: x | L60: x | M60: x | N60: x
B61: 4 Service Outcomes | G61: x | H61: x | I61: x | J61: x | K61: x | L61: x | M61: x | N61: x
C62: 4.1 Collaboration platform management | J62: x | K62: x | M62: x
D63: 4.1.1 Microsoft Services | J63: x | K63: x | M63: x
D64: 4.1.2 Productivity suite | J64: x | K64: x | M64: x
D65: 4.1.3 Email filtering | J65: x | K65: x
C66: 4.2 Viva Engage | J66: x | K66: x
C67: 4.3 Infrastructure Services | G67: x | H67: x | I67: x | L67: x | M67: x | N67: x
D68: 4.3.1 File service | G68: x | J68: x | M68: x
D69: 4.3.2 Printing management | G69: x | H69: x | I69: x | L69: x | N69: x | U69: For CapEx + OpEx devices
D70: 4.3.3 DNS, DHCP, IPAM and NTP (DDI) | G70: x | H70: x | I70: x
D71: 4.3.4 Secure access network - VPN | G71: x
D72: 4.3.5 Entra Application Proxy | J72: x | K72: x | M72: x
D73: 4.3.6 Hardware and Software Asset management | G73: x | H73: x | I73: x | J73: x | K73: x | L73: x | M73: x | N73: x
D74: 4.3.7 RADIUS generic directory service | J74: x
C75: 4.4 Identity and Access Management | G75: x | H75: x | I75: x | J75: x | K75: x | L75: x | M75: x | N75: x
D76: 4.4.1 Source feed from authoritative system | J76: x | K76: x
D77: 4.4.2 Active Directory | J77: x | K77: x | N77: x
D78: 4.4.3 Cloud and Federated Identity Management | J78: x | K78: x
D79: 4.4.4 Self-service password reset (SSPR) | J79: x | K79: x
D80: 4.4.5 Conditional Access | J80: x | K80: x
D81: 4.4.6 Public Key Infrastructure | J81: x | K81: x
D82: 4.4.7 Identity and Access Management Responsibilities | G82: x | H82: x | I82: x | J82: x | K82: x | M82: x
C83: 4.5 Workplace management | G83: x | H83: x | I83: x | J83: x | K83: x | L83: x | M83: x | N83: x
D84: 4.5.1 Common for endpoint management | G84: x | H84: x | I84: x
D85: 4.5.2 Windows management | G85: x | M85: x | N85: x
D86: 4.5.3 Mobile device management | H86: x | I86: x
D87: 4.5.4 Bring Your Own (BYO) | G87: x | H87: x | I87: x
D88: 4.5.5 Microsoft Teams certified equipment | L88: x
D89: 4.5.6 Endpoint protection | G89: x | H89: x | I89: x | L89: x | M89: x
D90: 4.5.7 Software packaging | G90: x | H90: x | I90: x | M90: x
D91: 4.5.8 Managed PC Software | G91: x | H91: x | I91: x | M91: x
D92: 4.5.9 Managed OS for On-site 'Office in a Box’ workplace servers | N92: x | U92: See also Schedule 3.B7 (Cloud and Infrastructure Services)
D93: 4.5.10 Remote app and/or desktop | M93: x
B94: 5 Reporting | G94: x | H94: x | I94: x | J94: x | K94: x | L94: x | M94: x | N94: x
A96: Cloud and Infrastructure Services (CIS)
G97: Cloud Center of Excellence – IT part | H97: Managed database non-PaaS | I97: Managed operating system (OS) – in Azure | J97: Managed operating system (OS) – on premises | K97: On-premises server – Service Management | L97: On-premises server – Hardware Maintenance | U97: Note: Hardware maintenance is set out in Schedule 3.B2 (Asset Lifecycle Responsibilities)
A98: Schedule 3.B1 (Service Description and Responsibilities) | G98: x | H98: x | I98: x | J98: x | K98: x | L98: x
A99: Schedule 3.B2 (Asset Lifecycle Responsibilities) | G99: x | H99: x | I99: x | J99: x | K99: x | L99: x
B100: 3.2 Software – Application Software | G100: x | H100: x | I100: x | J100: x | K100: x
B101: 3.3 Network connections | G101: x | H101: x | I101: x | J101: x | K101: x | L101: x
B102: 3.4 Underpinning Assets – Cloud | G102: x | I102: x
B103: 3.4 Underpinning Assets – On-premises Server | K103: x | L103: x
B104: 3.4 Underpinning Assets – Underpinning Software | G104: x | H104: x | I104: x | J104: x | K104: x | L104: x
...

Sheet Devices
A1: Schedule 5.A (Pricing Sheet) – Devices
Y2: Remarks
A3: Devices as Operational Expenses (DaaS)
E5: New DaaS install volumes | M5: Total installed DaaS volumes | U5: Monthly Recurring Charges
G7: 2025 | H7: 2026 | I7: 2027 | J7: 2028 | K7: 2029 | O7: 2025 | P7: 2026 | Q7: 2027 | R7: 2028 | S7: 2029 | V7: During target lifespan | W7: After target lifespan | Y7: Target lifespan is as set out in Schedule 3.B2 (Asset Lifecycle Responsibilities)
B8: Laptop | F8: DaaS | G8: =SUMIF($D$20:$D$60,$F8,F$20:F$60)+ SUMIF($D$20:$D$60,$F8,G$20:G$60) -> 3852 | H8: =SUMIF($D$20:$D$60,$F8,H$20:H$60) -> 1463 | I8: =SUMIF($D$20:$D$60,$F8,I$20:I$60) -> 1179 | J8: =SUMIF($D$20:$D$60,$F8,J$20:J$60) -> 2140 | K8: =SUMIF($D$20:$D$60,$F8,K$20:K$60) -> 277 | N8: 2025 is average | O8: =(SUMIF($D$20:$D$60,$F8,F$20:F$60)+ SUMIF($D$20:$D$60,$F8,G$20:G$60))*(4/12) -> 1284 | P8: =SUM($G8:H8) -> 5315 | Q8: =SUM($G8:I8) -> 6494 | R8: =SUM($G8:J8) -> 8634 | S8: =SUM($G8:K8) -> 8911 | V8: 24.850818 | W8: 21.123196 | Y8: Laptop PC (i5, 16GB, 256GB); Device, localized power adapter (no bag or other accessories)
B9: Desktop | F9: DaaS | G9: =SUMIF($D$20:$D$60,$F9,N$20:N$60)+ SUMIF($D$20:$D$60,$F9,O$20:O$60) -> 694 | H9: =SUMIF($D$20:$D$60,$F9,P$20:P$60) -> 75 | I9: =SUMIF($D$20:$D$60,$F9,Q$20:Q$60) -> 17 | J9: =SUMIF($D$20:$D$60,$F9,R$20:R$60) -> 39 | K9: =SUMIF($D$20:$D$60,$F9,S$20:S$60) -> 40 | N9: showing ramp-up. | O9: =(SUMIF($D$20:$D$60,$F9,N$20:N$60)+ SUMIF($D$20:$D$60,$F9,O$20:O$60))*(4/12) -> 231.33333 | P9: =SUM($G9:H9) -> 769 | Q9: =SUM($G9:I9) -> 786 | R9: =SUM($G9:J9) -> 825 | S9: =SUM($G9:K9) -> 865 | V9: 22.245047 | W9: 18.90829 | Y9: Desktop PC (i5, 16GB, 256GB); Device and localized keyboard (no display or other accessories)
G10: =SUM(G8:G9) -> 4546 | H10: =SUM(H8:H9) -> 1538 | I10: =SUM(I8:I9) -> 1196 | J10: =SUM(J8:J9) -> 2179 | K10: =SUM(K8:K9) -> 317 | N10: Excludes pre-existing DaaS. | O10: =SUM(O8:O9) -> 1515.3333 | P10: =SUM(P8:P9) -> 6084 | Q10: =SUM(Q8:Q9) -> 7280 | R10: =SUM(R8:R9) -> 9459 | S10: =SUM(S8:S9) -> 9776
G12: =G10/3 -> 1515.3333 | H12: =G12*2 -> 3030.6667 | O12: =SUMPRODUCT(O8:O9,$V$8:$V$9)*12 -> 444653.66 | P12: =SUMPRODUCT(P8:P9,$V$8:$V$9)*12 -> 1790262.5 | Q12: =SUMPRODUCT(Q8:Q9,$V$8:$V$9)*12 -> 2146389.9 | R12: =SUMPRODUCT(R8:R9,$V$8:$V$9)*12 -> 2794969.6 | S12: =SUMPRODUCT(S8:S9,$V$8:$V$9)*12 -> 2888251.3
H13: =H10 -> 1538 | I13: =I10 -> 1196 | J13: =J10 -> 2179 | K13: =K10 -> 317 | S13: =SUM(O12:S12) -> 10064527
A15: Devices | Y15: remarks
E17: New install volumes | U17: One-time Charge
F18: Laptop PC (i5, 16GB, 256GB) | N18: Desktop PC (i5, 16GB, 256GB) | O18: Desktop PC (i5, 16GB, 256GB)
D19: Specify if country is "DaaS" or "Non-DaaS" | F19: Project | G19: Rest 2025 | H19: 2026 | I19: 2027 | J19: 2028 | K19: 2029 | L19: Total | N19: Project | O19: Rest 2025 | P19: 2026 | Q19: 2027 | R19: 2028 | S19: 2029 | T19: Total | V19: Laptop | W19: Desktop | Y19: Note: 2030 is not requested on purpose
B20: Australia | D20: DaaS | F20: 25 | G20: 39 | H20: 16 | I20: 43 | J20: 108 | K20: 1 | L20: =SUM(F20:K20) -> 232 | N20: 5 | O20: 0 | P20: 0 | Q20: 1 | R20: 3 | S20: 0 | T20: =SUM(N20:S20) -> 9 | V20: 0 | W20: 0
B21: Austria | D21: DaaS | F21: 3 | G21: 0 | H21: 0 | I21: 0 | J21: 41 | K21: 0 | L21: =SUM(F21:K21) -> 44 | T21: =SUM(N21:S21) -> 0 | V21: 0 | W21: 0
B22: Belgium | D22: DaaS | F22: 85 | G22: 23 | H22: 6 | I22: 17 | J22: 62 | K22: 22 | L22: =SUM(F22:K22) -> 215 | T22: =SUM(N22:S22) -> 0 | V22: 0 | W22: 0
B23: Brazil | D23: DaaS | F23: 473 | G23: 0 | H23: 8 | I23: 152 | J23: 238 | K23: 1 | L23: =SUM(F23:K23) -> 872 | N23: 68 | O23: 0 | P23: 1 | Q23: 0 | R23: 0 | S23: 0 | T23: =SUM(N23:S23) -> 69 | V23: 0 | W23: 0
B24: Bulgaria | D24: DaaS | F24: 56 | G24: 3 | H24: 6 | I24: 8 | J24: 3 | K24: 54 | L24: =SUM(F24:K24) -> 130 | N24: 5 | O24: 0 | P24: 0 | Q24: 2 | R24: 0 | S24: 0 | T24: =SUM(N24:S24) -> 7 | V24: 0 | W24: 0
B25: China | D25: DaaS | F25: 90 | G25: 0 | H25: 132 | I25: 4 | J25: 3 | K25: 8 | L25: =SUM(F25:K25) -> 237 | N25: 1 | O25: 0 | P25: 12 | Q25: 1 | R25: 0 | S25: 0 | T25: =SUM(N25:S25) -> 14 | V25: 0 | W25: 0
B26: Czech Republic | D26: DaaS | F26: 131 | G26: 12 | H26: 10 | I26: 7 | J26: 12 | K26: 4 | L26: =SUM(F26:K26) -> 176 | N26: 30 | O26: 0 | P26: 1 | Q26: 0 | R26: 0 | S26: 0 | T26: =SUM(N26:S26) -> 31 | V26: 0 | W26: 0
B27: Denmark | D27: DaaS | F27: 48 | G27: 9 | H27: 156 | I27: 44 | J27: 32 | K27: 5 | L27: =SUM(F27:K27) -> 294 | N27: 2 | O27: 0 | P27: 0 | Q27: 0 | R27: 0 | S27: 0 | T27: =SUM(N27:S27) -> 2 | V27: 0 | W27: 0
B28: France | D28: DaaS | F28: 332 | G28: 6 | H28: 81 | I28: 83 | J28: 133 | K28: 35 | L28: =SUM(F28:K28) -> 670 | N28: 66 | O28: 0 | P28: 18 | Q28: 11 | R28: 28 | S28: 30 | T28: =SUM(N28:S28) -> 153 | V28: 0 | W28: 0
B29: Georgia | D29: Non-Daas | F29: 26 | G29: 0 | H29: 0 | I29: 1 | J29: 0 | K29: 0 | L29: =SUM(F29:K29) -> 27 | T29: =SUM(N29:S29) -> 0 | V29: 1609.5119 | W29: 0
B30: Germany | D30: DaaS | F30: 425 | G30: 44 | H30: 138 | I30: 112 | J30: 280 | K30: 0 | L30: =SUM(F30:K30) -> 999 | N30: 157 | O30: 0 | P30: 0 | Q30: 0 | R30: 0 | S30: 0 | T30: =SUM(N30:S30) -> 157 | V30: 0 | W30: 0
B31: Greece | D31: DaaS | F31: 21 | G31: 0 | H31: 2 | I31: 1 | J31: 58 | K31: 0 | L31: =SUM(F31:K31) -> 82 | N31: 11 | O31: 0 | P31: 0 | Q31: 0 | R31: 0 | S31: 0 | T31: =SUM(N31:S31) -> 11 | V31: 0 | W31: 0
B32: Hong Kong | D32: DaaS | F32: 5 | G32: 0 | H32: 5 | I32: 0 | J32: 0 | K32: 0 | L32: =SUM(F32:K32) -> 10 | T32: =SUM(N32:S32) -> 0 | V32: 0 | W32: 0
B33: Hungary | D33: DaaS | F33: 21 | G33: 0 | H33: 19 | I33: 3 | J33: 20 | K33: 0 | L33: =SUM(F33:K33) -> 63 | T33: =SUM(N33:S33) -> 0 | V33: 0 | W33: 0
B34: Ireland | D34: DaaS | F34: 0 | G34: 0 | H34: 0 | I34: 14 | J34: 0 | K34: 0 | L34: =SUM(F34:K34) -> 14 | T34: =SUM(N34:S34) -> 0 | V34: 0 | W34: 0
B35: Italy | D35: DaaS | F35: 42 | G35: 0 | H35: 0 | I35: 2 | J35: 0 | K35: 0 | L35: =SUM(F35:K35) -> 44 | T35: =SUM(N35:S35) -> 0 | V35: 0 | W35: 0
B36: Kazakhstan | D36: Non-Daas | F36: 44 | G36: 5 | H36: 0 | I36: 18 | J36: 9 | K36: 1 | L36: =SUM(F36:K36) -> 77 | N36: 3 | O36: 0 | P36: 0 | Q36: 0 | R36: 0 | S36: 0 | T36: =SUM(N36:S36) -> 3 | V36: 1383.1753 | W36: 1534.066
B37: Lithuania | D37: DaaS | F37: 9 | G37: 2 | H37: 1 | I37: 27 | J37: 0 | K37: 0 | L37: =SUM(F37:K37) -> 39 | T37: =SUM(N37:S37) -> 0 | V37: 0 | W37: 0
B38: Malaysia | D38: DaaS | F38: 221 | G38: 5 | H38: 159 | I38: 13 | J38: 8 | K38: 0 | L38: =SUM(F38:K38) -> 406 | N38: 0 | O38: 0 | P38: 27 | Q38: 0 | R38: 0 | S38: 0 | T38: =SUM(N38:S38) -> 27 | V38: 0 | W38: 0
B39: Mexico | D39: DaaS | F39: 16 | G39: 0 | H39: 0 | I39: 3 | J39: 3 | K39: 0 | L39: =SUM(F39:K39) -> 22 | T39: =SUM(N39:S39) -> 0 | V39: 0 | W39: 0
B40: Morocco | D40: DaaS | F40: 26 | G40: 0 | H40: 0 | I40: 0 | J40: 0 | K40: 0 | L40: =SUM(F40:K40) -> 26 | N40: 7 | O40: 0 | P40: 0 | Q40: 0 | R40: 0 | S40: 0 | T40: =SUM(N40:S40) -> 7 | V40: 0 | W40: 0
B41: Myanmar | D41: DaaS | F41: 8 | G41: 0 | H41: 13 | I41: 0 | J41: 0 | K41: 0 | L41: =SUM(F41:K41) -> 21 | T41: =SUM(N41:S41) -> 0 | V41: 0 | W41: 0
B42: Netherlands | D42: DaaS | F42: 611 | G42: 181 | H42: 438 | I42: 407 | J42: 584 | K42: 0 | L42: =SUM(F42:K42) -> 2221 | N42: 164 | O42: 5 | P42: 2 | Q42: 0 | R42: 0 | S42: 3 | T42: =SUM(N42:S42) -> 174 | V42: 0 | W42: 0
B43: New Zealand | D43: DaaS | F43: 111 | G43: 0 | H43: 10 | I43: 3 | J43: 7 | K43: 5 | L43: =SUM(F43:K43) -> 136 | N43: 12 | O43: 0 | P43: 0 | Q43: 0 | R43: 0 | S43: 0 | T43: =SUM(N43:S43) -> 12 | V43: 0 | W43: 0
B44: Norway | D44: DaaS | F44: 54 | G44: 0 | H44: 2 | I44: 9 | J44: 108 | K44: 0 | L44: =SUM(F44:K44) -> 173 | N44: 17 | O44: 0 | P44: 2 | Q44: 0 | R44: 2 | S44: 0 | T44: =SUM(N44:S44) -> 21 | V44: 0 | W44: 0
B45: Poland | D45: DaaS | F45: 119 | G45: 8 | H45: 66 | I45: 7 | J45: 38 | K45: 0 | L45: =SUM(F45:K45) -> 238 | N45: 18 | O45: 0 | P45: 0 | Q45: 0 | R45: 6 | S45: 0 | T45: =SUM(N45:S45) -> 24 | V45: 0 | W45: 0
B46: Portugal | D46: DaaS | F46: 0 | G46: 0 | H46: 0 | I46: 0 | J46: 4 | K46: 0 | L46: =SUM(F46:K46) -> 4 | T46: =SUM(N46:S46) -> 0 | V46: 0 | W46: 0
B47: Romania | D47: DaaS | F47: 43 | G47: 0 | H47: 0 | I47: 0 | J47: 77 | K47: 0 | L47: =SUM(F47:K47) -> 120 | N47: 1 | O47: 0 | P47: 0 | Q47: 0 | R47: 0 | S47: 0 | T47: =SUM(N47:S47) -> 1 | V47: 0 | W47: 0
B48: Singapore | D48: DaaS | F48: 31 | G48: 1 | H48: 51 | I48: 0 | J48: 0 | K48: 9 | L48: =SUM(F48:K48) -> 92 | T48: =SUM(N48:S48) -> 0 | V48: 0 | W48: 0
B49: Slovakia | D49: DaaS | F49: 21 | G49: 0 | H49: 0 | I49: 0 | J49: 0 | K49: 1 | L49: =SUM(F49:K49) -> 22 | T49: =SUM(N49:S49) -> 0 | V49: 0 | W49: 0
B50: South Africa | D50: DaaS | F50: 3 | G50: 0 | H50: 4 | I50: 13 | J50: 22 | K50: 0 | L50: =SUM(F50:K50) -> 42 | T50: =SUM(N50:S50) -> 0 | V50: 0 | W50: 0
B51: Spain | D51: DaaS | F51: 136 | G51: 0 | H51: 21 | I51: 5 | J51: 13 | K51: 0 | L51: =SUM(F51:K51) -> 175 | N51: 12 | O51: 0 | P51: 0 | Q51: 0 | R51: 0 | S51: 0 | T51: =SUM(N51:S51) -> 12 | V51: 0 | W51: 0
B52: Sweden | D52: DaaS | F52: 20 | G52: 0 | H52: 12 | I52: 11 | J52: 42 | K52: 0 | L52: =SUM(F52:K52) -> 85 | N52: 21 | O52: 0 | P52: 0 | Q52: 2 | R52: 0 | S52: 0 | T52: =SUM(N52:S52) -> 23 | V52: 0 | W52: 0
B53: Switzerland | D53: DaaS | F53: 13 | G53: 13 | H53: 5 | I53: 2 | J53: 5 | K53: 6 | L53: =SUM(F53:K53) -> 44 | T53: =SUM(N53:S53) -> 0 | V53: 0 | W53: 0
B54: Thailand | D54: DaaS | F54: 93 | G54: 0 | H54: 40 | I54: 2 | J54: 28 | K54: 76 | L54: =SUM(F54:K54) -> 239 | N54: 9 | O54: 0 | P54: 4 | Q54: 0 | R54: 0 | S54: 7 | T54: =SUM(N54:S54) -> 20 | V54: 0 | W54: 0
B55: Turkey | D55: DaaS | F55: 55 | G55: 0 | H55: 24 | I55: 0 | J55: 86 | K55: 0 | L55: =SUM(F55:K55) -> 165 | N55: 0 | O55: 0 | P55: 8 | Q55: 0 | R55: 0 | S55: 0 | T55: =SUM(N55:S55) -> 8 | V55: 0 | W55: 0
B56: Ukraine | D56: Non-Daas | F56: 233 | G56: 0 | H56: 0 | I56: 0 | J56: 0 | K56: 0 | L56: =SUM(F56:K56) -> 233 | N56: 35 | O56: 0 | P56: 0 | Q56: 0 | R56: 0 | S56: 0 | T56: =SUM(N56:S56) -> 35 | V56: 1634.6605 | W56: 1266.8619
B57: United Kingdom | D57: DaaS | F57: 154 | G57: 1 | H57: 23 | I57: 83 | J57: 125 | K57: 50 | L57: =SUM(F57:K57) -> 436 | N57: 83 | O57: 0 | P57: 0 | Q57: 0 | R57: 0 | S57: 0 | T57: =SUM(N57:S57) -> 83 | V57: 0 | W57: 0
B58: USA | D58: DaaS | F58: 0 | G58: 0 | H58: 0 | I58: 102 | J58: 0 | K58: 0 | L58: =SUM(F58:K58) -> 102 | T58: =SUM(N58:S58) -> 0 | V58: 0 | W58: 0
B59: Uzbekistan | D59: Non-Daas | F59: 5 | G59: 0 | H59: 0 | I59: 0 | J59: 0 | K59: 0 | L59: =SUM(F59:K59) -> 5 | T59: =SUM(N59:S59) -> 0 | V59: 1383.1743 | W59: 0
B60: Vietnam | D60: DaaS | F60: 4 | G60: 0 | H60: 15 | I60: 2 | J60: 0 | K60: 0 | L60: =SUM(F60:K60) -> 21 | T60: =SUM(N60:S60) -> 0 | V60: 0 | W60: 0
F61: =SUM(F20:F60) -> 3813 | G61: =SUM(G20:G60) -> 352 | H61: =SUM(H20:H60) -> 1463 | I61: =SUM(I20:I60) -> 1198 | J61: =SUM(J20:J60) -> 2149 | K61: =SUM(K20:K60) -> 278 | L61: =SUM(L20:L60) -> 9253 | N61: =SUM(N20:N60) -> 727 | O61: =SUM(O20:O60) -> 5 | P61: =SUM(P20:P60) -> 75 | Q61: =SUM(Q20:Q60) -> 17 | R61: =SUM(R20:R60) -> 39 | S61: =SUM(S20:S60) -> 40 | T61: =SUM(T20:T60) -> 903
D63: Subtotals Non-DaaS | F63: {=SUMPRODUCT(IF($D$20:$D$60="Non-DaaS",1, 0),F20:F60,$V20:$V60)} -> 490498.78 | G63: {=SUMPRODUCT(IF($D$20:$D$60="Non-DaaS",1, 0),G20:G60,$V20:$V60)} -> 6915.8763 | H63: {=SUMPRODUCT(IF($D$20:$D$60="Non-DaaS",1, 0),H20:H60,$V20:$V60)} -> 0 | I63: {=SUMPRODUCT(IF($D$20:$D$60="Non-DaaS",1, 0),I20:I60,$V20:$V60)} -> 26506.667 | J63: {=SUMPRODUCT(IF($D$20:$D$60="Non-DaaS",1, 0),J20:J60,$V20:$V60)} -> 12448.577 | K63: {=SUMPRODUCT(IF($D$20:$D$60="Non-DaaS",1, 0),K20:K60,$V20:$V60)} -> 1383.1753 | N63: {=SUMPRODUCT(IF($D$20:$D$60="Non-DaaS",1, 0),N20:N60,$W20:$W60)} -> 48942.364 | O63: {=SUMPRODUCT(IF($D$20:$D$60="Non-DaaS",1, 0),O20:O60,$W20:$W60)} -> 0 | P63: {=SUMPRODUCT(IF($D$20:$D$60="Non-DaaS",1, 0),P20:P60,$W20:$W60)} -> 0 | Q63: {=SUMPRODUCT(IF($D$20:$D$60="Non-DaaS",1, 0),Q20:Q60,$W20:$W60)} -> 0 | R63: {=SUMPRODUCT(IF($D$20:$D$60="Non-DaaS",1, 0),R20:R60,$W20:$W60)} -> 0 | S63: {=SUMPRODUCT(IF($D$20:$D$60="Non-DaaS",1, 0),S20:S60,$W20:$W60)} -> 0
K64: =SUM(F63:K63) -> 537753.08 | S64: =SUM(N63:S63) -> 48942.364
A66: Printers as operational expenses (MPS + 'per-click')
B68: Country | F68: Volumes | N68: MRC | P68: Per-click charges
G69: Year 01 | H69: A4 pages | J69: A3 pages | O69: Year 01 | P69: A4 | R69: A3
G70: Devices | H70: Black | I70: Color | J70: Black | K70: Color | O70: MPS | P70: Black | Q70: Color | R70: Black | S70: Color
B71: Managed printer small mono | G71: 65 | H71: 33452 | O71: 13.623697 | P71: 0.014837989 | Y71: As reference point, existing model is an HP LaserJet Enterprise E50145dn
B72: Managed printer small color | G72: 1 | H72: 233 | I72: - | O72: 19.374547 | P72: 0.015751534 | Q72: 0.076831677 | Y72: As reference point, existing model is an HP Color LaserJet Enterprise X55745dn
B73: Managed printer medium mono | G73: 89 | H73: 73126 | O73: 33.34382 | P73: 0.0090402569 | Y73: As reference point, existing model is an HP LaserJet Managed MFP E52645dn
B74: Managed printer medium color | G74: 41 | H74: 17267 | I74: 24461 | O74: 41.737981 | P74: 0.01009277 | Q74: 0.069905826 | Y74: As reference point, existing model is an HP Color LaserJet Enterprise MFP X58045dn
B75: Managed printer large mono | G75: 14 | H75: 7291 | J75: 729 | O75: 64.448519 | P75: 0.0095851932 | R75: 0.019170386 | Y75: As reference point, existing model is an HP LaserJet Managed Flow MFP E731z
B76: Managed printer large color | G76: 69 | H76: 78738 | I76: 54592 | J76: 7874 | K76: 5459 | O76: 70.980919 | P76: 0.0069660622 | Q76: 0.046348376 | R76: 0.013932124 | S76: 0.092696752 | Y76: As reference point, existing model is an HP Color LaserJet Managed MFP E786dn
O78: Estimates for summary
O79: =SUMPRODUCT(G71:G76,O71:O76)*12 -> 136604.82 | P79: =SUMPRODUCT(H71:H76,P71:P76)*12 -> 23445.116 | Q79: =SUMPRODUCT(I71:I76,Q71:Q76)*12 -> 50882.603 | R79: =SUMPRODUCT(J71:J76,R71:R76)*12 -> 1484.1211 | S79: =SUMPRODUCT(K71:K76,S71:S76)*12 -> 6072.3788
S80: =SUM(O79:S79) -> 218489.04
A83: Simplified subtotals for summary
G85: Year 01 | H85: Year 02 | I85: Year 03 | J85: Year 04 | K85: Year 05
G86: =O12+F63+G63+N63+O63+S80 -> 1209499.7 | H86: =P12+H63+P63+$S$80 -> 2008751.5 | I86: =Q12+I63+Q63+$S$80 -> 2391385.6 | J86: =R12+J63+R63+$S$80 -> 3025907.2 | K86: =S12+K63+S63+$S$80 -> 3108123.5

Sheet One-time Charges
A1: Schedule 5.A (Pricing Sheet) – One-time Charges (OTC)
A3: Section in Schedule 5.B (Pricing Principles)
B4: Service
C5: Service Component | H5: (totals exclude Options)
D6: Payment Milestone name as listed in Attachment 4.B.L2 (Integrated Deliverable Tracker) | E6: IDT Milestone ID | F6: Option | H6: Year 01 | I6: Year 02 | J6: Year 03 | K6: Year 04 | L6: Year 05 | N6: Remarks
A8: 3.1 | B8: Transition and Transformation | H8: =H10+H24+H45+H51 -> 0 | I8: =I10+I24+I45+I51 -> 496708.99 | J8: =J10+J24+J45+J51 -> 496708.99 | K8: =K10+K24+K45+K51 -> 496708.99 | L8: =L10+L24+L45+L51 -> 819938.4 | N8: Note: Schedule 5.C (Service Credit Procedure) applies.
H9: =SUMIFS(H10:H59,$F10:$F59,"Option") -> 0 | I9: =SUMIFS(I10:I59,$F10:$F59,"Option") -> 0 | J9: =SUMIFS(J10:J59,$F10:$F59,"Option") -> 233172.15 | K9: =SUMIFS(K10:K59,$F10:$F59,"Option") -> 0 | L9: =SUMIFS(L10:L59,$F10:$F59,"Option") -> 0
C10: Transition | H10: =SUMIFS(H11:H23,$F11:$F23,"<>Option") -> 0 | I10: =SUMIFS(I11:I23,$F11:$F23,"<>Option") -> 0 | J10: =SUMIFS(J11:J23,$F11:$F23,"<>Option") -> 0 | K10: =SUMIFS(K11:K23,$F11:$F23,"<>Option") -> 0 | L10: =SUMIFS(L11:L23,$F11:$F23,"<>Option") -> 0
D11: Service Integration and Management (SIAM) | H11: 0
D12: Service Desk Services (SDS) | H12: 0
D13: Brazilian Portuguese | F13: Option | H13: 0
D14: German | F14: Option | H14: 0
D15: French | F15: Option | H15: 0
D16: Mandarin | F16: Option | H16: 0
D17: Workplace Services (WPS) | H17: 0
D18: Cloud and Infrastructure Services (CIS) | H18: 0
D19: Operational Technology Services (OTS) | H19: 0
D20: Security Services (SEC) | H20: 0
C24: Transformation | H24: =SUMIFS(H25:H44,$F25:$F44,"<>Option") -> 0 | I24: =SUMIFS(I25:I44,$F25:$F44,"<>Option") -> 365488.94 | J24: =SUMIFS(J25:J44,$F25:$F44,"<>Option") -> 365488.94 | K24: =SUMIFS(K25:K44,$F25:$F44,"<>Option") -> 365488.94 | L24: =SUMIFS(L25:L44,$F25:$F44,"<>Option") -> 365488.94
D25: Service Integration and Management (SIAM) | E25: M60 M146 | H25: 0 | I25: 43894.306 | J25: 43894.306 | K25: 43894.306 | L25: 43894.306
D26: Service Desk Services (SDS) | E26: M59 M209 M64 | H26: 0 | I26: 37190.624 | J26: 37190.624 | K26: 37190.624 | L26: 37190.624
D27: Brazilian Portuguese | F27: Option | H27: 0 | I27: 0 | J27: 0 | K27: 0 | L27: 0
D28: German | F28: Option | H28: 0 | I28: 0 | J28: 0 | K28: 0 | L28: 0
D29: French | F29: Option | H29: 0 | I29: 0 | J29: 0 | K29: 0 | L29: 0
D30: Mandarin | F30: Option | H30: 0 | I30: 0 | J30: 0 | K30: 0 | L30: 0
D31: Workplace Services (WPS) | E31: M59 M66 M152 | H31: 0 | I31: 131875.21 | J31: 131875.21 | K31: 131875.21 | L31: 131875.21
D32: Cloud and Infrastructure Services (CIS) | E32: M185 M68 | H32: 0 | I32: 68477.181 | J32: 68477.181 | K32: 68477.181 | L32: 68477.181
D33: Operational Technology Services (OTS) | E33: M185 M70 | H33: 0 | I33: 10911.76 | J33: 10911.76 | K33: 10911.76 | L33: 10911.76
D34: Security Services (SEC) | E34: M72 | H34: 0 | I34: 8127.7625 | J34: 8127.7625 | K34: 8127.7625 | L34: 8127.7625
D35: One time charges for Movement of existing stock to Drive consolidation of Stock rooms | E35: M152 | H35: 0 | I35: 29236.16 | J35: 29236.16 | K35: 29236.16 | L35: 29236.16
D36: Follow Me Printing | E36: M152 | H36: 0 | I36: 35775.934 | J36: 35775.934 | K36: 35775.934 | L36: 35775.934
C45: Other – In-flight Projects or future Projects | H45: =SUMIFS(H46:H50,$F46:$F50,"<>Option") -> 0 | I45: =SUMIFS(I46:I50,$F46:$F50,"<>Option") -> 131220.05 | J45: =SUMIFS(J46:J50,$F46:$F50,"<>Option") -> 131220.05 | K45: =SUMIFS(K46:K50,$F46:$F50,"<>Option") -> 131220.05 | L45: =SUMIFS(L46:L50,$F46:$F50,"<>Option") -> 454449.46
D46: OS Update win 11 to 12 /13 | F46: Option | H46: 0 | I46: 0 | J46: 233172.15 | K46: 0 | L46: 0
D47: Juriba Setup | E47: M207 | H47: 0 | I47: 36263.989 | J47: 36263.989 | K47: 36263.989 | L47: 36263.989
D48: Device Refresh Project | E48: M33 | H48: 0 | I48: 94956.061 | J48: 94956.061 | K48: 94956.061 | L48: 418185.47
C51: Transfer of Assets | H51: =SUMIFS(H52:H59,$F52:$F59,"<>Option") -> 0 | I51: =SUMIFS(I52:I60,$F52:$F60,"<>Option") -> 0 | J51: =SUMIFS(J52:J60,$F52:$F60,"<>Option") -> 0 | K51: =SUMIFS(K52:K60,$F52:$F60,"<>Option") -> 0 | L51: =SUMIFS(L52:L60,$F52:$F60,"<>Option") -> 0
D52: Transfer of Existing Services' DaaS PCs | H52: 0 | I52: 0 | J52: 0 | K52: 0 | L52: 0
A60: 2 | B60: Service Requests
D61: (due to layout requirements, this is set out in worksheet 'Service Requests')
A63: 3.2 | B63: Demand Requests
D64: (due to layout requirements, this is set out in worksheet 'Demand Requests')
A67: 3.3 | B67: Termination for Convenience Fee | H67: =SUMIFS(H69:H77,$F69:$F77,"<>Option") -> 6634171.3 | I67: =SUMIFS(I69:I77,$F69:$F77,"<>Option") -> 10362539 | J67: =SUMIFS(J69:J77,$F69:$F77,"<>Option") -> 8904112.2 | K67: =SUMIFS(K69:K77,$F69:$F77,"<>Option") -> 7049765.8 | L67: =SUMIFS(L69:L77,$F69:$F77,"<>Option") -> 4020820.4 | N67: Termination Fee at completion of the Exit for the complete Domain, at the END of the period | P67: Year 01 – month of the Term | AA67: Year-end 01 | AB67: Year 02 | AM67: Year-end 02 | AN67: Year 03 | AY67: Year-end 03 | AZ67: Year 04 | BK67: Year-end 04 | BL67: Year 05 | BW67: Year-end 05
P68: 1 | Q68: 2 | R68: 3 | S68: 4 | T68: 5 | U68: 6 | V68: 7 | W68: 8 | X68: 9 | Y68: 10 | Z68: 11 | AA68: 12 | AB68: 13 | AC68: 14 | AD68: 15 | AE68: 16 | AF68: 17 | AG68: 18 | AH68: 19 | AI68: 20 | AJ68: 21 | AK68: 22 | AL68: 23 | AM68: 24 | AN68: 25 | AO68: 26 | AP68: 27 | AQ68: 28 | AR68: 29 | AS68: 30 | AT68: 31 | AU68: 32 | AV68: 33 | AW68: 34 | AX68: 35 | AY68: 36 | AZ68: 37 | BA68: 38 | BB68: 39 | BC68: 40 | BD68: 41 | BE68: 42 | BF68: 43 | BG68: 44 | BH68: 45 | BI68: 46 | BJ68: 47 | BK68: 48 | BL68: 49 | BM68: 50 | BN68: 51 | BO68: 52 | BP68: 53 | BQ68: 54 | BR68: 55 | BS68: 56 | BT68: 57 | BU68: 58 | BV68: 59 | BW68: 60
D69: Service Integration and Management (SIAM) | H69: =AA69 -> 88107.424 | I69: =AM69 -> 128706.63 | J69: =AY69 -> 111920.72 | K69: =SUM(BK69) -> 85556.169 | L69: =BW69 -> -8.9130481e-11 | P69: 89869.572 | Q69: 89709.377 | R69: 89549.182 | S69: 89388.986 | T69: 89228.791 | U69: 89068.596 | V69: 88908.4 | W69: 88748.205 | X69: 88588.01 | Y69: 88427.814 | Z69: 88267.619 | AA69: 88107.424 | AB69: 91490.691 | AC69: 94873.958 | AD69: 98257.226 | AE69: 101640.49 | AF69: 105023.76 | AG69: 108407.03 | AH69: 111790.29 | AI69: 115173.56 | AJ69: 118556.83 | AK69: 121940.1 | AL69: 125323.36 | AM69: 128706.63 | AN69: 127307.81 | AO69: 125908.98 | AP69: 124510.15 | AQ69: 123111.33 | AR69: 121712.5 | AS69: 120313.68 | AT69: 118914.85 | AU69: 117516.02 | AV69: 116117.2 | AW69: 114718.37 | AX69: 113319.55 | AY69: 111920.72 | AZ69: 109723.68 | BA69: 107526.63 | BB69: 105329.58 | BC69: 103132.54 | BD69: 100935.49 | BE69: 98738.445 | BF69: 96541.399 | BG69: 94344.353 | BH69: 92147.307 | BI69: 89950.261 | BJ69: 87753.215 | BK69: 85556.169 | BL69: 78426.488 | BM69: 71296.808 | BN69: 64167.127 | BO69: 57037.446 | BP69: 49907.765 | BQ69: 42778.085 | BR69: 35648.404 | BS69: 28518.723 | BT69: 21389.042 | BU69: 14259.362 | BV69: 7129.6808 | BW69: -8.9130481e-11
D70: Service Desk Services (SDS) | H70: =AA70 -> 96197.286 | I70: =AM70 -> 203089.78 | J70: =AY70 -> 159907.84 | K70: =SUM(BK70) -> 124891.76 | L70: =BW70 -> 1.3460522e-10 | P70: 98121.231 | Q70: 97946.327 | R70: 97771.423 | S70: 97596.519 | T70: 97421.615 | U70: 97246.71 | V70: 97071.806 | W70: 96896.902 | X70: 96721.998 | Y70: 96547.094 | Z70: 96372.19 | AA70: 96197.286 | AB70: 105104.99 | AC70: 114012.7 | AD70: 122920.41 | AE70: 131828.12 | AF70: 140735.83 | AG70: 149643.53 | AH70: 158551.24 | AI70: 167458.95 | AJ70: 176366.66 | AK70: 185274.37 | AL70: 194182.07 | AM70: 203089.78 | AN70: 199491.29 | AO70: 195892.79 | AP70: 192294.3 | AQ70: 188695.8 | AR70: 185097.31 | AS70: 181498.81 | AT70: 177900.32 | AU70: 174301.82 | AV70: 170703.33 | AW70: 167104.83 | AX70: 163506.33 | AY70: 159907.84 | AZ70: 156989.83 | BA70: 154071.83 | BB70: 151153.82 | BC70: 148235.81 | BD70: 145317.81 | BE70: 142399.8 | BF70: 139481.8 | BG70: 136563.79 | BH70: 133645.78 | BI70: 130727.78 | BJ70: 127809.77 | BK70: 124891.76 | BL70: 114484.12 | BM70: 104076.47 | BN70: 93668.824 | BO70: 83261.177 | BP70: 72853.53 | BQ70: 62445.882 | BR70: 52038.235 | BS70: 41630.588 | BT70: 31222.941 | BU70: 20815.294 | BV70: 10407.647 | BW70: 1.3460522e-10
D71: Workplace Services (WPS) | H71: =AA71 -> 358356.43 | I71: =AM71 -> 646247.08 | J71: =AY71 -> 535499.94 | K71: =SUM(BK71) -> 401501.63 | L71: =BW71 -> 5.6752469e-10 | P71: 365523.56 | Q71: 364872 | R71: 364220.44 | S71: 363568.89 | T71: 362917.33 | U71: 362265.77 | V71: 361614.22 | W71: 360962.66 | X71: 360311.1 | Y71: 359659.54 | Z71: 359007.99 | AA71: 358356.43 | AB71: 382347.32 | AC71: 406338.21 | AD71: 430329.09 | AE71: 454319.98 | AF71: 478310.87 | AG71: 502301.76 | AH71: 526292.64 | AI71: 550283.53 | AJ71: 574274.42 | AK71: 598265.31 | AL71: 622256.2 | AM71: 646247.08 | AN71: 637018.16 | AO71: 627789.23 | AP71: 618560.3 | AQ71: 609331.37 | AR71: 600102.44 | AS71: 590873.51 | AT71: 581644.59 | AU71: 572415.66 | AV71: 563186.73 | AW71: 553957.8 | AX71: 544728.87 | AY71: 535499.94 | AZ71: 524333.42 | BA71: 513166.89 | BB71: 502000.36 | BC71: 490833.84 | BD71: 479667.31 | BE71: 468500.79 | BF71: 457334.26 | BG71: 446167.73 | BH71: 435001.21 | BI71: 423834.68 | BJ71: 412668.15 | BK71: 401501.63 | BL71: 368043.16 | BM71: 334584.69 | BN71: 301126.22 | BO71: 267667.75 | BP71: 234209.28 | BQ71: 200750.81 | BR71: 167292.34 | BS71: 133833.88 | BT71: 100375.41 | BU71: 66916.938 | BV71: 33458.469 | BW71: 5.6752469e-10
D72: Cloud and Infrastructure Services (CIS) | H72: =AA72 -> 151140.29 | I72: =AM72 -> 290661.88 | J72: =AY72 -> 230212.47 | K72: =SUM(BK72) -> 163363.23 | L72: =BW72 -> -1.9645086e-10 | P72: 154163.1 | Q72: 153888.3 | R72: 153613.5 | S72: 153338.7 | T72: 153063.9 | U72: 152789.1 | V72: 152514.29 | W72: 152239.49 | X72: 151964.69 | Y72: 151689.89 | Z72: 151415.09 | AA72: 151140.29 | AB72: 162767.09 | AC72: 174393.89 | AD72: 186020.69 | AE72: 197647.49 | AF72: 209274.29 | AG72: 220901.09 | AH72: 232527.88 | AI72: 244154.68 | AJ72: 255781.48 | AK72: 267408.28 | AL72: 279035.08 | AM72: 290661.88 | AN72: 285624.43 | AO72: 280586.98 | AP72: 275549.53 | AQ72: 270512.07 | AR72: 265474.62 | AS72: 260437.17 | AT72: 255399.72 | AU72: 250362.27 | AV72: 245324.82 | AW72: 240287.37 | AX72: 235249.92 | AY72: 230212.47 | AZ72: 224641.7 | BA72: 219070.93 | BB72: 213500.16 | BC72: 207929.39 | BD72: 202358.62 | BE72: 196787.85 | BF72: 191217.08 | BG72: 185646.31 | BH72: 180075.54 | BI72: 174504.77 | BJ72: 168934 | BK72: 163363.23 | BL72: 149749.63 | BM72: 136136.03 | BN72: 122522.42 | BO72: 108908.82 | BP72: 95295.218 | BQ72: 81681.615 | BR72: 68068.013 | BS72: 54454.41 | BT72: 40840.808 | BU72: 27227.205 | BV72: 13613.603 | BW72: -1.9645086e-10
D73: Operational Technology Services (OTS) | H73: =AA73 -> 54206.694 | I73: =AM73 -> 80322.84 | J73: =AY73 -> 70452.886 | K73: =SUM(BK73) -> 65304.942 | L73: =BW73 -> 1.6370905e-11 | P73: 55290.828 | Q73: 55192.27 | R73: 55093.713 | S73: 54995.155 | T73: 54896.598 | U73: 54798.04 | V73: 54699.482 | W73: 54600.925 | X73: 54502.367 | Y73: 54403.809 | Z73: 54305.252 | AA73: 54206.694 | AB73: 56383.04 | AC73: 58559.385 | AD73: 60735.731 | AE73: 62912.076 | AF73: 65088.421 | AG73: 67264.767 | AH73: 69441.112 | AI73: 71617.458 | AJ73: 73793.803 | AK73: 75970.149 | AL73: 78146.494 | AM73: 80322.84 | AN73: 79500.344 | AO73: 78677.847 | AP73: 77855.351 | AQ73: 77032.855 | AR73: 76210.359 | AS73: 75387.863 | AT73: 74565.367 | AU73: 73742.871 | AV73: 72920.374 | AW73: 72097.878 | AX73: 71275.382 | AY73: 70452.886 | AZ73: 70023.891 | BA73: 69594.895 | BB73: 69165.9 | BC73: 68736.905 | BD73: 68307.909 | BE73: 67878.914 | BF73: 67449.919 | BG73: 67020.924 | BH73: 66591.928 | BI73: 66162.933 | BJ73: 65733.938 | BK73: 65304.942 | BL73: 59862.864 | BM73: 54420.785 | BN73: 48978.707 | BO73: 43536.628 | BP73: 38094.55 | BQ73: 32652.471 | BR73: 27210.393 | BS73: 21768.314 | BT73: 16326.236 | BU73: 10884.157 | BV73: 5442.0785 | BW73: 1.6370905e-11
D74: Security Services (SEC) | H74: =AA74 -> 54460.802 | I74: =AM74 -> 54902.262 | J74: =AY74 -> 54105.676 | K74: =SUM(BK74) -> 50476.503 | L74: =BW74 -> -3.092282e-11 | P74: 55550.018 | Q74: 55450.999 | R74: 55351.979 | S74: 55252.959 | T74: 55153.94 | U74: 55054.92 | V74: 54955.901 | W74: 54856.881 | X74: 54757.861 | Y74: 54658.842 | Z74: 54559.822 | AA74: 54460.802 | AB74: 54497.591 | AC74: 54534.379 | AD74: 54571.167 | AE74: 54607.956 | AF74: 54644.744 | AG74: 54681.532 | AH74: 54718.32 | AI74: 54755.109 | AJ74: 54791.897 | AK74: 54828.685 | AL74: 54865.474 | AM74: 54902.262 | AN74: 54835.88 | AO74: 54769.497 | AP74: 54703.115 | AQ74: 54636.733 | AR74: 54570.351 | AS74: 54503.969 | AT74: 54437.586 | AU74: 54371.204 | AV74: 54304.822 | AW74: 54238.44 | AX74: 54172.058 | AY74: 54105.676 | AZ74: 53803.244 | BA74: 53500.813 | BB74: 53198.382 | BC74: 52895.951 | BD74: 52593.52 | BE74: 52291.089 | BF74: 51988.658 | BG74: 51686.227 | BH74: 51383.796 | BI74: 51081.365 | BJ74: 50778.934 | BK74: 50476.503 | BL74: 46270.128 | BM74: 42063.752 | BN74: 37857.377 | BO74: 33651.002 | BP74: 29444.627 | BQ74: 25238.251 | BR74: 21031.876 | BS74: 16825.501 | BT74: 12619.126 | BU74: 8412.7505 | BV74: 4206.3752 | BW74: -3.092282e-11
D75: Devices* | H75: =AA75 -> 2606952.8 | I75: =AM75 -> 6540046.2 | J75: =AY75 -> 6129637.9 | K75: =SUM(BK75) -> 5352484.2 | L75: =BW75 -> 4020820.4 | P75: 3163687 | Q75: 3112851 | R75: 3062050.9 | S75: 3011289.1 | T75: 2960568.1 | U75: 2909890.9 | V75: 2859260.8 | W75: 2808681.2 | X75: 2758156.1 | Y75: 2707689.7 | Z75: 2657286.9 | AA75: 2606952.8 | AB75: 8252960.8 | AC75: 8096631.6 | AD75: 7940391.1 | AE75: 7784247.6 | AF75: 7628210.5 | AG75: 7472290.4 | AH75: 7316499.4 | AI75: 7160851.3 | AJ75: 7005362.2 | AK75: 6850050.1 | AL75: 6694936.5 | AM75: 6540046.2 | AN75: 8154154.1 | AO75: 7967239.6 | AP75: 7780652.8 | AQ75: 7594442.9 | AR75: 7408669.4 | AS75: 7223405 | AT75: 7038739.6 | AU75: 6854785.4 | AV75: 6671684.8 | AW75: 6489620.6 | AX75: 6308832 | AY75: 6129637.9 | AZ75: 8653246.7 | BA75: 8428245.6 | BB75: 8206762.1 | BC75: 7990115.3 | BD75: 7780378 | BE75: 7581005 | BF75: 7398214.8 | BG75: 7244444.6 | BH75: 7148714.5 | BI75: 7198084.3 | BJ75: 7827854 | BK75: 5352484.2 | BL75: 7380171.4 | BM75: 7132012.9 | BN75: 6883854.5 | BO75: 6635696.1 | BP75: 6387537.6 | BQ75: 6139379.2 | BR75: 5891220.7 | BS75: 5643062.3 | BT75: 5394903.8 | BU75: 5146745.4 | BV75: 4898587 | BW75: 4020820.4
D76: Others (including Supplier's investment in transition and transformation) | H76: =AA76 -> 3224749.6 | I76: =AM76 -> 2418562.2 | J76: =AY76 -> 1612374.8 | K76: =SUM(BK76) -> 806187.39 | L76: =BW76 -> 0 | P76: 0 | Q76: 0 | R76: 0 | S76: 0 | T76: 1400000 | U76: 1374545.5 | V76: 3304115.8 | W76: 3288242.5 | X76: 3272369.3 | Y76: 3256496 | Z76: 3240622.8 | AA76: 3224749.6 | AB76: 3157567.3 | AC76: 3090385 | AD76: 3023202.7 | AE76: 2956020.4 | AF76: 2888838.2 | AG76: 2821655.9 | AH76: 2754473.6 | AI76: 2687291.3 | AJ76: 2620109 | AK76: 2552926.7 | AL76: 2485744.5 | AM76: 2418562.2 | AN76: 2351379.9 | AO76: 2284197.6 | AP76: 2217015.3 | AQ76: 2149833 | AR76: 2082650.8 | AS76: 2015468.5 | AT76: 1948286.2 | AU76: 1881103.9 | AV76: 1813921.6 | AW76: 1746739.4 | AX76: 1679557.1 | AY76: 1612374.8 | AZ76: 1545192.5 | BA76: 1478010.2 | BB76: 1410827.9 | BC76: 1343645.7 | BD76: 1276463.4 | BE76: 1209281.1 | BF76: 1142098.8 | BG76: 1074916.5 | BH76: 1007734.2 | BI76: 940551.96 | BJ76: 873369.68 | BK76: 806187.39 | BL76: 739005.11 | BM76: 671822.83 | BN76: 604640.54 | BO76: 537458.26 | BP76: 470275.98 | BQ76: 403093.7 | BR76: 335911.41 | BS76: 268729.13 | BT76: 201546.85 | BU76: 134364.57 | BV76: 67182.283 | BW76: 0
D77: * Device related termination charges are based on the estimated refresh plan and shall be adjusted based on the actual refresh plan as per the formula defined in the Agreement.
A78: 3.4 | B78: Remaining value Sole-use Assets | H78: =SUMIFS(H80:H92,$F80:$F92,"<>Option") -> 0 | I78: =SUMIFS(I80:I92,$F80:$F92,"<>Option") -> 0 | J78: =SUMIFS(J80:J92,$F80:$F92,"<>Option") -> 0 | K78: =SUMIFS(K80:K92,$F80:$F92,"<>Option") -> 0 | L78: =SUMIFS(L80:L92,$F80:$F92,"<>Option") -> 0 | P78: Year 01 – month of the Term | AA78: Year-end 01 | AB78: Year 02 | AM78: Year-end 02 | AN78: Year 03 | AY78: Year-end 03 | AZ78: Year 04 | BK78: Year-end 04 | BL78: Year 05 | BW78: Year-end 05
D79: Note: remaining value for devices as operational expenses (PCs, printers) is governed by the 'Device-specific terms' chapter of Schedule 5.B (Pricing Principles) and therefore must NOT be included here. | H79: =SUMIFS(H80:H92,$F80:$F92,"Option") -> 0 | I79: =SUMIFS(I80:I92,$F80:$F92,"Option") -> 0 | J79: =SUMIFS(J80:J92,$F80:$F92,"Option") -> 0 | K79: =SUMIFS(K80:K92,$F80:$F92,"Option") -> 0 | L79: =SUMIFS(L80:L92,$F80:$F92,"Option") -> 0 | N79: Prices are at the END of that period | P79: 1 | Q79: 2 | R79: 3 | S79: 4 | T79: 5 | U79: 6 | V79: 7 | W79: 8 | X79: 9 | Y79: 10 | Z79: 11 | AA79: 12 | AB79: 13 | AC79: 14 | AD79: 15 | AE79: 16 | AF79: 17 | AG79: 18 | AH79: 19 | AI79: 20 | AJ79: 21 | AK79: 22 | AL79: 23 | AM79: 24 | AN79: 25 | AO79: 26 | AP79: 27 | AQ79: 28 | AR79: 29 | AS79: 30 | AT79: 31 | AU79: 32 | AV79: 33 | AW79: 34 | AX79: 35 | AY79: 36 | AZ79: 37 | BA79: 38 | BB79: 39 | BC79: 40 | BD79: 41 | BE79: 42 | BF79: 43 | BG79: 44 | BH79: 45 | BI79: 46 | BJ79: 47 | BK79: 48 | BL79: 49 | BM79: 50 | BN79: 51 | BO79: 52 | BP79: 53 | BQ79: 54 | BR79: 55 | BS79: 56 | BT79: 57 | BU79: 58 | BV79: 59 | BW79: 60
H80: =AA80 -> 0 | I80: =AM80 -> 0 | J80: =AY80 -> 0 | K80: =SUM(BK80) -> 0 | L80: =BW80 -> 0
D81: [ list all Assets that are marked Sole-use in Attachment 3.B3.L Asset Lists ] | H81: =AA81 -> 0 | I81: =AM81 -> 0 | J81: =AY81 -> 0 | K81: =SUM(BK81) -> 0 | L81: =BW81 -> 0
H82: =AA82 -> 0 | I82: =AM82 -> 0 | J82: =AY82 -> 0 | K82: =SUM(BK82) -> 0 | L82: =BW82 -> 0
H83: =AA83 -> 0 | I83: =AM83 -> 0 | J83: =AY83 -> 0 | K83: =SUM(BK83) -> 0 | L83: =BW83 -> 0
H84: =AA84 -> 0 | I84: =AM84 -> 0 | J84: =AY84 -> 0 | K84: =SUM(BK84) -> 0 | L84: =BW84 -> 0
H85: =AA85 -> 0 | I85: =AM85 -> 0 | J85: =AY85 -> 0 | K85: =SUM(BK85) -> 0 | L85: =BW85 -> 0
H86: =AA86 -> 0 | I86: =AM86 -> 0 | J86: =AY86 -> 0 | K86: =SUM(BK86) -> 0 | L86: =BW86 -> 0
H87: =AA87 -> 0 | I87: =AM87 -> 0 | J87: =AY87 -> 0 | K87: =SUM(BK87) -> 0 | L87: =BW87 -> 0
H88: =AA88 -> 0 | I88: =AM88 -> 0 | J88: =AY88 -> 0 | K88: =SUM(BK88) -> 0 | L88: =BW88 -> 0
H89: =AA89 -> 0 | I89: =AM89 -> 0 | J89: =AY89 -> 0 | K89: =SUM(BK89) -> 0 | L89: =BW89 -> 0
H90: =AA90 -> 0 | I90: =AM90 -> 0 | J90: =AY90 -> 0 | K90: =SUM(BK90) -> 0 | L90: =BW90 -> 0
H91: =AA91 -> 0 | I91: =AM91 -> 0 | J91: =AY91 -> 0 | K91: =SUM(BK91) -> 0 | L91: =BW91 -> 0
A93: 3.5 | B93: Exit Assistance | H93: =SUMIFS(H95:H103,$F95:$F103,"<>Option") -> 629264.84 | I93: =SUMIFS(I95:I103,$F95:$F103,"<>Option") -> 629264.84 | J93: =SUMIFS(J95:J103,$F95:$F103,"<>Option") -> 629264.84 | K93: =SUMIFS(K95:K103,$F95:$F103,"<>Option") -> 629264.84 | L93: =SUMIFS(L95:L103,$F95:$F103,"<>Option") -> 629264.84
C94: At Acceptance of Exit for Domain:
D95: Service Integration and Management (SIAM) | H95: 121392.75 | I95: 121392.75 | J95: 121392.75 | K95: 121392.75 | L95: 121392.75
D96: Service Desk Services (SDS) | H96: 39651.962 | I96: 39651.962 | J96: 39651.962 | K96: 39651.962 | L96: 39651.962
D97: Workplace Services (WPS) | H97: 155643.9 | I97: 155643.9 | J97: 155643.9 | K97: 155643.9 | L97: 155643.9
D98: Cloud and Infrastructure Services (CIS) | H98: 151662.18 | I98: 151662.18 | J98: 151662.18 | K98: 151662.18 | L98: 151662.18
D99: Operational Technology Services (OTS) | H99: 59959.149 | I99: 59959.149 | J99: 59959.149 | K99: 59959.149 | L99: 59959.149
D100: Security Services (SEC) | H100: 100954.91 | I100: 100954.91 | J100: 100954.91 | K100: 100954.91 | L100: 100954.91
H104: =SUMIFS(H69:H103,$F69:$F103,"Option") -> 0 | I104: =SUMIFS(I69:I103,$F69:$F103,"Option") -> 0 | J104: =SUMIFS(J69:J103,$F69:$F103,"Option") -> 0 | K104: =SUMIFS(K69:K103,$F69:$F103,"Option") -> 0 | L104: =SUMIFS(L69:L103,$F69:$F103,"Option") -> 0 | N104: Options for Termination Fee, Remaining value, and Exit Assistance

Sheet Service Requests
A1: Schedule 5.A (Pricing Sheet) – Service Requests (One-time Charges)
B3: Service Domain | G3: Monthly volume | I3: Price in
C4: Service Request | E4: Pricing unit | G4: estimate | I4: Year 01 | J4: Year 02 | K4: Year 03 | L4: Year 04 | M4: Year 05 | O4: Remarks
B6: Service Integration and Management (SIAM)
C7: On-board a Service Provider into the SIAM Service, including into common processes | G7: =1/12 -> 0.083333333 | I7: 58067.795 | J7: 58067.795 | K7: 58067.795 | L7: 58067.795 | M7: 58067.795
C8: Remove a Service Provider from the SIAM Service, including from the common processes | G8: =1/12 -> 0.083333333 | I8: 6701.839 | J8: 6701.839 | K8: 6701.839 | L8: 6701.839 | M8: 6701.839
C9: Project coordination, Service Provider management, and administration for a move or on-boarding of a Customer Location | G9: 0.5 | I9: 456.19567 | J9: 456.19567 | K9: 456.19567 | L9: 456.19567 | M9: 456.19567
B12: Service Desk Services (SDS)
I13: 0 | J13: 0 | K13: 0 | L13: 0 | M13: 0
B15: Workplace Services (WPS)
C16: Uplift for shipping joiner's laptop to specified address rather than to Customer Location | E16: Laptop | G16: =ROUND(8455/4/12*10%,) -> 18 | I16: 226.65234 | J16: 226.65234 | K16: 226.65234 | L16: 226.65234 | M16: 226.65234
C17: Create/update Medium Complexity MSI software package | E17: Per Package | G17: =1/12 -> 0.083333333 | I17: 571.31052 | J17: 571.31052 | K17: 571.31052 | L17: 571.31052 | M17: 571.31052
I18: 0 | J18: 0 | K18: 0 | L18: 0 | M18: 0
I19: 0 | J19: 0 | K19: 0 | L19: 0 | M19: 0
B21: Cloud and Infrastructure Services (CIS)
I22: 0 | J22: 0 | K22: 0 | L22: 0 | M22: 0
I23: 0 | J23: 0 | K23: 0 | L23: 0 | M23: 0
I24: 0 | J24: 0 | K24: 0 | L24: 0 | M24: 0
B26: Operational Technology Services (OTS)
C27: Installation of Claroty Sensor (Netherlands) | E27: Per Sensor | G27: =1/12 -> 0.083333333 | I27: 1252.4426 | J27: 1252.4426 | K27: 1252.4426 | L27: 1252.4426 | M27: 1252.4426
B30: Security Services (SEC)
I31: 0 | J31: 0 | K31: 0 | L31: 0 | M31: 0
C34: Note to Bidder: 'copy + insert copied' rows as needed. | G34: Subtotal at estimated volume | I34: =SUMPRODUCT($G6:$G33,I6:I33)*12 -> 118287.47 | J34: =SUMPRODUCT($G6:$G33,J6:J33)*12 -> 118287.47 | K34: =SUMPRODUCT($G6:$G33,K6:K33)*12 -> 118287.47 | L34: =SUMPRODUCT($G6:$G33,L6:L33)*12 -> 118287.47 | M34: =SUMPRODUCT($G6:$G33,M6:M33)*12 -> 118287.47
C36: Supplier will charge Customer
C37: the above-listed one-time Charges
C38: as the sole compensation for executing
C39: a Service Request, for every such request.

Sheet Demand Requests
A1: Schedule 5.A (Pricing Sheet) – Demand Requests (One-time Charges)
B3: Geography
C4: Service Component | F4: 2025 Hourly Rate | N4: 42 | P4: Estimate is calculated at this (fictious) volume of hours for all job titles and all skill levels
D5: Job Title / Labor Category 1) | F5: Level 1 | G5: Level 2 | H5: Level 3 | I5: Level 4 | J5: Level 5 | K5: Level 6 | L5: Level 7 | N5: Estimate
F6: Follow | G6: Assist | H6: Apply | I6: Enable | J6: Ensure, Advise | K6: Initiate, influence | L6: Set strategy, inspire, mobilize | P6: Remarks
B7: Typical Project locations – Long-term 2) work
B9: Customer IT headquarters: On-site
B10: Utrecht, Netherlands
C11: Change analysis and implementation
D12: Project management (PRMG) or Programme management (PGMG) | H12: 91.076091 | I12: 100.1837 | J12: 110.20207 | K12: 121.22228 | L12: 133.34451 | N12: =(IFERROR(AVERAGE(F12:L12),0)*intEstimateVolume) -> 4670.6406
D13: Portfolio, programme and project support (PROF) or Quality management (QUMG) | G13: 44.492123 | H13: 48.941335 | I13: 53.835469 | J13: 59.219016 | K13: 65.140918 | N13: =(IFERROR(AVERAGE(F13:L13),0)*intEstimateVolume) -> 2281.6824
D14: Business situation analysis (BUSA) or Requirements definition and management (REQM) | H14: 57.736585 | I14: 63.510243 | J14: 69.861268 | K14: 76.847394 | N14: =(IFERROR(AVERAGE(F14:L14),0)*intEstimateVolume) -> 2813.5326
C15: Strategy and architecture
D16: Enterprise and business architecture (STPL) | J16: 81.028569 | K16: 89.131426 | L16: 100.2102 | N16: =(IFERROR(AVERAGE(F16:L16),0)*intEstimateVolume) -> 3785.1828
D17: Technical / Solution architecture (ARCH) and Specialist advice (TECH) | I17: 64.587168 | J17: 71.045885 | K17: 78.150474 | N17: =(IFERROR(AVERAGE(F17:L17),0)*intEstimateVolume) -> 2992.9694
C18: Systems Development
D19: Systems design (DESN) or Network design (NTDS) or User experience design (HCEV) | H19: 63.673757 | I19: 70.041133 | J19: 77.045246 | N19: =(IFERROR(AVERAGE(F19:L19),0)*intEstimateVolume) -> 2950.6419
D20: Programming/software development (PROG) or Functional Testing (TEST) or Systems integration and build (SINT) | G20: 63.673757 | H20: 70.041133 | I20: 77.045246 | J20: 84.749771 | K20: 93.224748 | N20: =(IFERROR(AVERAGE(F20:L20),0)*intEstimateVolume) -> 3265.3711
C21: Delivery and operation
D22: Technology service management (ITMG) | J22: 67.344821 | K22: 74.079303 | L22: 81.487233 | N22: =(IFERROR(AVERAGE(F22:L22),0)*intEstimateVolume) -> 3120.759
D23: Application support (ASUP) or Infrastructure Operations (ITOP) or Network support (NTAS) or System software (SYSP) | G23: 57.736585 | H23: 63.510243 | I23: 69.861268 | J23: 76.847394 | N23: =(IFERROR(AVERAGE(F23:L23),0)*intEstimateVolume) -> 2813.5326
D24: Information security (SCTY) | H24: 59.41484 | I24: 65.356324 | J24: 71.891957 | K24: 79.081152 | L24: 86.989267 | N24: =(IFERROR(AVERAGE(F24:L24),0)*intEstimateVolume) -> 3046.9617
B26: Supplier delivery center in European Union / European Economic Area (EU/EEA): Near-shore
B27: Supplier location
D28: Poland
C29: Change analysis and implementation
D30: Project management (PRMG) or Programme management (PGMG) | H30: 70.623074 | I30: 77.685381 | J30: 85.453919 | K30: 93.999311 | L30: 103.39924 | N30: =(IFERROR(AVERAGE(F30:L30),0)*intEstimateVolume) -> 3621.7518
D31: Portfolio, programme and project support (PROF) or Quality management (QUMG) | G31: 26.95379 | H31: 29.649169 | I31: 32.614086 | J31: 35.875495 | K31: 40.175784 | N31: =(IFERROR(AVERAGE(F31:L31),0)*intEstimateVolume) -> 1388.2539
D32: Business situation analysis (BUSA) or Requirements definition and management (REQM) | H32: 34.380989 | I32: 37.819088 | J32: 41.600997 | K32: 59.339564 | N32: =(IFERROR(AVERAGE(F32:L32),0)*intEstimateVolume) -> 1817.9767
C33: Strategy and architecture
D34: Enterprise and business architecture (STPL) | J34: 58.215779 | K34: 64.037357 | L34: 89.313257 | N34: =(IFERROR(AVERAGE(F34:L34),0)*intEstimateVolume) -> 2961.9295
D35: Technical / Solution architecture (ARCH) and Specialist advice (TECH) | I35: 41.298751 | J35: 45.428626 | K35: 49.971489 | N35: =(IFERROR(AVERAGE(F35:L35),0)*intEstimateVolume) -> 1913.7841
C36: Systems Development
D37: Systems design (DESN) or Network design (NTDS) or User experience design (HCEV) | H37: 34.572631 | I37: 38.029894 | J37: 41.832884 | N37: =(IFERROR(AVERAGE(F37:L37),0)*intEstimateVolume) -> 1602.0957
D38: Programming/software development (PROG) or Functional Testing (TEST) or Systems integration and build (SINT) | G38: 34.572631 | H38: 38.029894 | I38: 41.832884 | J38: 46.016172 | K38: 50.617789 | N38: =(IFERROR(AVERAGE(F38:L38),0)*intEstimateVolume) -> 1772.9827
C39: Delivery and operation
D40: Technology service management (ITMG) | J40: 52.86158 | K40: 58.147738 | L40: 63.962511 | N40: =(IFERROR(AVERAGE(F40:L40),0)*intEstimateVolume) -> 2449.6056
D41: Application support (ASUP) or Infrastructure Operations (ITOP) or Network support (NTAS) or System software (SYSP) | G41: 34.380989 | H41: 37.819088 | I41: 41.600997 | J41: 45.761096 | N41: =(IFERROR(AVERAGE(F41:L41),0)*intEstimateVolume) -> 1675.4028
D42: Information security (SCTY) | H42: 53.027371 | I42: 58.330108 | J42: 64.163119 | K42: 70.579431 | L42: 77.637374 | N42: =(IFERROR(AVERAGE(F42:L42),0)*intEstimateVolume) -> 2719.3942
B44: Supplier delivery center off-shore
B45: Supplier location
D46: India
C47: Change analysis and implementation
D48: Project management (PRMG) or Programme management (PGMG) | H48: 14.54732 | I48: 17.456784 | J48: 20.94814 | K48: 26.1854 | L48: 31.42248 | N48: =(IFERROR(AVERAGE(F48:L48),0)*intEstimateVolume) -> 928.70503
D49: Portfolio, programme and project support (PROF) or Quality management (QUMG) | G49: 11.393343 | H49: 13.672011 | I49: 16.406414 | J49: 19.687696 | K49: 20.959724 | N49: =(IFERROR(AVERAGE(F49:L49),0)*intEstimateVolume) -> 689.80118
D50: Business situation analysis (BUSA) or Requirements definition and management (REQM) | H50: 13.973674 | I50: 16.768408 | J50: 20.12209 | K50: 25.33614 | N50: =(IFERROR(AVERAGE(F50:L50),0)*intEstimateVolume) -> 800.10328
C51: Strategy and architecture
D52: Enterprise and business architecture (STPL) | J52: 38.817278 | K52: 46.580734 | L52: 62.717032 | N52: =(IFERROR(AVERAGE(F52:L52),0)*intEstimateVolume) -> 2073.6106
D53: Technical / Solution architecture (ARCH) and Specialist advice (TECH) | I53: 28.8258 | J53: 34.59096 | K53: 41.509151 | N53: =(IFERROR(AVERAGE(F53:L53),0)*intEstimateVolume) -> 1468.9627
C54: Systems Development
D55: Systems design (DESN) or Network design (NTDS) or User experience design (HCEV) | H55: 14.352814 | I55: 17.223376 | J55: 20.668052 | N55: =(IFERROR(AVERAGE(F55:L55),0)*intEstimateVolume) -> 731.41939
D56: Programming/software development (PROG) or Functional Testing (TEST) or Systems integration and build (SINT) | G56: 8.5123225 | H56: 14.352814 | I56: 17.223376 | J56: 20.668052 | K56: 24.801662 | N56: =(IFERROR(AVERAGE(F56:L56),0)*intEstimateVolume) -> 718.6891
C57: Delivery and operation
D58: Technology service management (ITMG) | J58: 10.153655 | K58: 12.184386 | L58: 14.621263 | N58: =(IFERROR(AVERAGE(F58:L58),0)*intEstimateVolume) -> 517.43027
D59: Application support (ASUP) or Infrastructure Operations (ITOP) or Network support (NTAS) or System software (SYSP) | G59: 8.4411963 | H59: 13.973674 | I59: 16.768408 | J59: 20.12209 | N59: =(IFERROR(AVERAGE(F59:L59),0)*intEstimateVolume) -> 622.70637
D60: Information security (SCTY) | H60: 11.20087 | I60: 13.441044 | J60: 16.129252 | K60: 19.355103 | L60: 23.226124 | N60: =(IFERROR(AVERAGE(F60:L60),0)*intEstimateVolume) -> 700.1601
B63: On-site Services
C64: Provisioning of the following role, in any Customer Location in the countries listed below. | F64: Ad-hoc | G64: Ad-hoc | H64: Ad-hoc | I64: Ad-hoc | J64: Long-term | K64: Long-term | M64: 2) 3)
D65: Systems installation and removal (HSIN) | F65: Single ticket dispatch Next Business Day (NBD) | G65: Single ticket dispatch Five Business Days (5BD) | H65: Emergency single ticket dispatch Same Business Day (SBD) | I65: Single ticket dispatch: additional hour | J65: Scheduled Half Day | K65: Scheduled Full Day
B66: Australia | F66: 54.7902 | G66: 51.7463 | H66: 57.8341 | I66: Additional hour is equal to 1st hr of dispatch ticket for the same SLA Eg. For NBD ticket, 2nd hr price = 1st hr price for NBD | J66: 136.9755 | K66: 273.951 | N66: =(IFERROR(AVERAGE(F66:K66),0)*intEstimateVolume) -> 4832.4956
B67: Austria | F67: 127.93 | G67: 127.93 | H67: 178.96 | I67: Additional hour is equal to 1st hr of dispatch ticket for the same SLA Eg. For NBD ticket, 2nd hr price = 1st hr price for NBD | J67: 289.6 | K67: 398.03 | N67: =(IFERROR(AVERAGE(F67:K67),0)*intEstimateVolume) -> 9428.58
B68: Belgium | F68: 84 | G68: 74.4 | H68: 98.4 | I68: Additional hour is equal to 1st hr of dispatch ticket for the same SLA Eg. For NBD ticket, 2nd hr price = 1st hr price for NBD | J68: 244.8 | K68: 414 | N68: =(IFERROR(AVERAGE(F68:K68),0)*intEstimateVolume) -> 7691.04
B69: Brazil | F69: 62.010337 | G69: 62.010337 | H69: 67.158364 | I69: Additional hour is equal to 1st hr of dispatch ticket for the same SLA Eg. For NBD ticket, 2nd hr price = 1st hr price for NBD | J69: 148.82481 | K69: 198.43308 | N69: =(IFERROR(AVERAGE(F69:K69),0)*intEstimateVolume) -> 4522.8701
B70: Bulgaria | F70: 70.865526 | G70: 65.874996 | H70: 88.831434 | I70: Additional hour is equal to 1st hr of dispatch ticket for the same SLA Eg. For NBD ticket, 2nd hr price = 1st hr price for NBD | J70: 141.73105 | K70: 241.54165 | N70: =(IFERROR(AVERAGE(F70:K70),0)*intEstimateVolume) -> 5114.2951
B71: China | F71: 31.828165 | G71: 32.50536 | H71: 44.017675 | I71: Additional hour is equal to 1st hr of dispatch ticket for the same SLA Eg. For NBD ticket, 2nd hr price = 1st hr price for NBD | J71: 94.265544 | K71: 178.10228 | N71: =(IFERROR(AVERAGE(F71:K71),0)*intEstimateVolume) -> 3198.0398
B72: Czech Republic | F72: 77.852268 | G72: 72.861738 | H72: 97.814388 | I72: Additional hour is equal to 1st hr of dispatch ticket for the same SLA Eg. For NBD ticket, 2nd hr price = 1st hr price for NBD | J72: 171.67423 | K72: 291.44695 | N72: =(IFERROR(AVERAGE(F72:K72),0)*intEstimateVolume) -> 5977.8565
B73: Denmark | F73: 148.627 | G73: 141.16802 | H73: 255.53898 | I73: Additional hour is equal to 1st hr of dispatch ticket for the same SLA Eg. For NBD ticket, 2nd hr price = 1st hr price for NBD | J73: 210.92326 | K73: 421.84652 | N73: =(IFERROR(AVERAGE(F73:K73),0)*intEstimateVolume) -> 9896.0717
B74: France | F74: 163.18 | G74: 163.18 | H74: 163.18 | I74: Additional hour is equal to 1st hr of dispatch ticket for the same SLA Eg. For NBD ticket, 2nd hr price = 1st hr price for NBD | J74: 302.1 | K74: 404.16 | N74: =(IFERROR(AVERAGE(F74:K74),0)*intEstimateVolume) -> 10044.72
B75: Georgia | F75: 80.487268 | G75: 75.376965 | H75: 100.92848 | I75: Additional hour is equal to 1st hr of dispatch ticket for the same SLA Eg. For NBD ticket, 2nd hr price = 1st hr price for NBD | J75: 196.74665 | K75: 333.44725 | N75: =(IFERROR(AVERAGE(F75:K75),0)*intEstimateVolume) -> 6610.6876
B76: Germany | F76: 136.51 | G76: 136.51 | H76: 136.51 | I76: Additional hour is equal to 1st hr of dispatch ticket for the same SLA Eg. For NBD ticket, 2nd hr price = 1st hr price for NBD | J76: 308.9 | K76: 376.94 | N76: =(IFERROR(AVERAGE(F76:K76),0)*intEstimateVolume) -> 9201.108
B77: Greece | F77: 80.82 | G77: 76.64 | H77: 94.74 | I77: Additional hour is equal to 1st hr of dispatch ticket for the same SLA Eg. For NBD ticket, 2nd hr price = 1st hr price for NBD | J77: 168.91892 | K77: 267.45495 | N77: =(IFERROR(AVERAGE(F77:K77),0)*intEstimateVolume) -> 5784.0205
... B106: Vietnam | F106: 32.937498 | G106: 30.941286 | H106: 34.93371 | I106: Additional hour is equal to 1st hr of dispatch ticket for the same SLA Eg. For NBD ticket, 2nd hr price = 1st hr price for NBD | J106: 64.87689 | K106: 129.75378 | N106: =(IFERROR(AVERAGE(F106:K106),0)*intEstimateVolume) -> 2464.9226
L109: Subtotal at estimated volume | N109: =SUM(N7:N108) -> 299497.9
C110: 1) Job Title / Labor Category
D111: The 'Skills Framework for the Information Age' (SFIA) is used to select Personnel profiles anticipated to be required, see
D112: https://sfia-online.org/en/sfia-9
D114: If Bidder wishes to propose an alternative system – possibly more aligned to Bidder's internal terminology) than such proposal is permitted, under these conditions:
D115: • The system uses a 'skills' and 'level' system that is based on objectively measurable qualities of Personnel, i.e. not just 'years in the job' or 'junior/medior/senior'.
D116: • Bidder endeavors to realistically match the skills and levels requested.
D117: • The system's 'skills' job descriptions and 'levels' quality description are shared with Customer during the Tender for Customer to assess.
C119: 2) Long-term
D120: One or more days per week for multiple weeks.
C122: 3) Response times are during Business Hours
D123: • NBD means that the visit will be at the latest on the next Business Day after
D124: it was requested (for example request on Monday, visit on Tuesday).
D125: • 5BD means that the visit will be at the latest on the fifth Business Day after
D126: it was requested (for example request on Monday, visit latest next Monday).
D127: • SBD means that the visit will be during the same Business Day as it was requested
D128: • Half day: Half a work day 'shift' of work at Customer Location
D129: • Full day: Full work day 'shift' of work at Customer Location

Sheet Optional Pricing
A1: Optional Items | C1: Year 1 | D1: Year 2 | E1: Year 3 | F1: Year 4 | G1: Year 5 | H1: Total | I1: Remarks
A3: DLP | C3: 6865.7795 | D3: 11299.111 | E3: 10734.156 | F3: 10197.448 | G3: 9687.5756 | H3: =SUM(C3:G3) -> 48784.07 | I3: Indicative price proposed as per Diego's request
A5: Hardware Maintenance - Storage | C5: 6343.6031 | D5: 10439.758 | E5: 9917.7704 | F5: 9421.8818 | G5: 8950.7877 | H5: =SUM(C5:G5) -> 45073.801
A7: Total | C7: =SUM(C3:C6) -> 13209.383 | D7: =SUM(D3:D6) -> 21738.87 | E7: =SUM(E3:E6) -> 20651.926 | F7: =SUM(F3:F6) -> 19619.33 | G7: =SUM(G3:G6) -> 18638.363 | H7: =SUM(H3:H6) -> 93857.871
